Workbook
Name Base: 'Caisse à Plateau'!$C$35
Name Base: 'Caisse Garde-Meubles'!#REF!
Name Base: 'Claire-Voie'!$C$30
Name Base: 'Objet 1'!$C$36
Name Base: 'Wrapp Barré'!$C$27
Name Base_OAV: ' Objet Anti Vibratoire'!$C$33
Name Base1: '1 Caisson Objet'!$C$25
Name Base1: '6 Caissons Objets'!$C$22
Name Base1: 'Objet 2 à 6'!$C$29
Name Base2: '1 Caisson Objet'!#REF!
Name Base2: '6 Caissons Objets'!$C$32
Name Base2: 'Objet 2 à 6'!$C$36
Name Base3: '1 Caisson Objet'!#REF!
Name Base3: '6 Caissons Objets'!$C$42
Name Base3: 'Objet 2 à 6'!$C$43
Name Base4: '1 Caisson Objet'!$H$25
Name Base4: '6 Caissons Objets'!$H$22
Name Base4: 'Objet 2 à 6'!$H$29
Name Base5: '1 Caisson Objet'!#REF!
Name Base5: '6 Caissons Objets'!$H$32
Name Base5: 'Objet 2 à 6'!$H$36
Name Base6: '1 Caisson Objet'!#REF!
Name Base6: '6 Caissons Objets'!$H$42
Name Base6: 'Objet 2 à 6'!$H$43
Name BaseP: 'Caisse à Plateau'!$C$32
Name BaseP: Palette!$C$21
Name Carton: '[1]Prix Matiere'!$J$11
Name Carton: '[1]Prix Matiere'!$J$11
Name Carton: '[1]Prix Matiere'!$J$11
Name Carton: '[1]Prix Matiere'!$J$11
Name Carton: '[1]Prix Matiere'!$J$11
Name Carton: '[1]Prix Matiere'!$J$11
Name Carton: '[1]Prix Matiere'!$J$11
Name Carton: '[1]Prix Matiere'!$J$11
Name Carton: '[1]Prix Matiere'!$J$11
Name Carton: '[1]Prix Matiere'!$J$11
Name Carton: '[1]Prix Matiere'!$J$11
Name Carton: '[1]Prix Matiere'!$J$11
Name Carton: 'Prix Matiere'!$J$11
Name CCBase1: 'Caisse Cuvette'!$C$28
Name CCBase2: 'Caisse Cuvette'!$C$35
Name CCBase3: 'Caisse Cuvette'!$C$42
Name CCBase4: 'Caisse Cuvette'!$I$28
Name CCBase5: 'Caisse Cuvette'!$I$35
Name CCBase6: 'Caisse Cuvette'!$I$42
Name CCType_de_mousse1: 'Caisse Cuvette'!$F$26
Name CCType_de_mousse2: 'Caisse Cuvette'!$F$33
Name CCType_de_mousse3: 'Caisse Cuvette'!$F$40
Name CCType_de_mousse4: 'Caisse Cuvette'!$L$26
Name CCType_de_mousse5: 'Caisse Cuvette'!$L$33
Name CCType_de_mousse6: 'Caisse Cuvette'!$L$40
Name Dimensions_intérieures_CP_15_hauteur: 'Caisse à Plateau'!$E$92
Name Dimensions_intérieures_CP_15_hauteur: 'Caisse Cuvette'!$E$95
Name Dimensions_intérieures_CP_15_hauteur: 'Caisse Garde-Meubles'!#REF!
Name Dimensions_intérieures_CP_15_hauteur: 'Claire-Voie'!$E$58
Name Dimensions_intérieures_CP_15_hauteur: 'Objet 1'!$E$93
Name Dimensions_intérieures_CP_15_hauteur: 'Objet 2 à 6'!$E$109
Name Dimensions_intérieures_CP_15_hauteur: Tapisserie!$E$90
Name Dimensions_intérieures_CP_15_hauteur: 'Wrapp Barré'!$E$54
Name Dimensions_intérieures_CP_15_hauteur_OAV: ' Objet Anti Vibratoire'!$E$98

Sheet T1
A1: Caisse Tableau
E3: =IF(C19="Boulons et platines","Boulons et platines",0) -> 0 | F3: =IF(E3="Boulons et Platines","Nbre de Trous",0) -> 0 | G3: =IF(E3="Boulons et Platines","Dim du Bord",0) -> 0
E4: =IF(C19="Vis bois",0,"Trous dans la Longueur") -> 0 | F4: =IF(E4=0,0,IF(C58<100,2,IF(C58<150,3,IF(C58<200,4,IF(C58<250,5,IF(C58<300,6,7)))))) -> 0 | G4: =IF(F4=0,0,IF(F4=3,0,(($C$58-32)/(F4-1))+16)) -> 0
E5: =IF(F4=6,"2ème Trou",IF(F4=7,"2ème Trou",0)) -> 0 | G5: =IF(E5=0,0,G4+G4-16) -> 0
E6: =IF(C19="Vis bois",0,"Trous dans la Hauteur") -> 0 | F6: =IF(E6=0,0,IF(D58<100,2,IF(D58<150,3,IF(D58<200,4,IF(D58<250,5,IF(D58<310,6,7)))))) -> 0 | G6: =IF(F6=0,0,IF(F6=3,0,(($D$58-32)/(F6-1))+16)) -> 0
E7: =IF(F6=6,"2ème Trou",IF(F6=7,"2ème Trou",0)) -> 0 | G7: =IF(E7=0,0,G6+G6-16) -> 0
B9: N° de dossier | C9: 1 | E9: Responsable Dossier | F9: Grégory MORA
B10: Ville de destination | C10: 1 | E10: Client | F10: ESI
B11: Caisse N° | C11: 1 | E11: Délai | F11: 1
B13: Type de Contreplaqué | C13: Peuplier 15 mm
B15: Barres | C15: Pin raboté 4 faces | E15: Garnissage Valsem | F15: Oui
B17: Type d'isolant | C17: Aucun
B19: Fermeture | C19: Vis bois | E19: Peinture | F19: Non
E20: =IF(F19="Oui","Type de Peinture",0) -> 0 | F20: =IF(F19="Non",0,VLOOKUP(F10,'Infos Clients'!B2:E10,4)) -> 0
B21: Poignées | C21: Bois | E21: Tyvek | F21: Non
B23: Skis | C23: Skis | E23: Option Calage | F23: Aucun
E25: Epaisseur Mousse | F25: PU 50 mm
B26: =IF(F23="Aucun"," ",F23) | D26: =IF(F21="Oui","+",0) -> 0 | E26: =IF(F21="Oui","Mousse Garnie Tyvek",0) -> 0
B28: =IF(B34="Aucun","Dimensions intérieures utiles","Dimensions de l'œuvre") -> Dimensions de l'œuvre | C28: Longueur | D28: Epaisseur | E28: Hauteur
C29: 100 | D29: 5 | E29: 100
B33: Type de calage
B34: Bandes de mousse
C35: Largeur | D35: Longueur | E35: Epaisseur | F35: Quantité
B36: Dessus | C36: 5
B37: Dessous | C37: 5
B38: Ethafoam 50 mm | C38: =+IF(C29=0,0,IF(C29>70,12,6)) -> 12 | F38: =IF(C29>300,6,IF(C29>250,5,IF(C29>200,4,IF(C29>150,3,IF(C29>120,3,2))))) -> 2 | G38: ,
B39: Rattrapage
B41: Remplissage 1
B42: Remplissage 2
B44: Dimensions intérieures caisse | C44: =C29+VLOOKUP(C17,B142:Q148,2)+VLOOKUP(B34,B169:M177,2) -> 110.2 | D44: =D29+VLOOKUP($B$34,B169:M177,3)+VLOOKUP($C$17,B142:Q148,3) -> 16 | E44: =E29+VLOOKUP($B$34,B169:M177,4)+VLOOKUP($C$17,B142:Q148,4) -> 110.2 | F44: Prix d'achat Arckx
B46: Dimensions extérieures caisse | C46: =C44+VLOOKUP(C21,B153:C156,2)+VLOOKUP(C13,B132:F134,5)*2+VLOOKUP(C15,B136:E137,4)*2 -> 121.6 | D46: =IF(OR($F$23="Aucun",$F$23="Stabilisateur"),$D$44+VLOOKUP($C$13,$B$132:$F$134,4)*2+VLOOKUP($C$15,$B$136:$E$137,4)*2+0.5,$E$44+VLOOKUP($C$13,$B$132:$F$134,5)*2+VLOOKUP($C$15,$B$136:$E$137,4)*2) -> 23.7 | E46: =IF(OR($F$23="Aucun",$F$23="Stabilisateur"),$E$44+VLOOKUP($C$13,$B$132:$F$134,5)*2+VLOOKUP($C$15,$B$136:$E$137,4)*2+VLOOKUP($C$23,$B$185:$C$187,2),$D$44+VLOOKUP($C$13,$B$132:$F$134,4)*2+VLOOKUP($C$15,$B$136:$E$137,4)*2+VLOOKUP($C$23,$B$185:$C$187,2)+VLOOKUP($F$23,$B$158:$E$161,4)+0.5) -> 120.4 | F46: =ROUNDUP(C129,0) -> 386
B48: Poids de la Caisse | C48: =Q121 -> 40.93123 | D48: Kg | E48: Bilan Carbone
B49: Minutes de Production | C49: =D123 -> 120.02949 | D49: Min | E49: =R121 -> 29.294938
B52: Commentaires
Q56: Poids en Kg | R56: CO²
F57: Quantité
B58: Grand côtés | C58: =IF(C44=0,0,C44+2*(VLOOKUP(E59,B132:E134,4)+VLOOKUP(C15,B136:E137,4))) -> 117.4 | D58: =IF(E44=0,0,E44+2*(VLOOKUP(E60,B132:E134,4)+VLOOKUP(C15,B136:E137,4))) -> 117.4 | E58: =VLOOKUP($C$13,$B$132:$E$134,2) -> Peuplier 15 mm | F58: 2 | J58: =IF(C58=0,0,(C58/100)*(D58/100)*F58) -> 2.756552 | K58: =J58/0.8 -> 3.44569 | L58: =IF(E58=0,0,VLOOKUP(E58,'Prix Matiere'!$A$4:$J$65,10)) -> 16.895876 | M58: =L58*K58-IF($F$15="Non",K58*0.75,0) -> 58.217952 | N58: =IF(J58=0,0,IF($F$15="Oui",(7.0924*J58)+15,(6.0924*J58)+10)) -> 34.550569 | O58: =N58*MinuteMO -> 29.367984 | Q58: =IF(J58=0,0,J58*VLOOKUP(E58,'Prix Matiere'!$A$4:$L$60,12)) -> 18.193243 | R58: =IF(J58=0,0,Q58*VLOOKUP(E58,'Prix Matiere'!$A$4:$L$60,11)) -> 14.063377
B59: Dessus dessous | C59: =C58 -> 117.4 | D59: =D44 -> 16 | E59: =VLOOKUP($C$13,$B$132:$E$134,3) -> Peuplier 15 mm | F59: 2 | J59: =IF(C59=0,0,(C59/100)*(D59/100)*F59) -> 0.37568 | K59: =J59/0.8 -> 0.4696 | L59: =IF(E59=0,0,VLOOKUP(E59,'Prix Matiere'!$A$4:$J$65,10)) -> 16.895876 | M59: =L59*K59-IF($F$15="Non",K59*0.75,0) -> 7.9343035 | N59: =IF(J59=0,0,IF($F$15="Oui",(7.0924*J59)+15,(6.0924*J59)+10)) -> 17.664473 | O59: =N59*MinuteMO -> 15.014802 | Q59: =IF(J59=0,0,J59*VLOOKUP(E59,'Prix Matiere'!$A$4:$L$60,12)) -> 2.479488 | R59: =IF(J59=0,0,Q59*VLOOKUP(E59,'Prix Matiere'!$A$4:$L$60,11)) -> 1.9166442
B60: Bouts | C60: =E44 -> 110.2 | D60: =D44 -> 16 | E60: =VLOOKUP($C$13,$B$132:$E$134,3) -> Peuplier 15 mm | F60: 2 | J60: =IF(C60=0,0,(C60/100)*(D60/100)*F60) -> 0.35264 | K60: =J60/0.8 -> 0.4408 | L60: =IF(E60=0,0,VLOOKUP(E60,'Prix Matiere'!$A$4:$J$65,10)) -> 16.895876 | M60: =L60*K60-IF($F$15="Non",K60*0.75,0) -> 7.4477023 | N60: =IF(J60=0,0,IF($F$15="Oui",(7.0924*J60)+15,(6.0924*J60)+10)) -> 17.501064 | O60: =N60*MinuteMO -> 14.875904 | Q60: =IF(J60=0,0,J60*VLOOKUP(E60,'Prix Matiere'!$A$4:$L$60,12)) -> 2.327424 | R60: =IF(J60=0,0,Q60*VLOOKUP(E60,'Prix Matiere'!$A$4:$L$60,11)) -> 1.7990988
J61: =IF(C61=0,0,(C61/100)*(D61/100)*F61) -> 0 | K61: =J61/0.8 -> 0
J62: =IF(C62=0,0,(C62/100)*(D62/100)*F62) -> 0 | K62: =J62/0.8 -> 0
B63: Barres de GC | C63: =C58 -> 117.4 | D63: =IF(D58>80,9.4,7) -> 9.4 | E63: =IF($C$15="Pin raboté 4 faces","Barres 21 R4F","Barres 19 mm") -> Barres 21 R4F | F63: 4 | J63: =IF(C63=0,0,(C63/100)*(D63/100)*F63) -> 0.441424 | K63: =J63/0.8 -> 0.55178 | L63: =IF(E63=0,0,VLOOKUP(E63,'Prix Matiere'!$A$4:$J$65,10)) -> 18.969072 | M63: =L63*K63 -> 10.466755 | N63: =IF(J63=0,0,1+(11*J63)) -> 5.855664 | O63: =N63*MinuteMO -> 4.9773144 | Q63: =IF(J63=0,0,J63*VLOOKUP(E63,'Prix Matiere'!$A$4:$L$60,12)) -> 4.41424 | R63: =IF(J63=0,0,Q63*VLOOKUP(E63,'Prix Matiere'!$A$4:$L$60,11)) -> 2.1364922
B64: Remplis GC | C64: =IF(D58=0,0,D58-2*D63) -> 98.6 | D64: =D63 -> 9.4 | E64: =IF($C$15="Pin raboté 4 faces","Barres 21 R4F","Barres 19 mm") -> Barres 21 R4F | F64: =4 -> 4 | J64: =IF(C64=0,0,(C64/100)*(D64/100)*F64) -> 0.370736 | K64: =J64/0.8 -> 0.46342 | L64: =IF(E64=0,0,VLOOKUP(E64,'Prix Matiere'!$A$4:$J$65,10)) -> 18.969072 | M64: =L64*K64 -> 8.7906474 | N64: =IF(J64=0,0,1+(11*J64)) -> 5.078096 | O64: =N64*MinuteMO -> 4.3163816 | Q64: =IF(J64=0,0,J64*VLOOKUP(E64,'Prix Matiere'!$A$4:$L$60,12)) -> 3.70736 | R64: =IF(J64=0,0,Q64*VLOOKUP(E64,'Prix Matiere'!$A$4:$L$60,11)) -> 1.7943622
B65: Dessus / Dessous | C65: =C63 -> 117.4 | D65: =IF($D$44<14.4,$D$44,7) -> 7 | E65: =IF($C$15="Pin raboté 4 faces","Barres 21 R4F","Barres 19 mm") -> Barres 21 R4F | F65: =IF(D44<14.4,2,4) -> 4 | J65: =IF(C65=0,0,(C65/100)*(D65/100)*F65) -> 0.32872 | K65: =J65/0.8 -> 0.4109 | L65: =IF(E65=0,0,VLOOKUP(E65,'Prix Matiere'!$A$4:$J$65,10)) -> 18.969072 | M65: =L65*K65 -> 7.7943918 | N65: =IF(J65=0,0,1+(11*J65)) -> 4.61592 | O65: =N65*MinuteMO -> 3.923532 | Q65: =IF(J65=0,0,J65*VLOOKUP(E65,'Prix Matiere'!$A$4:$L$60,12)) -> 3.2872 | R65: =IF(J65=0,0,Q65*VLOOKUP(E65,'Prix Matiere'!$A$4:$L$60,11)) -> 1.5910048
B66: =C23 -> Skis | C66: =IF(C58=0,0,IF(B66="Skis",C58-10,IF(B66="10 dessous en semelles",D46,IF(B66="10 dessous en skis",(C63-70)/2)))) -> 107.4 | D66: =IF($F$10="BOVIS",9.4,7) -> 7 | E66: =IF($C$23="Skis","Barres 30 R4F","Semelles R4F") -> Barres 30 R4F | F66: =IF(B66="Skis",2,IF(B66="10 dessous en semelles",2,F65)) -> 2 | J66: =IF(C66=0,0,(C66/100)*(D66/100)*F66) -> 0.15036 | K66: =J66/0.8 -> 0.18795 | L66: =IF(E66=0,0,VLOOKUP(E66,'Prix Matiere'!$A$4:$J$65,10)) -> 45.43299 | M66: =L66*K66 -> 8.5391304 | N66: =IF(J66=0,0,1+(11*J66)) -> 2.65396 | O66: =N66*MinuteMO -> 2.255866 | Q66: =IF(J66=0,0,J66*VLOOKUP(E66,'Prix Matiere'!$A$4:$L$60,12)) -> 1.5036 | R66: =IF(J66=0,0,Q66*VLOOKUP(E66,'Prix Matiere'!$A$4:$L$60,11)) -> 0.7277424
B67: Longueur Bouts | C67: =IF(D44<14.4,0,D44) -> 16 | D67: =IF(D44<14.4,0,D63) -> 9.4 | E67: =IF($C$15="Pin raboté 4 faces","Barres 21 R4F","Barres 19 mm") -> Barres 21 R4F | F67: =IF(D44<14.4,0,4) -> 4 | J67: =IF(C67=0,0,(C67/100)*(D67/100)*F67) -> 0.06016 | K67: =J67/0.8 -> 0.0752 | L67: =IF(E67=0,0,VLOOKUP(E67,'Prix Matiere'!$A$4:$J$65,10)) -> 18.969072 | M67: =L67*K67 -> 1.4264742 | N67: =IF(J67=0,0,1+(11*J67)) -> 1.66176 | O67: =N67*MinuteMO -> 1.412496 | Q67: =IF(J67=0,0,J67*VLOOKUP(E67,'Prix Matiere'!$A$4:$L$60,12)) -> 0.6016 | R67: =IF(J67=0,0,Q67*VLOOKUP(E67,'Prix Matiere'!$A$4:$L$60,11)) -> 0.2911744
B68: Hauteur Bouts | C68: =IF(D44<14.4,E44,C60-2*D67) -> 91.4 | D68: =IF($D$44<14.4,$D$44,IF($D$44<20,5,7)) -> 5 | E68: =IF($C$15="Pin raboté 4 faces","Barres 21 R4F","Barres 19 mm") -> Barres 21 R4F | F68: =IF(D44<14.4,2,4) -> 4 | J68: =IF(C68=0,0,(C68/100)*(D68/100)*F68) -> 0.1828 | K68: =J68/0.8 -> 0.2285 | L68: =IF(E68=0,0,VLOOKUP(E68,'Prix Matiere'!$A$4:$J$65,10)) -> 18.969072 | M68: =L68*K68 -> 4.334433 | N68: =IF(J68=0,0,1+(11*J68)) -> 3.0108 | O68: =N68*MinuteMO -> 2.55918 | Q68: =IF(J68=0,0,J68*VLOOKUP(E68,'Prix Matiere'!$A$4:$L$60,12)) -> 1.828 | R68: =IF(J68=0,0,Q68*VLOOKUP(E68,'Prix Matiere'!$A$4:$L$60,11)) -> 0.884752
B69: =IF(D44<14.4,0,IF(C21="Bois","Poignées",IF(C21="Métal x 2 sur bouts","Supports poignées",0))) -> Poignées | C69: =IF(B69="Poignées",D60+VLOOKUP(C13,B132:E134,4)*2+4.2,IF(B69="Supports poignées",D60-2*D68,0)) -> 23.2 | D69: =IF(B69="Poignées",7,IF(B69="Supports poignées",9.4,0)) -> 7 | E69: Barres 21 R4F | F69: =IF(B69=0,0,2) -> 2 | J69: =IF(C69=0,0,(C69/100)*(D69/100)*F69) -> 0.03248 | K69: =J69/0.8 -> 0.0406 | L69: =IF(E69=0,0,VLOOKUP(E69,'Prix Matiere'!$A$4:$J$65,10)) -> 18.969072 | M69: =L69*K69 -> 0.77014433 | N69: =IF(J69=0,0,1+(11*J69)) -> 1.35728 | O69: =N69*MinuteMO -> 1.153688 | Q69: =IF(J69=0,0,J69*VLOOKUP(E69,'Prix Matiere'!$A$4:$L$60,12)) -> 0.3248 | R69: =IF(J69=0,0,Q69*VLOOKUP(E69,'Prix Matiere'!$A$4:$L$60,11)) -> 0.1572032
B71: Mousse 1
B72: GC | C72: =IF(F72=0,0,C44) -> 0 | D72: =IF(F72=0,0,E76+VLOOKUP($C$17,B142:Q148,5)) -> 0 | E72: =VLOOKUP($C$17,B142:Q148,6) -> 0 | F72: =VLOOKUP($C$17,B142:Q148,7) -> 0 | J72: =IF(C72=0,0,(C72/100)*(D72/100)*F72) -> 0 | K72: =J72/0.8 -> 0 | L72: =IF(E72=0,0,VLOOKUP(E72,'Prix Matiere'!$A$4:$J$65,10)) -> 0 | M72: =L72*K72 -> 0 | N72: =IF(J72=0,0,(4.7283*J72)+3) -> 0 | O72: =N72*MinuteMO -> 0 | Q72: =IF(J72=0,0,J72*VLOOKUP(E72,'Prix Matiere'!$A$4:$L$60,12)) -> 0 | R72: =IF(J72=0,0,Q72*VLOOKUP(E72,'Prix Matiere'!$A$4:$L$60,11)) -> 0
B73: Dessus dessous | C73: =IF(F73=0,0,C44) -> 0 | D73: =IF(F73=0,0,D76) -> 0 | E73: =IF($C$17="Aucun",0,VLOOKUP($C$17,B142:Q148,6)) -> 0 | F73: =VLOOKUP($C$17,B142:Q148,7) -> 0 | J73: =IF(C73=0,0,(C73/100)*(D73/100)*F73) -> 0 | K73: =J73/0.8 -> 0 | L73: =IF(E73=0,0,VLOOKUP(E73,'Prix Matiere'!$A$4:$J$65,10)) -> 0 | M73: =L73*K73 -> 0 | N73: =IF(J73=0,0,(4.7283*J73)+3) -> 0 | O73: =N73*MinuteMO -> 0 | Q73: =IF(J73=0,0,J73*VLOOKUP(E73,'Prix Matiere'!$A$4:$L$60,12)) -> 0 | R73: =IF(J73=0,0,Q73*VLOOKUP(E73,'Prix Matiere'!$A$4:$L$60,11)) -> 0
B74: Bouts | C74: =IF(F74=0,0,E76) -> 0 | D74: =IF(F74=0,0,D76) -> 0 | E74: =IF($C$17="Aucun",0,VLOOKUP($C$17,B142:Q148,6)) -> 0 | F74: =VLOOKUP($C$17,B142:Q148,7) -> 0 | J74: =IF(C74=0,0,(C74/100)*(D74/100)*F74) -> 0 | K74: =J74/0.8 -> 0 | L74: =IF(E74=0,0,VLOOKUP(E74,'Prix Matiere'!$A$4:$J$65,10)) -> 0 | M74: =L74*K74 -> 0 | N74: =IF(J74=0,0,(4.7283*J74)+3) -> 0 | O74: =N74*MinuteMO -> 0 | Q74: =IF(J74=0,0,J74*VLOOKUP(E74,'Prix Matiere'!$A$4:$L$60,12)) -> 0 | R74: =IF(J74=0,0,Q74*VLOOKUP(E74,'Prix Matiere'!$A$4:$L$60,11)) -> 0
B76: Dimensions intérieures mousse | C76: =C44-VLOOKUP(C17,B142:Q148,5) -> 110.2 | D76: =D44-VLOOKUP(C17,B142:Q148,5) -> 16 | E76: =E44-VLOOKUP(C17,B142:Q148,5) -> 110.2
B78: Extrudé 1
B79: GC | C79: =IF(F79=0,0,C83+VLOOKUP(C17,B142:Q148,8))-0.5 -> -0.5 | D79: =IF(F79=0,0,E83+VLOOKUP(C17,B142:Q148,8))-0.5 -> -0.5 | E79: =VLOOKUP(C17,B142:Q148,9) -> 0 | F79: =VLOOKUP($C$17,B142:Q148,10) -> 0 | J79: =IF(C79=0,0,(C79/100)*(D79/100)*F79) -> 0 | K79: =J79/0.8 -> 0 | L79: =IF(E79=0,0,VLOOKUP(E79,'Prix Matiere'!A4:J60,10)) -> 0 | M79: =L79*K79 -> 0 | N79: =IF(J79=0,0,(3.94*J79)+5) -> 0 | O79: =N79*MinuteMO -> 0 | Q79: =IF(J79=0,0,J79*VLOOKUP(E79,'Prix Matiere'!$A$4:$L$60,12)) -> 0 | R79: =IF(J79=0,0,Q79*VLOOKUP(E79,'Prix Matiere'!$A$4:$L$60,11)) -> 0
B80: Dessus dessous | C80: =IF(F80=0,0,C83+VLOOKUP(C17,B142:Q148,8)) -> 0 | D80: =IF(F80=0,0,D83) -> 0 | E80: =VLOOKUP(C17,B142:Q148,9) -> 0 | F80: =VLOOKUP($C$17,B142:Q148,10) -> 0 | J80: =IF(C80=0,0,(C80/100)*(D80/100)*F80) -> 0 | K80: =J80/0.8 -> 0 | L80: =IF(E80=0,0,VLOOKUP(E80,'Prix Matiere'!A5:J61,10)) -> 0 | M80: =L80*K80 -> 0 | N80: =IF(J80=0,0,(3.94*J80)+5) -> 0 | O80: =N80*MinuteMO -> 0 | Q80: =IF(J80=0,0,J80*VLOOKUP(E80,'Prix Matiere'!$A$4:$L$60,12)) -> 0 | R80: =IF(J80=0,0,Q80*VLOOKUP(E80,'Prix Matiere'!$A$4:$L$60,11)) -> 0
B81: Bouts | C81: =IF(F81=0,0,E83) -> 0 | D81: =IF(F81=0,0,D83) -> 0 | E81: =VLOOKUP(C17,B142:Q148,9) -> 0 | F81: =VLOOKUP($C$17,B142:Q148,10) -> 0 | J81: =IF(C81=0,0,(C81/100)*(D81/100)*F81) -> 0 | K81: =J81/0.8 -> 0 | L81: =IF(E81=0,0,VLOOKUP(E81,'Prix Matiere'!A6:J62,10)) -> 0 | M81: =L81*K81 -> 0 | N81: =IF(J81=0,0,(3.94*J81)+5) -> 0 | O81: =N81*MinuteMO -> 0 | Q81: =IF(J81=0,0,J81*VLOOKUP(E81,'Prix Matiere'!$A$4:$L$60,12)) -> 0 | R81: =IF(J81=0,0,Q81*VLOOKUP(E81,'Prix Matiere'!$A$4:$L$60,11)) -> 0
B83: Dimensions intérieures styro | C83: =C76-VLOOKUP(C17,B142:Q148,8) -> 110.2 | D83: =D76-VLOOKUP(C17,B142:Q148,8) -> 16 | E83: =E76-VLOOKUP(C17,B142:Q148,8) -> 110.2
J84: =IF(C84=0,0,(C84/100)*(D84/100)*F84) -> 0 | K84: =J84/0.8 -> 0
B85: Plaquettes
B86: GC | C86: =IF(F86=0,0,C89) -> 0 | D86: =IF(F86=0,0,10) -> 0 | E86: =VLOOKUP(C17,B142:Q148,12) -> 0 | F86: =VLOOKUP(C17,B142:Q148,13) -> 0 | J86: =IF(C86=0,0,(C86/100)*(D86/100)*F86) -> 0 | K86: =J86/0.8 -> 0 | L86: =IF(E86=0,0,VLOOKUP(E86,'Prix Matiere'!$A$4:$J$65,10)) -> 0 | M86: =L86*K86 -> 0 | N86: =IF(J86=0,0,1+(6*J86)) -> 0 | O86: =N86*MinuteMO -> 0 | Q86: =IF(J86=0,0,J86*VLOOKUP(E86,'Prix Matiere'!$A$4:$L$60,12)) -> 0 | R86: =IF(J86=0,0,Q86*VLOOKUP(E86,'Prix Matiere'!$A$4:$L$60,11)) -> 0
B87: Dessus dessous | C87: =IF(F87=0,0,D83) -> 0 | D87: =IF(F86=0,0,D86) -> 0 | E87: =VLOOKUP(C17,B142:Q148,12) -> 0 | F87: =VLOOKUP(C17,B142:Q148,13)*2 -> 0 | J87: =IF(C87=0,0,(C87/100)*(D87/100)*F87) -> 0 | K87: =J87/0.8 -> 0 | L87: =IF(E87=0,0,VLOOKUP(E87,'Prix Matiere'!$A$4:$J$65,10)) -> 0 | M87: =L87*K87 -> 0 | N87: =IF(J87=0,0,1+(6*J87)) -> 0 | O87: =N87*MinuteMO -> 0 | Q87: =IF(J87=0,0,J87*VLOOKUP(E87,'Prix Matiere'!$A$4:$L$60,12)) -> 0 | R87: =IF(J87=0,0,Q87*VLOOKUP(E87,'Prix Matiere'!$A$4:$L$60,11)) -> 0
J88: =IF(C88=0,0,(C88/100)*(D88/100)*F88) -> 0 | K88: =J88/0.8 -> 0 | R88: =IF(J88=0,0,Q88*VLOOKUP(E88,'Prix Matiere'!$A$4:$L$60,11)) -> 0
B89: Dimensions intérieures plaquettes | C89: =C83-VLOOKUP($C$17,B142:Q148,11) -> 110.2 | D89: =D83-VLOOKUP($C$17,B142:Q148,11) -> 16 | E89: =E83-VLOOKUP($C$17,B142:Q148,11) -> 110.2 | J89: =IF(C89=0,0,(C89/100)*(D89/100)*F89) -> 0 | K89: =J89/0.8 -> 0
J90: =IF(C90=0,0,(C90/100)*(D90/100)*F90) -> 0 | K90: =J90/0.8 -> 0
B91: Extrudé 2
B92: GC | C92: =IF(F92=0,0,C96+VLOOKUP($C$17,B142:Q148,14)) -> 0 | D92: =IF(F92=0,0,E96+VLOOKUP($C$17,B142:Q148,14)) -> 0 | E92: =VLOOKUP($C$17,B142:Q148,15) -> 0 | F92: =VLOOKUP($C$17,B142:Q148,16) -> 0 | J92: =IF(C92=0,0,(C92/100)*(D92/100)*F92) -> 0 | K92: =J92/0.8 -> 0 | L92: =IF(E92=0,0,VLOOKUP(E92,'Prix Matiere'!A4:J60,10)) -> 0 | M92: =L92*K92 -> 0 | N92: =IF(J92=0,0,(3.94*J92)+5) -> 0 | O92: =N92*MinuteMO -> 0 | Q92: =IF(J92=0,0,J92*VLOOKUP(E92,'Prix Matiere'!$A$4:$L$60,12)) -> 0 | R92: =IF(J92=0,0,Q92*VLOOKUP(E92,'Prix Matiere'!$A$4:$L$60,11)) -> 0
B93: Dessus dessous | C93: =IF(F93=0,0,C96+VLOOKUP($C$17,B142:Q148,14)) -> 0 | D93: =IF(F93=0,0,D96) -> 0 | E93: =VLOOKUP($C$17,B142:Q148,15) -> 0 | F93: =VLOOKUP($C$17,B142:Q148,16) -> 0 | J93: =IF(C93=0,0,(C93/100)*(D93/100)*F93) -> 0 | K93: =J93/0.8 -> 0 | L93: =IF(E93=0,0,VLOOKUP(E93,'Prix Matiere'!A5:J61,10)) -> 0 | M93: =L93*K93 -> 0 | N93: =IF(J93=0,0,(3.94*J93)+5) -> 0 | O93: =N93*MinuteMO -> 0 | Q93: =IF(J93=0,0,J93*VLOOKUP(E93,'Prix Matiere'!$A$4:$L$60,12)) -> 0 | R93: =IF(J93=0,0,Q93*VLOOKUP(E93,'Prix Matiere'!$A$4:$L$60,11)) -> 0
B94: Bouts | C94: =IF(F94=0,0,E96) -> 0 | D94: =IF(F94=0,0,D96) -> 0 | E94: =VLOOKUP($C$17,B142:Q148,15) -> 0 | F94: =VLOOKUP($C$17,B142:Q148,16) -> 0 | J94: =IF(C94=0,0,(C94/100)*(D94/100)*F94) -> 0 | K94: =J94/0.8 -> 0 | L94: =IF(E94=0,0,VLOOKUP(E94,'Prix Matiere'!A6:J62,10)) -> 0 | M94: =L94*K94 -> 0 | N94: =IF(J94=0,0,(3.94*J94)+5) -> 0 | O94: =N94*MinuteMO -> 0 | Q94: =IF(J94=0,0,J94*VLOOKUP(E94,'Prix Matiere'!$A$4:$L$60,12)) -> 0 | R94: =IF(J94=0,0,Q94*VLOOKUP(E94,'Prix Matiere'!$A$4:$L$60,11)) -> 0
J95: =IF(C95=0,0,(C95/100)*(D95/100)*F95) -> 0 | K95: =J95/0.8 -> 0 | Q95: =IF(J95=0,0,J95*VLOOKUP(E95,'Prix Matiere'!$A$4:$L$60,12)) -> 0
B96: Dimensions intérieures styro | C96: =C89-VLOOKUP($C$17,B142:Q148,14) -> 110.2 | D96: =D89-VLOOKUP($C$17,B142:Q148,14) -> 16 | E96: =E89-VLOOKUP($C$17,B142:Q148,14) -> 110.2 | J96: =IF(C96=0,0,(C96/100)*(D96/100)*F96) -> 0 | K96: =J96/0.8 -> 0
J97: =IF(C97=0,0,(C97/100)*(D97/100)*F97) -> 0 | K97: =J97/0.8 -> 0
J98: =IF(C98=0,0,(C98/100)*(D98/100)*F98) -> 0 | K98: =J98/0.8 -> 0
B99: Mousse de calage | J99: =IF(C99=0,0,(C99/100)*(D99/100)*F99) -> 0 | K99: =J99/0.8 -> 0
B100: =IF(B34="Aucun",0,"Dessus") -> Dessus | C100: =IF(B34="Aucun",0,C96) -> 110.2 | D100: =IF(B34="Aucun",0,D29+VLOOKUP(B34,B169:M177,5)) -> 16 | E100: =VLOOKUP(B34,B169:M177,9) -> PU 50 mm | F100: =IF(B34="Aucun",0,IF(B34="Entourage Stratocell 20 mm",2,IF(B34="Entourage Stratocell 30 mm",2,1))) -> 1 | J100: =IF(C100=0,0,(C100/100)*(D100/100)*F100) -> 0.17632 | K100: =J100/0.8 -> 0.2204 | L100: =IF(E100=0,0,VLOOKUP(E100,'Prix Matiere'!$A$4:$J$65,10)) -> 9.5670103 | M100: =L100*K100 -> 2.1085691 | N100: =IF(J100=0,0,4.7283*J100+2) -> 2.8336939 | O100: =N100*MinuteMO -> 2.4086398 | Q100: =IF(J100=0,0,J100*VLOOKUP(E100,'Prix Matiere'!$A$4:$L$60,12)) -> 0.2204 | R100: =IF(J100=0,0,Q100*VLOOKUP(E100,'Prix Matiere'!$A$4:$L$60,11)) -> 0.59508
B101: =IF(B34="Aucun",0,"Extrémité") -> Extrémité | C101: =IF(B34="Aucun",0,IF(B34="Entourage Stratocell 20 mm",0,IF(B34="Entourage Stratocell 30 mm",0,IF(C29<60,10,IF(C29<80,15,20))))) -> 20 | D101: =IF(B34="Entourage Stratocell 20 mm",0,IF(B34="Entourage Stratocell 30 mm",0,D100)) -> 16 | E101: =IF(B34="Entourage Stratocell 20 mm",0,IF(B34="Entourage Stratocell 30 mm",0,VLOOKUP(B34,B169:M177,9))) -> PU 50 mm | F101: =IF(B34="Aucun",0,IF(B34="Entourage Stratocell 20 mm",0,IF(B34="Entourage Stratocell 30 mm",0,2))) -> 2 | J101: =IF(C101=0,0,(C101/100)*(D101/100)*F101) -> 0.064 | K101: =J101/0.8 -> 0.08 | L101: =IF(E101=0,0,VLOOKUP(E101,'Prix Matiere'!$A$4:$J$65,10)) -> 9.5670103 | M101: =L101*K101 -> 0.76536082 | N101: =IF(J101=0,0,4.7283*J101+2) -> 2.3026112 | O101: =N101*MinuteMO -> 1.9572195 | Q101: =IF(J101=0,0,J101*VLOOKUP(E101,'Prix Matiere'!$A$4:$L$60,12)) -> 0.08 | R101: =IF(J101=0,0,Q101*VLOOKUP(E101,'Prix Matiere'!$A$4:$L$60,11)) -> 0.216
B102: =IF(B34="Aucun",0,B38) -> Ethafoam 50 mm | C102: =C38 -> 12 | D102: =IF(B34="Entourage Stratocell 20 mm",0,IF(B34="Entourage Stratocell 30 mm",0,D101)) -> 16 | E102: =IF(B34="Aucun",0,IF(B34="Entourage Stratocell 20 mm",0,IF(B34="Entourage Stratocell 30 mm",0,IF(B102="Ethafoam 50 mm","Ethafoam 50 mm","Agglocelle 50 mm")))) -> Ethafoam 50 mm | F102: =F38 -> 2 | J102: =IF(C102=0,0,(C102/100)*(D102/100)*F102) -> 0.0384 | K102: =J102/0.8 -> 0.048 | L102: =IF(E102=0,0,VLOOKUP(E102,'Prix Matiere'!$A$4:$J$65,10)) -> 22.000937 | M102: =L102*K102 -> 1.056045 | N102: =IF(J102=0,0,4.7283*J102+2) -> 2.1815667 | O102: =N102*MinuteMO -> 1.8543317 | Q102: =IF(J102=0,0,J102*VLOOKUP(E102,'Prix Matiere'!$A$4:$L$60,12)) -> 0.0672 | R102: =IF(J102=0,0,Q102*VLOOKUP(E102,'Prix Matiere'!$A$4:$L$60,11)) -> 0.19488
B103: =IF(B34="Aucun",0,"Milieu") -> Milieu | C103: =IF(B34="Entourage Stratocell 20 mm",0,IF(B34="Entourage Stratocell 30 mm",0,(C100-((C101*F101)+(C102*F102)))/(F102-1))) -> 46.2 | D103: =IF(B34="Entourage Stratocell 20 mm",0,IF(B34="Entourage 30 mm",0,D102)) -> 16 | E103: =IF(B34="Entourage Stratocell 20 mm",0,IF(B34="Entourage Stratocell 30 mm",0,VLOOKUP(B34,B169:M177,9))) -> PU 50 mm | F103: =IF(B34="Aucun",0,IF(B34="Entourage Stratocell 20 mm",0,IF(B34="Entourage Stratocell 30 mm",0,F102-1))) -> 1 | J103: =IF(C103=0,0,(C103/100)*(D103/100)*F103) -> 0.07392 | K103: =J103/0.8 -> 0.0924 | L103: =IF(E103=0,0,VLOOKUP(E103,'Prix Matiere'!$A$4:$J$65,10)) -> 9.5670103 | M103: =L103*K103 -> 0.88399175 | N103: =IF(J103=0,0,4.7283*J103+2) -> 2.3495159 | O103: =N103*MinuteMO -> 1.9970885 | Q103: =IF(J103=0,0,J103*VLOOKUP(E103,'Prix Matiere'!$A$4:$L$60,12)) -> 0.0924 | R103: =IF(J103=0,0,Q103*VLOOKUP(E103,'Prix Matiere'!$A$4:$L$60,11)) -> 0.24948
B104: =IF(B34="Aucun",0,"Bouts avec passage de main") -> Bouts avec passage de main | C104: =IF(B34="Aucun",0,IF(B34="Entourage Stratocell 20 mm",E96-4.4,IF(B34="Entourage Stratocell 30 mm",E96-6.4,(E29-IF(E29>120,30,15))/(F104/2)))) -> 42.5 | D104: =IF(B34="Entourage Stratocell 20 mm",D100,IF(B34="Entourage Stratocell 30 mm",D100,D103)) -> 16 | E104: =VLOOKUP(B34,B169:M177,9) -> PU 50 mm | F104: =IF(B34="Aucun",0,IF(B34="Entourage Stratocell 20 mm",2,IF(B34="Entourage Stratocell 30 mm",2,IF(E29>120,6,4)))) -> 4 | J104: =IF(C104=0,0,(C104/100)*(D104/100)*F104) -> 0.272 | K104: =J104/0.8 -> 0.34 | L104: =IF(E104=0,0,VLOOKUP(E104,'Prix Matiere'!$A$4:$J$65,10)) -> 9.5670103 | M104: =L104*K104 -> 3.2527835 | N104: =IF(J104=0,0,4.7283*J104+2) -> 3.2860976 | O104: =N104*MinuteMO -> 2.793183 | Q104: =IF(J104=0,0,J104*VLOOKUP(E104,'Prix Matiere'!$A$4:$L$60,12)) -> 0.34 | R104: =IF(J104=0,0,Q104*VLOOKUP(E104,'Prix Matiere'!$A$4:$L$60,11)) -> 0.918
B105: =IF(B34="Aucun",0,"Fond") -> Fond | C105: =IF(B34="Aucun",0,C29+VLOOKUP(B34,B169:M177,6)) -> 100.2 | D105: =IF(B34="Sous verre 2 faces",E29+VLOOKUP(B34,B169:M177,6),IF(B34="Bandes de mousse fond plein",E29+VLOOKUP(B34,B169:M177,6),IF(B34="Entourage Stratocell 20 mm",E96,IF(B34="Entourage Stratocell 30 mm",E96,C37)))) -> 5 | E105: =VLOOKUP(B34,B169:M177,8) -> PU 50 mm | F105: =VLOOKUP(B34,B169:M177,7) -> 2 | J105: =IF(C105=0,0,(C105/100)*(D105/100)*F105) -> 0.1002 | K105: =J105/0.8 -> 0.12525 | L105: =IF(E105=0,0,VLOOKUP(E105,'Prix Matiere'!$A$4:$J$65,10)) -> 9.5670103 | M105: =L105*K105 -> 1.198268 | N105: =IF(J105=0,0,4.7283*J105+2) -> 2.4737757 | O105: =N105*MinuteMO -> 2.1027093 | Q105: =IF(J105=0,0,J105*VLOOKUP(E105,'Prix Matiere'!$A$4:$L$60,12)) -> 0.12525 | R105: =IF(J105=0,0,Q105*VLOOKUP(E105,'Prix Matiere'!$A$4:$L$60,11)) -> 0.338175
B106: =IF(B34="Aucun",0,"Remplis de fond") -> Remplis de fond | C106: =IF(B34="Aucun",0,IF(B34="Entourage Stratocell 20 mm",0,IF(B34="Entourage Stratocell 30 mm",0,IF(B34="Sous verre 2 faces",0,IF(B34="Bandes de mousse fond plein",0,E29-D105*2+VLOOKUP(B34,B169:M177,6)))))) -> 90.2 | D106: =IF(B34="Sous verre 2 faces",0,C37) -> 5 | E106: =IF(C106=0,0,VLOOKUP(B34,B169:M177,8)) -> PU 50 mm | F106: =IF(B34="Aucun",0,IF(B34="Entourage Stratocell 20 mm",0,IF(B34="Entourage Stratocell 30 mm",0,IF(B34="Sous verre 2 faces",0,2)))) -> 2 | J106: =IF(C106=0,0,(C106/100)*(D106/100)*F106) -> 0.0902 | K106: =J106/0.8 -> 0.11275 | L106: =IF(E106=0,0,VLOOKUP(E106,'Prix Matiere'!$A$4:$J$65,10)) -> 9.5670103 | M106: =L106*K106 -> 1.0786804 | N106: =IF(J106=0,0,4.7283*J106+2) -> 2.4264927 | O106: =N106*MinuteMO -> 2.0625188 | Q106: =IF(J106=0,0,J106*VLOOKUP(E106,'Prix Matiere'!$A$4:$L$60,12)) -> 0.11275 | R106: =IF(J106=0,0,Q106*VLOOKUP(E106,'Prix Matiere'!$A$4:$L$60,11)) -> 0.304425
B107: =IF(B34="Aucun",0,"Dessus") -> Dessus | C107: =IF(B34="Aucun",0,C29+VLOOKUP(B34,B169:M177,10)) -> 99.5 | D107: =IF(B34="Sous verre 2 faces",E29+VLOOKUP(B34,B169:M177,10),IF(B34="Sous verre / bandes de mousse",E29+VLOOKUP(B34,B169:M177,10),C36)) -> 5 | E107: =VLOOKUP(B34,B169:M177,9) -> PU 50 mm | F107: =VLOOKUP(B34,B169:M177,11) -> 2 | J107: =IF(C107=0,0,(C107/100)*(D107/100)*F107) -> 0.0995 | K107: =J107/0.8 -> 0.124375 | L107: =IF(E107=0,0,VLOOKUP(E107,'Prix Matiere'!$A$4:$J$65,10)) -> 9.5670103 | M107: =L107*K107 -> 1.1898969 | N107: =IF(J107=0,0,4.7283*J107+2) -> 2.4704659 | O107: =N107*MinuteMO -> 2.099896 | Q107: =IF(J107=0,0,J107*VLOOKUP(E107,'Prix Matiere'!$A$4:$L$60,12)) -> 0.124375 | R107: =IF(J107=0,0,Q107*VLOOKUP(E107,'Prix Matiere'!$A$4:$L$60,11)) -> 0.3358125
B108: =IF(B34="Aucun",0,"Remplis de dessus") -> Remplis de dessus | C108: =IF(B34="Aucun",0,IF(B34="Entourage Stratocell 20 mm",0,IF(B34="Entourage Stratocell 30 mm",0,IF(B34="Sous verre 2 faces",0,IF(B34="Sous verre / bandes de mousse",0,E29-2*D107+VLOOKUP(B34,B169:M177,10)))))) -> 89.5 | D108: =IF(B34="Sous verre / bandes de mousse",0,IF(B34="Sous verre 2 faces",0,C36)) -> 5 | E108: =IF(C108=0,0,VLOOKUP(B34,B169:M177,9)) -> PU 50 mm | F108: =IF(B34="Aucun",0,IF(B34="Entourage Stratocell 20 mm",0,IF(B34="Entourage Stratocell 30 mm",0,IF(B34="Sous verre 2 faces",0,IF(B34="Sous verre / bandes de mousse",0,2))))) -> 2 | J108: =IF(C108=0,0,(C108/100)*(D108/100)*F108) -> 0.0895 | K108: =J108/0.8 -> 0.111875 | L108: =IF(E108=0,0,VLOOKUP(E108,'Prix Matiere'!$A$4:$J$65,10)) -> 9.5670103 | M108: =L108*K108 -> 1.0703093 | N108: =IF(J108=0,0,4.7283*J108+2) -> 2.4231828 | O108: =N108*MinuteMO -> 2.0597054 | Q108: =IF(J108=0,0,J108*VLOOKUP(E108,'Prix Matiere'!$A$4:$L$60,12)) -> 0.111875 | R108: =IF(J108=0,0,Q108*VLOOKUP(E108,'Prix Matiere'!$A$4:$L$60,11)) -> 0.3020625
B109: =IF(B34="Aucun",0,"Rattrapage 1") -> Rattrapage 1 | C109: =IF(C39=0,0,C29+0.2) -> 0 | D109: =IF(C39=0,0,C39) -> 0 | E109: =IF(C109=0,0,CONCATENATE("PU ",$E$39*10," mm")) -> 0 | F109: =IF(C39=0,0,2) -> 0 | J109: =IF(C109=0,0,(C109/100)*(D109/100)*F109) -> 0 | K109: =J109/0.8 -> 0 | L109: =IF(E109=0,0,VLOOKUP(E109,'Prix Matiere'!$A$4:$J$65,10)) -> 0 | M109: =L109*K109 -> 0 | N109: =IF(J109=0,0,4.7283*J109+2) -> 0 | O109: =N109*MinuteMO -> 0 | Q109: =IF(J109=0,0,J109*VLOOKUP(E109,'Prix Matiere'!$A$4:$L$60,12)) -> 0 | R109: =IF(J109=0,0,Q109*VLOOKUP(E109,'Prix Matiere'!$A$4:$L$60,11)) -> 0
B110: =IF(B34="Aucun",0,"Rattrapage 2") -> Rattrapage 2 | C110: =IF(C39=0,0,E29+0.2-2*D109) -> 0 | D110: =IF(C28=0,0,D109) -> 0 | E110: =IF(C110=0,0,CONCATENATE("PU ",$E$39*10," mm")) -> 0 | F110: =IF(C39=0,0,2) -> 0 | J110: =IF(C110=0,0,(C110/100)*(D110/100)*F110) -> 0 | K110: =J110/0.8 -> 0 | L110: =IF(E110=0,0,VLOOKUP(E110,'Prix Matiere'!$A$4:$J$65,10)) -> 0 | M110: =L110*K110 -> 0 | N110: =IF(J110=0,0,4.7283*J110+2) -> 0 | O110: =N110*MinuteMO -> 0 | Q110: =IF(J110=0,0,J110*VLOOKUP(E110,'Prix Matiere'!$A$4:$L$60,12)) -> 0 | R110: =IF(J110=0,0,Q110*VLOOKUP(E110,'Prix Matiere'!$A$4:$L$60,11)) -> 0
B111: =IF(B34="Aucun",0,"Remplissage 1") -> Remplissage 1 | C111: =IF(C41=0,0,C41) -> 0 | D111: =IF(D41=0,0,D41) -> 0 | E111: =IF(C111=0,0,CONCATENATE("PU ",$E$41*10," mm")) -> 0 | F111: =IF(C41=0,0,1) -> 0 | J111: =IF(C111=0,0,(C111/100)*(D111/100)*F111) -> 0 | K111: =J111/0.8 -> 0 | L111: =IF(E111=0,0,VLOOKUP(E111,'Prix Matiere'!$A$4:$J$65,10)) -> 0 | M111: =L111*K111 -> 0 | N111: =IF(J111=0,0,4.7283*J111+2) -> 0 | O111: =N111*MinuteMO -> 0 | Q111: =IF(J111=0,0,J111*VLOOKUP(E111,'Prix Matiere'!$A$4:$L$60,12)) -> 0 | R111: =IF(J111=0,0,Q111*VLOOKUP(E111,'Prix Matiere'!$A$4:$L$60,11)) -> 0
B112: =IF(B34="Aucun",0,"Remplissage 2") -> Remplissage 2 | C112: =IF(C42=0,0,C42) -> 0 | D112: =IF(D42=0,0,D42) -> 0 | E112: =IF(C112=0,0,CONCATENATE("PU ",$E$42*10," mm")) -> 0 | F112: =IF(C42=0,0,1) -> 0 | J112: =IF(C112=0,0,(C112/100)*(D112/100)*F112) -> 0 | K112: =J112/0.8 -> 0 | L112: =IF(E112=0,0,VLOOKUP(E112,'Prix Matiere'!$A$4:$J$65,10)) -> 0 | M112: =L112*K112 -> 0 | N112: =IF(J112=0,0,4.7283*J112+2) -> 0 | O112: =N112*MinuteMO -> 0 | Q112: =IF(J112=0,0,J112*VLOOKUP(E112,'Prix Matiere'!$A$4:$L$60,12)) -> 0 | R112: =IF(J112=0,0,Q112*VLOOKUP(E112,'Prix Matiere'!$A$4:$L$60,11)) -> 0
B113: =IF(B34="Aucun",0,"Carton") -> Carton | C113: =IF(F113=0,0,C29+VLOOKUP(B34,B169:M177,10)) -> 99.5 | D113: =IF(F113=0,0,E29+VLOOKUP(B34,B167:M178,10)) -> 99.5 | E113: =IF(C113=0,0,"Carton") -> Carton | F113: =VLOOKUP(B34,B169:M177,12) -> 1 | J113: =IF(C113=0,0,(C113/100)*(D113/100)*F113) -> 0.990025 | K113: =J113/0.8 -> 1.2375312 | L113: =IF(E113=0,0,Carton) -> 2.324775 | M113: =L113*K113 -> 2.8769817 | N113: =IF(J113=0,0,2.356*J113+1) -> 3.3324989 | O113: =N113*MinuteMO -> 2.8326241 | Q113: =IF(J113=0,0,J113*Poids_Carton) -> 0.990025 | R113: =IF(J113=0,0,Q113*VLOOKUP(E113,'Prix Matiere'!$A$4:$L$60,11)) -> 0.4791721
O114: =N114*MinuteMO -> 0 | Q114: =IF(J114=0,0,J114*Poids_Carton) -> 0 | R114: =IF(J114=0,0,Q114*VLOOKUP(E114,'Prix Matiere'!$A$4:$L$60,11)) -> 0
B115: Option | C115: =IF(F23="Aucun"," ",F23) | M115: =VLOOKUP($F$23,$B$158:$E$161,3) -> 0 | N115: =IF(M115=0,0,12.5) -> 0 | O115: =N115*MinuteMO -> 0 | R115: =IF(J115=0,0,Q115*VLOOKUP(E115,'Prix Matiere'!$A$4:$L$60,11)) -> 0
B116: Tyvek | C116: =IF($F$21="Oui","Tyvek",0) -> 0 | K116: =IF(C116="Tyvek",SUM(K100:K112)/0.7,0) -> 0 | L116: =IF(C116=0,0,2.75) -> 0 | M116: =K116*L116 -> 0 | N116: =IF(K116=0,0,7*K116+2) -> 0 | O116: =N116*MinuteMO -> 0 | Q116: =IF(K116=0,0,K116*VLOOKUP(C116,'Prix Matiere'!$A$4:$L$60,12)) -> 0 | R116: =IF(J116=0,0,Q116*VLOOKUP(E116,'Prix Matiere'!$A$4:$L$60,11)) -> 0
B117: Peinture | C117: =IF(F19="Non",0,"Peinture") -> 0 | J117: =IF(C117=0,0,(((C46/100)*(D46/100))+((C46/100)*(E46/100))+((D46/100)*(E46/100)))*2) -> 0 | K117: =J117*0.5 -> 0 | L117: =IF(C117=0,0,VLOOKUP(C117,'Prix Matiere'!$A$4:$J$60,10)) -> 0 | M117: =K117*L117 -> 0 | N117: =IF(J117=0,0,IF(C117="Peinture",30+J117*15)) -> 0 | O117: =N117*MinuteMO -> 0 | Q117: =IF(J117=0,0,J117*VLOOKUP(C117,'Prix Matiere'!$A$4:$L$60,12)) -> 0 | R117: =IF(J117=0,0,Q117*VLOOKUP(C117,'Prix Matiere'!$A$4:$L$60,11)) -> 0
B118: Fermetures | C118: =C19 -> Vis bois | M118: =IF(C118="Vis bois",0,(F4*2+F6*2)*1.5) -> 0 | N118: =IF(C118="Vis bois",0,45) -> 0 | O118: =N118*MinuteMO -> 0 | Q118: =IF(J118=0,0,J118*Poids_Carton) -> 0
B119: Poignées | C119: =C21 -> Bois | M119: =IF(C119="Métal x 4 sur GC",4*2,IF(C119="Métal x 2 sur bouts",2*2,0)) -> 0 | N119: =IF(C119="Métal x 4 sur GC",4*3,IF(C119="Métal x 2 sur bouts",2*3,0)) -> 0 | O119: =N119*MinuteMO -> 0 | Q119: =IF(J119=0,0,J119*Poids_Carton) -> 0
L121: =IF(E121=0,0,VLOOKUP(E121,'Prix Matiere'!$A$4:$J$65,10)) -> 0 | M121: =SUM(M58:M120) -> 131.20282 | N121: =SUM(N58:N120) -> 120.02949 | O121: =N121*MinuteMO -> 102.02506 | Q121: =SUM(Q58:Q119) -> 40.93123 | R121: =SUM(R58:R119) -> 29.294938
B122: Total matière | C122: =IF($F$9=0,0,M121) -> 131.20282 | E122: Contreplaqué | F122: =CONCATENATE(ROUNDUP(SUM(K58:K60)+SUM(K86:K87),2)," m²") -> 4,36 m² | G122: =SUM(M58:M60)+SUM(M86:M87) -> 73.599958
B123: Total MO | C123: =IF($F$9=0,0,O121) -> 102.02506 | D123: =IF($F$9=0,0,N121) -> 120.02949 | E123: Bois massif | F123: =CONCATENATE(ROUNDUP(SUM(K63:K69),2)," m²") -> 1,96 m² | G123: =SUM(M63:M69) -> 42.121976
B124: Total frais généraux | C124: =IF($F$9=0,0,((C122+C123)/Frais_Généraux)-(C122+C123)) -> 125.58425 | E124: Polystyrène extrudé | F124: =CONCATENATE(ROUNDUP(SUM(K79:K81)+SUM(K92:K94),2)," m²") -> 0 m² | G124: =SUM(M79:M81)+SUM(M92:M94) -> 0
B125: Total revient | C125: =IF($F$9=0,0,SUM(C122:C124)) -> 358.81213 | E125: Mousse | F125: =CONCATENATE(ROUNDUP(SUM(K72:K74)+SUM(K100:K112),2)," m²") -> 1,26 m² | G125: =SUM(M72:M74)+SUM(M100:M112) -> 12.603905
B126: Marge | C126: =IF($F$9=0,0,(C125/(1-Marge)-C125)) -> 27.007365 | D126: =C125+C126 -> 385.81949 | E126: Carton | F126: =CONCATENATE(ROUNDUP(K113,2)," m²") -> 1,24 m² | G126: =M113 -> 2.8769817
...

Sheet T1-T6
A1: Caisse Tableau de 1 à 6 Œuvres
E3: =IF(C19="Boulons et platines","Boulons et Platines",0) -> 0 | F3: =IF(E3="Boulons et Platines","Nbre de Trous",0) -> 0 | G3: =IF(E3="Boulons et Platines","Dim du Bord",0) -> 0
E4: =IF(C19="Vis bois",0,"Trous dans la Longueur") -> 0 | F4: =IF(E4=0,0,IF(C90<100,2,IF(C90<150,3,IF(C90<200,4,IF(C90<250,5,IF(C90<300,6,7)))))) -> 0 | G4: =IF(F4=0,0,IF(F4=3,0,(($C$90-32)/(F4-1))+16)) -> 0
E5: =IF(F4=6,"2ème Trou",IF(F4=7,"2ème Trou",0)) -> 0 | G5: =IF(E5=0,0,G4+G4-16) -> 0
E6: =IF(C19="Vis bois",0,"Trous dans la Hauteur") -> 0 | F6: =IF(E6=0,0,IF(D90<100,2,IF(D90<150,3,IF(D90<200,4,IF(D90<250,5,IF(D90<310,6,7)))))) -> 0 | G6: =IF(F6=0,0,IF(F6=3,0,(($D$90-32)/(F6-1))+16)) -> 0
E7: =IF(F6=6,"2ème Trou",IF(F6=7,"2ème Trou",0)) -> 0 | G7: =IF(E7=0,0,G6+G6-16) -> 0
B9: N° de dossier | E9: Responsable Dossier | F9: Grégory MORA
B10: Ville de destination | E10: Client | F10: ESI
B11: N° de caisse | E11: Délai
B13: Type de Contreplaqué | C13: Peuplier 15 mm | H13: =VLOOKUP($F$10,'Infos Clients'!$B$2:$G$10,2) -> #VALUE!
B15: Barres | C15: Pin raboté 4 faces | E15: Garnissage Valsem | F15: Oui
B17: Type d'isolant | C17: Super isotherme en 30
B19: Fermeture | C19: Vis bois | E19: Peinture | F19: Non
E20: =IF(F19="Oui","Type de Peinture",0) -> 0 | F20: =IF(F19="Non",0,VLOOKUP(F10,'Infos Clients'!B2:E10,4)) -> 0
B21: Poignées | C21: Bois | E21: Tyvek | F21: Non
B23: Skis | C23: Skis | E23: Option Calage | F23: Aucun
B24: =IF(F23="Aucun"," ",F23) | D24: =IF(F21="Oui","+",0) -> 0 | E24: =IF(F21="Oui","Mousse Garnie Tyvek",0) -> 0
B26: =IF(F10="Bovis","Attention retirer 2 mm aux dimensions transmises",0) -> 0
A28: =IF(B29="Aucun","Dimensions intérieures utiles","Dimensions de l'œuvre") -> Dimensions de l'œuvre | B28: Longueur | C28: Epaisseur | D28: Hauteur | E28: Mousse de Calage 1 | G28: =IF(H29="Aucun","Dimensions intérieures utiles","Dimensions de l'œuvre") -> Dimensions de l'œuvre | H28: Longueur | I28: Epaisseur | J28: Hauteur | K28: Mousse de Calage 2
B29: 62 | C29: 13 | D29: 43
A30: Type de calage | B30: Bandes de mousse | C30: N° d'inventaire | G30: Type de calage | H30: Aucun | I30: N° d'inventaire
B31: Largeur | C31: Longueur | D31: Epaisseur | E31: Quantité | H31: Largeur | I31: Longueur | J31: Epaisseur | K31: Quantité
A32: Dessus | B32: 10 | G32: Dessus
A33: Dessous | B33: 10 | G33: Dessous
A34: Agglocelle 50 mm | B34: =+IF(B29=0,0,IF(B29>70,12,6)) -> 6 | E34: =IF(B29>300,6,IF(B29>250,5,IF(B29>200,4,IF(B29>150,3,IF(B29>120,3,2))))) -> 2 | G34: Aucun | H34: =+IF(H29=0,0,IF(H29>70,12,6)) -> 0 | K34: =IF(H29>300,6,IF(H29>250,5,IF(H29>200,4,IF(H29>150,3,IF(H29>120,3,2))))) -> 2
A35: Rattrapage | G35: Rattrapage
A36: Remplissage 1 | G36: Remplissage 1
A37: Remplissage 2 | G37: Remplissage 2
A38: Dimensions nécéssaires | B38: =IF(B29=0,0,B29+VLOOKUP(B30,$A$282:$L$288,2)) -> 72.2 | C38: =IF(C29=0,0,C29+VLOOKUP(B30,$A$282:$L$288,3)) -> 24 | D38: =IF(D29=0,0,D29+VLOOKUP(B30,$A$282:$L$288,4)) -> 53.2 | G38: Dims nécéssaires | H38: =IF(H29=0,0,H29+VLOOKUP(H30,$A$282:$L$288,2)) -> 0 | I38: =IF(I29=0,0,I29+VLOOKUP(H30,$A$282:$L$288,3)) -> 0 | J38: =IF(J29=0,0,J29+VLOOKUP(H30,$A$282:$L$288,4)) -> 0
G40: Dims fond de caisse | H40: =IF(B41=0,0,MAX(B41,B56+5.5,B72+5.5)) -> 75.2 | I40: =C41 -> 24 | J40: =IF(D41=0,0,MAX(D41,D56+5.5,D72+5.5)) -> 56.2
A41: Dims necessaire fond de caisse | B41: =B38+IF(H38=0,0,1.5+H38) -> 72.2 | C41: =MAX(C38,I38) -> 24 | D41: =MAX(D38,J38) -> 53.2 | G41: Dims ext fond de caisse | H41: =IF(H40=0,0,H40) -> 75.2 | I41: =IF(I40=0,0,I40) -> 24 | J41: =IF(J40=0,0,J40) -> 56.2
A43: =IF(B44="Aucun","Dimensions intérieures utiles","Dimensions de l'œuvre") -> Dimensions de l'œuvre | B43: Longueur | C43: Epaisseur | D43: Hauteur | E43: Mousse de Calage 3 | G43: =IF(H44="Aucun","Dimensions intérieures utiles","Dimensions de l'œuvre") -> Dimensions de l'œuvre | H43: Longueur | I43: Epaisseur | J43: Hauteur | K43: Mousse de Calage 4
B44: 59 | C44: 8.5 | D44: 40.5
A45: Type de calage | B45: Bandes de mousse | C45: N° d'inventaire | G45: Type de calage | H45: Aucun | I45: N° d'inventaire
B46: Largeur | C46: Longueur | D46: Epaisseur | E46: Quantité | H46: Largeur | I46: Longueur | J46: Epaisseur | K46: Quantité
A47: Dessus | B47: 10 | G47: Dessus
A48: Dessous | B48: 10 | G48: Dessous
A49: Agglocelle 50 mm | B49: =+IF(B44=0,0,IF(B44>70,12,6)) -> 6 | E49: =IF(B44>300,6,IF(B44>250,5,IF(B44>200,4,IF(B44>150,3,IF(B44>120,3,2))))) -> 2 | G49: Aucun | H49: =+IF(H44=0,0,IF(H44>70,12,6)) -> 0 | K49: =IF(H44>300,6,IF(H44>250,5,IF(H44>200,4,IF(H44>150,3,IF(H44>120,3,2))))) -> 2
A50: Rattrapage | G50: Rattrapage
A51: Remplissage 1 | G51: Remplissage 1
A52: Remplissage 2 | G52: Remplissage 2
A53: Dimensions nécéssaires | B53: =IF(B44=0,0,B44+VLOOKUP(B45,$A$282:$L$288,2)) -> 69.2 | C53: =IF(C44=0,0,C44+VLOOKUP(B45,$A$282:$L$288,3)) -> 19.5 | D53: =IF(D44=0,0,D44+VLOOKUP(B45,$A$282:$L$288,4)) -> 50.7 | G53: Dims nécéssaires | H53: =IF(H44=0,0,H44+VLOOKUP(H45,$A$282:$L$288,2)) -> 0 | I53: =IF(I44=0,0,I44+VLOOKUP(H45,$A$282:$L$288,3)) -> 0 | J53: =IF(J44=0,0,J44+VLOOKUP(H45,$A$282:$L$288,4)) -> 0
A55: Dims nécéssaire cuvette 1 | G55: Dims int cuvette | H55: =IF(H57=0,0,H56-3) -> 69.7 | I55: =IF(I57=0,0,I56-1) -> 19.5 | J55: =IF(J57=0,0,J56-3) -> 50.7
B56: =B53+IF(H53=0,0,1.5+H53) -> 69.2 | C56: =MAX(C53,I53) -> 19.5 | D56: =MAX(D53,J53) -> 50.7 | G56: Dims ext cuvette | H56: =IF(H57=0,0,H57-2.5) -> 72.7 | I56: =IF(I57=0,0,I57-0.2) -> 20.5 | J56: =IF(J57=0,0,J57-2.5) -> 53.7
G57: Dims nec caisse | H57: =IF(B56=0,0,MAX(B41,B56+5.5,B72+5.5)) -> 75.2 | I57: =IF(C56=0,0,C56+1.2) -> 20.7 | J57: =IF(D56=0,0,MAX(D41,D56+5.5,D72+5.5)) -> 56.2
A59: =IF(B60="Aucun","Dimensions intérieures utiles","Dimensions de l'œuvre") -> Dimensions de l'œuvre | B59: Longueur | C59: Epaisseur | D59: Hauteur | E59: Mousse de Calage 5 | G59: =IF(H60="Aucun","Dimensions intérieures utiles","Dimensions de l'œuvre") -> Dimensions de l'œuvre | H59: Longueur | I59: Epaisseur | J59: Hauteur | K59: Mousse de Calage 6
B60: 59.5 | C60: 8 | D60: 39.5
A61: Type de calage | B61: Bandes de mousse | C61: N° d'inventaire | G61: Type de calage | H61: Aucun | I61: N° d'inventaire
B62: Largeur | C62: Longueur | D62: Epaisseur | E62: Quantité | H62: Largeur | I62: Longueur | J62: Epaisseur | K62: Quantité
A63: Dessus | B63: 7 | G63: Dessus
A64: Dessous | B64: 7 | G64: Dessous
A65: Ethafoam 50 mm | B65: =+IF(B60=0,0,IF(B60>70,12,6)) -> 6 | E65: =IF(B60>300,6,IF(B60>250,5,IF(B60>200,4,IF(B60>150,3,IF(B60>120,3,2))))) -> 2 | G65: Aucun | H65: =+IF(H60=0,0,IF(H60>70,12,6)) -> 0 | K65: =IF(H60>300,6,IF(H60>250,5,IF(H60>200,4,IF(H60>150,3,IF(H60>120,3,2))))) -> 2
A66: Rattrapage | G66: Rattrapage
A67: Remplissage 1 | G67: Remplissage 1
A68: Remplissage 2 | G68: Remplissage 2
A69: Dimensions nécéssaires | B69: =IF(B60=0,0,B60+VLOOKUP(B61,$A$282:$L$288,2)) -> 69.7 | C69: =IF(C60=0,0,C60+VLOOKUP(B61,$A$282:$L$288,3)) -> 19 | D69: =IF(D60=0,0,D60+VLOOKUP(B61,$A$282:$L$288,4)) -> 49.7 | G69: Dims nécéssaires | H69: =IF(H60=0,0,H60+VLOOKUP(H61,$A$282:$L$288,2)) -> 0 | I69: =IF(I60=0,0,I60+VLOOKUP(H61,$A$282:$L$288,3)) -> 0 | J69: =IF(J60=0,0,J60+VLOOKUP(H61,$A$282:$L$288,4)) -> 0
A71: Dims nécéssaire cuvette 2 | G71: Dims int cuvette | H71: =IF(H73=0,0,H72-3) -> 69.7 | I71: =IF(I73=0,0,I72-1) -> 19 | J71: =IF(J73=0,0,J72-3) -> 50.7
B72: =B69+IF(H69=0,0,1.5+H69) -> 69.7 | C72: =MAX(C69,I69) -> 19 | D72: =MAX(D69,J69) -> 49.7 | G72: Dims ext cuvette | H72: =IF(H73=0,0,H73-2.5) -> 72.7 | I72: =IF(I73=0,0,I73-0.2) -> 20 | J72: =IF(J73=0,0,J73-2.5) -> 53.7
G73: Dims nec caisse | H73: =IF(B72=0,0,MAX(B41,B56+5.5,B72+5.5)) -> 75.2 | I73: =IF(C72=0,0,C72+1.2) -> 20.2 | J73: =IF(D72=0,0,MAX(D41,D56+5.5,D72+5.5)) -> 56.2
A74: Dimensions nécessaire caisse
C75: =MAX(H41,H57,H73) -> 75.2 | D75: =I41+I57+I73 -> 64.9 | E75: =MAX(J41,J57,J73) -> 56.2
B77: Dimensions intérieures caisse | C77: =C75+VLOOKUP(C17,$A$257:$P$263,2) -> 95.7 | D77: =D75+VLOOKUP(C17,$A$257:$P$263,3) -> 85.4 | E77: =E75+VLOOKUP(C17,$A$257:$P$263,4) -> 76.7 | F77: Prix d'achat Arckx
B79: Dimensions extérieures caisse | C79: =C77+VLOOKUP(C21,A268:B270,2)+VLOOKUP(C13,A247:E249,5)*2+VLOOKUP(C15,A251:D252,4)*2 -> 107.1 | D79: =IF(OR($F$23="Aucun",$F$23="Stalilisateur"),$D$77+VLOOKUP($C$13,$A$247:$E$249,4)*2+VLOOKUP($C$15,$A$251:$D$252,4)*2+0.5,$E$77+VLOOKUP($C$13,$A$247:$E$249,5)*2+VLOOKUP($C$15,$A$251:$D$252,4)*2) -> 93.1 | E79: =IF(OR($F$23="Aucun",$F$23="Stabilisateur"),$E$77+VLOOKUP($C$13,$A$247:$E$249,5)*2+VLOOKUP($C$15,$A$251:$D$252,4)*2+VLOOKUP($C$23,$A$296:$B$298,2),$D$77+VLOOKUP($C$13,$A$247:$E$249,4)*2+VLOOKUP($C$15,$A$251:$D$252,4)*2+VLOOKUP($C$23,$A$296:$B$298,2)+VLOOKUP($F$23,$A$272:$D$275,4)+0.5) -> 86.9 | F79: =ROUNDUP(C244,0) -> 918
B81: Poids de la Caisse | C81: =Q236 -> 74.936374 | D81: Kg | E81: Bilan Carbone
B82: Minutes de Production | C82: =D238 -> 271.75585 | D82: Min | E82: =R236 -> 79.123893
B84: Commentaires
F89: Quantité | Q89: Poids KG | R89: CO²
A90: Grand côtés | B90: =VLOOKUP(C13,A247:D249,2) -> Peuplier 15 mm | C90: =IF(C77=0,0,C77+2*(VLOOKUP(B91,A247:D249,4)+VLOOKUP(C15,A251:D252,4))) -> 102.9 | D90: =IF(E77=0,0,E77+2*(VLOOKUP(B92,A247:D249,4)+VLOOKUP(C15,A251:D252,4))) -> 83.9 | E90: =B90 -> Peuplier 15 mm | F90: 2 | J90: =IF(C90=0,0,(C90/100)*(D90/100)*F90) -> 1.726662 | K90: =J90/0.8 -> 2.1583275 | L90: =IF(E90=0,0,VLOOKUP(E90,'Prix Matiere'!$A$4:$J$65,10)) -> 16.895876 | M90: =L90*K90-IF($F$15="Non",K90*0.75,0) -> 36.466834 | N90: =IF(J90=0,0,IF($F$15="Oui",(7.0924*J90)+15,(6.0924*J90)+10)) -> 27.246178 | O90: =N90*MinuteMO -> 23.159251 | Q90: =IF(J90=0,0,J90*VLOOKUP(E90,'Prix Matiere'!$A$4:$L$60,12)) -> 11.395969 | R90: =IF(J90=0,0,Q90*VLOOKUP(E90,'Prix Matiere'!$A$4:$L$60,11)) -> 8.8090842
A91: Dessus dessous | B91: =VLOOKUP(C13,A247:D249,3) -> Peuplier 15 mm | C91: =C90 -> 102.9 | D91: =D77 -> 85.4 | E91: =B91 -> Peuplier 15 mm | F91: 2 | J91: =IF(C91=0,0,(C91/100)*(D91/100)*F91) -> 1.757532 | K91: =J91/0.8 -> 2.196915 | L91: =IF(E91=0,0,VLOOKUP(E91,'Prix Matiere'!$A$4:$J$65,10)) -> 16.895876 | M91: =L91*K91-IF($F$15="Non",K91*0.75,0) -> 37.118804 | N91: =IF(J91=0,0,IF($F$15="Oui",(7.0924*J91)+15,(6.0924*J91)+10)) -> 27.46512 | O91: =N91*MinuteMO -> 23.345352 | Q91: =IF(J91=0,0,J91*VLOOKUP(E91,'Prix Matiere'!$A$4:$L$60,12)) -> 11.599711 | R91: =IF(J91=0,0,Q91*VLOOKUP(E91,'Prix Matiere'!$A$4:$L$60,11)) -> 8.9665768
A92: Bouts | B92: =VLOOKUP(C13,A247:D249,3) -> Peuplier 15 mm | C92: =E77 -> 76.7 | D92: =D77 -> 85.4 | E92: =B92 -> Peuplier 15 mm | F92: 2 | J92: =IF(C92=0,0,(C92/100)*(D92/100)*F92) -> 1.310036 | K92: =J92/0.8 -> 1.637545 | L92: =IF(E92=0,0,VLOOKUP(E92,'Prix Matiere'!$A$4:$J$65,10)) -> 16.895876 | M92: =L92*K92-IF($F$15="Non",K92*0.75,0) -> 27.667758 | N92: =IF(J92=0,0,IF($F$15="Oui",(7.0924*J92)+15,(6.0924*J92)+10)) -> 24.291299 | O92: =N92*MinuteMO -> 20.647604 | Q92: =IF(J92=0,0,J92*VLOOKUP(E92,'Prix Matiere'!$A$4:$L$60,12)) -> 8.6462376 | R92: =IF(J92=0,0,Q92*VLOOKUP(E92,'Prix Matiere'!$A$4:$L$60,11)) -> 6.6835417
J93: =IF(C93=0,0,(C93/100)*(D93/100)*F93) -> 0 | K93: =J93/0.8 -> 0 | Q93: =IF(J93=0,0,J93*VLOOKUP(E93,'Prix Matiere'!$A$4:$L$60,12)) -> 0
J94: =IF(C94=0,0,(C94/100)*(D94/100)*F94) -> 0 | K94: =J94/0.8 -> 0 | Q94: =IF(J94=0,0,J94*VLOOKUP(E94,'Prix Matiere'!$A$4:$L$60,12)) -> 0
A95: Barres | B95: Barres de GC | C95: =C90 -> 102.9 | D95: =IF(D90>80,9.4,7) -> 9.4 | E95: =IF($C$15="Pin raboté 4 faces","Barres 21 R4F","Barres 19 mm") -> Barres 21 R4F | F95: 4 | J95: =IF(C95=0,0,(C95/100)*(D95/100)*F95) -> 0.386904 | K95: =J95/0.8 -> 0.48363 | L95: =IF(E95=0,0,VLOOKUP(E95,'Prix Matiere'!$A$4:$J$65,10)) -> 18.969072 | M95: =L95*K95 -> 9.1740124 | N95: =IF(J95=0,0,1+(11*J95)) -> 5.255944 | O95: =N95*MinuteMO -> 4.4675524 | Q95: =IF(J95=0,0,J95*VLOOKUP(E95,'Prix Matiere'!$A$4:$L$60,12)) -> 3.86904 | R95: =IF(J95=0,0,Q95*VLOOKUP(E95,'Prix Matiere'!$A$4:$L$60,11)) -> 1.8726154
B96: Remplis GC | C96: =IF(D90=0,0,D90-2*D95) -> 65.1 | D96: =D95 -> 9.4 | E96: =IF($C$15="Pin raboté 4 faces","Barres 21 R4F","Barres 19 mm") -> Barres 21 R4F | F96: =4 -> 4 | J96: =IF(C96=0,0,(C96/100)*(D96/100)*F96) -> 0.244776 | K96: =J96/0.8 -> 0.30597 | L96: =IF(E96=0,0,VLOOKUP(E96,'Prix Matiere'!$A$4:$J$65,10)) -> 18.969072 | M96: =L96*K96 -> 5.803967 | N96: =IF(J96=0,0,1+(11*J96)) -> 3.692536 | O96: =N96*MinuteMO -> 3.1386556 | Q96: =IF(J96=0,0,J96*VLOOKUP(E96,'Prix Matiere'!$A$4:$L$60,12)) -> 2.44776 | R96: =IF(J96=0,0,Q96*VLOOKUP(E96,'Prix Matiere'!$A$4:$L$60,11)) -> 1.1847158
B97: Dessus / Dessous | C97: =C95 -> 102.9 | D97: =IF($D$77<14.4,$D$77,7) -> 7 | E97: =IF($C$15="Pin raboté 4 faces","Barres 21 R4F","Barres 19 mm") -> Barres 21 R4F | F97: =IF(D77<14.4,2,4) -> 4 | J97: =IF(C97=0,0,(C97/100)*(D97/100)*F97) -> 0.28812 | K97: =J97/0.8 -> 0.36015 | L97: =IF(E97=0,0,VLOOKUP(E97,'Prix Matiere'!$A$4:$J$65,10)) -> 18.969072 | M97: =L97*K97 -> 6.8317113 | N97: =IF(J97=0,0,1+(11*J97)) -> 4.16932 | O97: =N97*MinuteMO -> 3.543922 | Q97: =IF(J97=0,0,J97*VLOOKUP(E97,'Prix Matiere'!$A$4:$L$60,12)) -> 2.8812 | R97: =IF(J97=0,0,Q97*VLOOKUP(E97,'Prix Matiere'!$A$4:$L$60,11)) -> 1.3945008
B98: =C23 -> Skis | C98: =IF(C90=0,0,IF(B98="Skis",C97-10,IF(B98="10 dessous en semelles",D79,IF(B98="10 dessous en skis",(C97-70)/2)))) -> 92.9 | D98: =IF($F$10="BOVIS",9.4,7) -> 7 | E98: =IF($C$23="Skis","Barres 30 R4F","Semelles R4F") -> Barres 30 R4F | F98: =IF(B98="Skis",2,IF(B98="10 dessous en semelles",2,F97)) -> 2 | J98: =IF(C98=0,0,(C98/100)*(D98/100)*F98) -> 0.13006 | K98: =J98/0.8 -> 0.162575 | L98: =IF(E98=0,0,VLOOKUP(E98,'Prix Matiere'!$A$4:$J$65,10)) -> 45.43299 | M98: =L98*K98 -> 7.3862683 | N98: =IF(J98=0,0,1+(11*J98)) -> 2.43066 | O98: =N98*MinuteMO -> 2.066061 | Q98: =IF(J98=0,0,J98*VLOOKUP(E98,'Prix Matiere'!$A$4:$L$60,12)) -> 1.3006 | R98: =IF(J98=0,0,Q98*VLOOKUP(E98,'Prix Matiere'!$A$4:$L$60,11)) -> 0.6294904
B99: Longueur Bouts | C99: =IF(D77<14.4,0,D77) -> 85.4 | D99: =IF(D77<14.4,0,D95) -> 9.4 | E99: =IF($C$15="Pin raboté 4 faces","Barres 21 R4F","Barres 19 mm") -> Barres 21 R4F | F99: =IF(D77<14.4,0,4) -> 4 | J99: =IF(C99=0,0,(C99/100)*(D99/100)*F99) -> 0.321104 | K99: =J99/0.8 -> 0.40138 | L99: =IF(E99=0,0,VLOOKUP(E99,'Prix Matiere'!$A$4:$J$65,10)) -> 18.969072 | M99: =L99*K99 -> 7.6138062 | N99: =IF(J99=0,0,1+(11*J99)) -> 4.532144 | O99: =N99*MinuteMO -> 3.8523224 | Q99: =IF(J99=0,0,J99*VLOOKUP(E99,'Prix Matiere'!$A$4:$L$60,12)) -> 3.21104 | R99: =IF(J99=0,0,Q99*VLOOKUP(E99,'Prix Matiere'!$A$4:$L$60,11)) -> 1.5541434
B100: Hauteur Bouts | C100: =IF(D77<14.4,E77,C92-2*D99) -> 57.9 | D100: =IF($D$77<14.4,$D$77,IF($D$77<20,5,7)) -> 7 | E100: =IF($C$15="Pin raboté 4 faces","Barres 21 R4F","Barres 19 mm") -> Barres 21 R4F | F100: =IF(D77<14.4,2,4) -> 4 | J100: =IF(C100=0,0,(C100/100)*(D100/100)*F100) -> 0.16212 | K100: =J100/0.8 -> 0.20265 | L100: =IF(E100=0,0,VLOOKUP(E100,'Prix Matiere'!$A$4:$J$65,10)) -> 18.969072 | M100: =L100*K100 -> 3.8440825 | N100: =IF(J100=0,0,1+(11*J100)) -> 2.78332 | O100: =N100*MinuteMO -> 2.365822 | Q100: =IF(J100=0,0,J100*VLOOKUP(E100,'Prix Matiere'!$A$4:$L$60,12)) -> 1.6212 | R100: =IF(J100=0,0,Q100*VLOOKUP(E100,'Prix Matiere'!$A$4:$L$60,11)) -> 0.7846608
B101: =IF(D77<14.4,0,IF(C21="Bois","Poignées",IF(C21="Métal x 2 sur bouts","Supports poignées",0))) -> Poignées | C101: =IF(B101="Poignées",D92+VLOOKUP(C13,A247:D249,4)*2+4.2,IF(B101="Supports poignées",D92-2*D100,0)) -> 92.6 | D101: =IF(B101="Poignées",7,IF(B101="Supports poignées",9.4,0)) -> 7 | E101: Barres 21 R4F | F101: =IF(B101=0,0,2) -> 2 | J101: =IF(C101=0,0,(C101/100)*(D101/100)*F101) -> 0.12964 | K101: =J101/0.8 -> 0.16205 | L101: =IF(E101=0,0,VLOOKUP(E101,'Prix Matiere'!$A$4:$J$65,10)) -> 18.969072 | M101: =L101*K101 -> 3.0739381 | N101: =IF(J101=0,0,1+(11*J101)) -> 2.42604 | O101: =N101*MinuteMO -> 2.062134 | Q101: =IF(J101=0,0,J101*VLOOKUP(E101,'Prix Matiere'!$A$4:$L$60,12)) -> 1.2964 | R101: =IF(J101=0,0,Q101*VLOOKUP(E101,'Prix Matiere'!$A$4:$L$60,11)) -> 0.6274576
Q102: =IF(J102=0,0,J102*VLOOKUP(E102,'Prix Matiere'!$A$4:$L$60,12)) -> 0
Q103: =IF(J103=0,0,J103*VLOOKUP(E103,'Prix Matiere'!$A$4:$L$60,12)) -> 0
A104: Mousse 1 | B104: GC | C104: =IF(F104=0,0,C77) -> 95.7 | D104: =IF(F104=0,0,E108+VLOOKUP($C$17,A257:P263,5)) -> 76.7 | E104: =VLOOKUP($C$17,A257:P263,6) -> PU 30 mm | F104: =VLOOKUP($C$17,A257:P263,7) -> 2 | J104: =IF(C104=0,0,(C104/100)*(D104/100)*F104) -> 1.468038 | K104: =J104/0.8 -> 1.8350475 | L104: =IF(E104=0,0,VLOOKUP(E104,'Prix Matiere'!$A$4:$J$65,10)) -> 8.3118241 | M104: =L104*K104 -> 15.252592 | N104: =IF(J104=0,0,(4.7283*J104)+3) -> 9.9413241 | O104: =N104*MinuteMO -> 8.4501255 | Q104: =IF(J104=0,0,J104*VLOOKUP(E104,'Prix Matiere'!$A$4:$L$60,12)) -> 1.1010285 | R104: =IF(J104=0,0,Q104*VLOOKUP(E104,'Prix Matiere'!$A$4:$L$60,11)) -> 2.972777
B105: Dessus dessous | C105: =IF(F105=0,0,C77) -> 95.7 | D105: =IF(F105=0,0,D108) -> 79.4 | E105: =IF($C$17="Aucun",0,VLOOKUP($C$17,A257:P263,6)) -> PU 30 mm | F105: =VLOOKUP($C$17,A257:P263,7) -> 2 | J105: =IF(C105=0,0,(C105/100)*(D105/100)*F105) -> 1.519716 | K105: =J105/0.8 -> 1.899645 | L105: =IF(E105=0,0,VLOOKUP(E105,'Prix Matiere'!$A$4:$J$65,10)) -> 8.3118241 | M105: =L105*K105 -> 15.789515 | N105: =IF(J105=0,0,(4.7283*J105)+3) -> 10.185673 | O105: =N105*MinuteMO -> 8.6578222 | Q105: =IF(J105=0,0,J105*VLOOKUP(E105,'Prix Matiere'!$A$4:$L$60,12)) -> 1.139787 | R105: =IF(J105=0,0,Q105*VLOOKUP(E105,'Prix Matiere'!$A$4:$L$60,11)) -> 3.0774249
B106: Bouts | C106: =IF(F106=0,0,E108) -> 70.7 | D106: =IF(F106=0,0,D108) -> 79.4 | E106: =IF($C$17="Aucun",0,VLOOKUP($C$17,A257:P263,6)) -> PU 30 mm | F106: =VLOOKUP($C$17,A257:P263,7) -> 2 | J106: =IF(C106=0,0,(C106/100)*(D106/100)*F106) -> 1.122716 | K106: =J106/0.8 -> 1.403395 | L106: =IF(E106=0,0,VLOOKUP(E106,'Prix Matiere'!$A$4:$J$65,10)) -> 8.3118241 | M106: =L106*K106 -> 11.664772 | N106: =IF(J106=0,0,(4.7283*J106)+3) -> 8.3085381 | O106: =N106*MinuteMO -> 7.0622574 | Q106: =IF(J106=0,0,J106*VLOOKUP(E106,'Prix Matiere'!$A$4:$L$60,12)) -> 0.842037 | R106: =IF(J106=0,0,Q106*VLOOKUP(E106,'Prix Matiere'!$A$4:$L$60,11)) -> 2.2734999
Q107: =IF(J107=0,0,J107*VLOOKUP(E107,'Prix Matiere'!$A$4:$L$60,12)) -> 0
A108: Dimensions intérieures mousse | C108: =C77-VLOOKUP(C17,A257:P263,5) -> 89.7 | D108: =D77-VLOOKUP(C17,A257:P263,5) -> 79.4 | E108: =E77-VLOOKUP(C17,A257:P263,5) -> 70.7 | Q108: =IF(J108=0,0,J108*VLOOKUP(E108,'Prix Matiere'!$A$4:$L$60,12)) -> 0
Q109: =IF(J109=0,0,J109*VLOOKUP(E109,'Prix Matiere'!$A$4:$L$60,12)) -> 0
A110: Extrudé 1 | B110: GC | C110: =IF(F110=0,0,C114+VLOOKUP(C17,A257:P263,8))-0.5 -> 89.2 | D110: =IF(F110=0,0,E114+VLOOKUP(C17,A257:P263,8))-0.5 -> 70.2 | E110: =VLOOKUP(C17,A257:P263,9) -> Styro 30 mm | F110: =VLOOKUP($C$17,A257:P263,10) -> 2 | J110: =IF(C110=0,0,(C110/100)*(D110/100)*F110) -> 1.252368 | K110: =J110/0.8 -> 1.56546 | L110: =IF(E110=0,0,VLOOKUP(E110,'Prix Matiere'!A4:J60,10)) -> 7.014433 | M110: =L110*K110 -> 10.980814 | N110: =IF(J110=0,0,(3.94*J110)+5) -> 9.9343299 | O110: =N110*MinuteMO -> 8.4441804 | Q110: =IF(J110=0,0,J110*VLOOKUP(E110,'Prix Matiere'!$A$4:$L$60,12)) -> 1.2774154 | R110: =IF(J110=0,0,Q110*VLOOKUP(E110,'Prix Matiere'!$A$4:$L$60,11)) -> 3.7683753
B111: Dessus dessous | C111: =IF(F111=0,0,C114+VLOOKUP(C17,A257:P263,8)) -> 89.7 | D111: =IF(F111=0,0,D114) -> 73.4 | E111: =VLOOKUP(C17,A257:P263,9) -> Styro 30 mm | F111: =VLOOKUP($C$17,A257:P263,10) -> 2 | J111: =IF(C111=0,0,(C111/100)*(D111/100)*F111) -> 1.316796 | K111: =J111/0.8 -> 1.645995 | L111: =IF(E111=0,0,VLOOKUP(E111,'Prix Matiere'!A5:J61,10)) -> 7.014433 | M111: =L111*K111 -> 11.545722 | N111: =IF(J111=0,0,(3.94*J111)+5) -> 10.188176 | O111: =N111*MinuteMO -> 8.6599498 | Q111: =IF(J111=0,0,J111*VLOOKUP(E111,'Prix Matiere'!$A$4:$L$60,12)) -> 1.3431319 | R111: =IF(J111=0,0,Q111*VLOOKUP(E111,'Prix Matiere'!$A$4:$L$60,11)) -> 3.9622392
B112: Bouts | C112: =IF(F112=0,0,E114) -> 64.7 | D112: =IF(F112=0,0,D114) -> 73.4 | E112: =VLOOKUP(C17,A257:P263,9) -> Styro 30 mm | F112: =VLOOKUP($C$17,A257:P263,10) -> 2 | J112: =IF(C112=0,0,(C112/100)*(D112/100)*F112) -> 0.949796 | K112: =J112/0.8 -> 1.187245 | L112: =IF(E112=0,0,VLOOKUP(E112,'Prix Matiere'!A6:J62,10)) -> 7.014433 | M112: =L112*K112 -> 8.3278505 | N112: =IF(J112=0,0,(3.94*J112)+5) -> 8.7421962 | O112: =N112*MinuteMO -> 7.4308668 | Q112: =IF(J112=0,0,J112*VLOOKUP(E112,'Prix Matiere'!$A$4:$L$60,12)) -> 0.96879192 | R112: =IF(J112=0,0,Q112*VLOOKUP(E112,'Prix Matiere'!$A$4:$L$60,11)) -> 2.8579362
Q113: =IF(J113=0,0,J113*VLOOKUP(E113,'Prix Matiere'!$A$4:$L$60,12)) -> 0
A114: Dimensions intérieures styro | C114: =C108-VLOOKUP(C17,A257:P263,8) -> 83.7 | D114: =D108-VLOOKUP(C17,A257:P263,8) -> 73.4 | E114: =E108-VLOOKUP(C17,A257:P263,8) -> 64.7 | Q114: =IF(J114=0,0,J114*VLOOKUP(E114,'Prix Matiere'!$A$4:$L$60,12)) -> 0
Q115: =IF(J115=0,0,J115*VLOOKUP(E115,'Prix Matiere'!$A$4:$L$60,12)) -> 0
A116: Plaquettes | B116: GC | C116: =IF(F116=0,0,C119) -> 81.2 | D116: =IF(F116=0,0,10) -> 10 | E116: =VLOOKUP(C17,A257:P263,12) -> Peuplier 10 mm | F116: =VLOOKUP(C17,A257:P263,13) -> 4 | J116: =IF(C116=0,0,(C116/100)*(D116/100)*F116) -> 0.3248 | K116: =J116/0.8 -> 0.406 | L116: =IF(E116=0,0,VLOOKUP(E116,'Prix Matiere'!$A$4:$J$65,10)) -> 13.071134 | M116: =L116*K116 -> 5.3068804 | N116: =IF(J116=0,0,1+(6*J116)) -> 2.9488 | O116: =N116*MinuteMO -> 2.50648 | Q116: =IF(J116=0,0,J116*VLOOKUP(E116,'Prix Matiere'!$A$4:$L$60,12)) -> 1.33168 | R116: =IF(J116=0,0,Q116*VLOOKUP(E116,'Prix Matiere'!$A$4:$L$60,11)) -> 1.0293886
B117: Dessus dessous | C117: =IF(F117=0,0,D114) -> 73.4 | D117: =IF(F116=0,0,D116) -> 10 | E117: =VLOOKUP(C17,A257:P263,12) -> Peuplier 10 mm | F117: =VLOOKUP(C17,A257:P263,13)*2 -> 8 | J117: =IF(C117=0,0,(C117/100)*(D117/100)*F117) -> 0.5872 | K117: =J117/0.8 -> 0.734 | L117: =IF(E117=0,0,VLOOKUP(E117,'Prix Matiere'!$A$4:$J$65,10)) -> 13.071134 | M117: =L117*K117 -> 9.5942124 | N117: =IF(J117=0,0,1+(6*J117)) -> 4.5232 | O117: =N117*MinuteMO -> 3.84472 | Q117: =IF(J117=0,0,J117*VLOOKUP(E117,'Prix Matiere'!$A$4:$L$60,12)) -> 2.40752 | R117: =IF(J117=0,0,Q117*VLOOKUP(E117,'Prix Matiere'!$A$4:$L$60,11)) -> 1.861013
Q118: =IF(J118=0,0,J118*VLOOKUP(E118,'Prix Matiere'!$A$4:$L$60,12)) -> 0
A119: Dimensions intérieures plaquettes | C119: =C114-VLOOKUP($C$17,A257:P263,11) -> 81.2 | D119: =D114-VLOOKUP($C$17,A257:P263,11) -> 70.9 | E119: =E114-VLOOKUP($C$17,A257:P263,11) -> 62.2 | Q119: =IF(J119=0,0,J119*VLOOKUP(E119,'Prix Matiere'!$A$4:$L$60,12)) -> 0
Q120: =IF(J120=0,0,J120*VLOOKUP(E120,'Prix Matiere'!$A$4:$L$60,12)) -> 0
A121: Extrudé 2 | B121: GC | C121: =IF(F121=0,0,C125+VLOOKUP($C$17,A257:P263,14)) -> 81.2 | D121: =IF(F121=0,0,E125+VLOOKUP($C$17,A257:P263,14)) -> 62.2 | E121: =VLOOKUP($C$17,A257:P263,15) -> Styro 30 mm | F121: =VLOOKUP($C$17,A257:P263,16) -> 2 | J121: =IF(C121=0,0,(C121/100)*(D121/100)*F121) -> 1.010128 | K121: =J121/0.8 -> 1.26266 | L121: =IF(E121=0,0,VLOOKUP(E121,'Prix Matiere'!A4:J60,10)) -> 7.014433 | M121: =L121*K121 -> 8.856844 | N121: =IF(J121=0,0,(3.94*J121)+5) -> 8.9799043 | O121: =N121*MinuteMO -> 7.6329187 | Q121: =IF(J121=0,0,J121*VLOOKUP(E121,'Prix Matiere'!$A$4:$L$60,12)) -> 1.0303306 | R121: =IF(J121=0,0,Q121*VLOOKUP(E121,'Prix Matiere'!$A$4:$L$60,11)) -> 3.0394752
B122: Dessus dessous | C122: =IF(F122=0,0,C125+VLOOKUP($C$17,A257:P263,14)) -> 81.2 | D122: =IF(F122=0,0,D125) -> 64.9 | E122: =VLOOKUP($C$17,A257:P263,15) -> Styro 30 mm | F122: =VLOOKUP($C$17,A257:P263,16) -> 2 | J122: =IF(C122=0,0,(C122/100)*(D122/100)*F122) -> 1.053976 | K122: =J122/0.8 -> 1.31747 | L122: =IF(E122=0,0,VLOOKUP(E122,'Prix Matiere'!A5:J61,10)) -> 7.014433 | M122: =L122*K122 -> 9.241305 | N122: =IF(J122=0,0,(3.94*J122)+5) -> 9.1526654 | O122: =N122*MinuteMO -> 7.7797656 | Q122: =IF(J122=0,0,J122*VLOOKUP(E122,'Prix Matiere'!$A$4:$L$60,12)) -> 1.0750555 | R122: =IF(J122=0,0,Q122*VLOOKUP(E122,'Prix Matiere'!$A$4:$L$60,11)) -> 3.1714138
...

Sheet T1-T6 + Caissons
A1: Caisse Objet et Caissons Tableaux de 2 à 6 Œuvres
E3: =IF(C19="Boulons et platines","Boulons et Platines GC",0) -> 0 | F3: =IF(E3="Boulons et Platines GC","Nbre de Trous",0) -> 0 | G3: =IF(E3="Boulons et Platines GC","Dim du Bord",0) -> 0 | H3: =IF(C19="Boulons et platines","Boulons et Platines CV",0) -> 0 | I3: =IF(H3="Boulons et Platines CV","Nbre de Trous",0) -> 0 | J3: =IF(H3="Boulons et Platines CV","Dim du Bord",0) -> 0
E4: =IF(C19="Vis bois",0,"Trous dans la Longueur") -> 0 | F4: =IF(E4=0,0,IF(C91<100,2,IF(C91<150,3,IF(C91<200,4,IF(C91<250,5,IF(C91<300,6,7)))))) -> 0 | G4: =IF(F4=0,0,IF(F4=2,0,IF(F4=3,0,(($C$91-32)/(F4-1))+16))) -> 0 | H4: =IF(C19="Vis bois",0,"Trous dans la Longueur") -> 0 | I4: =IF(H4=0,0,IF(C92<100,2,IF(C92<150,3,IF(C92<200,4,IF(C92<250,5,IF(E51<300,6,7)))))) -> 0 | J4: =IF(I4=0,0,IF(I4=2,0,IF(I4=3,0,(($C$92-32)/(I4-1))+16))) -> 0
E5: =IF(F4=6,"2ème Trou",IF(F4=7,"2ème Trou",0)) -> 0 | G5: =IF(E5=0,0,G4+G4-16) -> 0 | H5: =IF(I4=6,"2ème Trou",IF(I4=7,"2ème Trou",0)) -> 0 | J5: =IF(H5=0,0,J4+J4-16) -> 0
E6: =IF(C19="Vis bois",0,"Trous dans la Hauteur") -> 0 | F6: =IF(E6=0,0,IF(D91<100,2,IF(D91<150,3,IF(D91<200,4,IF(D91<250,5,IF(D91<310,6,7)))))) -> 0 | G6: =IF(F6=0,0,IF(F6=2,0,IF(F6=3,0,(($D$91-32)/(F6-1))+16))) -> 0 | H6: =IF(C19="Vis bois",0,"Trous dans la Largeur") -> 0 | I6: =IF(H6=0,0,IF(D92<50,1,IF(D92<100,2,IF(D92<150,3,IF(D92<200,4,IF(D92<250,5,IF(D92<310,6,7))))))) -> 0 | J6: =IF(I6=0,0,IF(I6=1,0,IF(I6=2,0,IF(I6=3,0,(($D$92-32)/(I6-1))+16)))) -> 0
E7: =IF(F6=6,"2ème Trou",IF(F6=7,"2ème Trou",0)) -> 0 | G7: =IF(E7=0,0,G6+G6-16) -> 0 | H7: =IF(I6=6,"2ème Trou",IF(I6=7,"2ème Trou",0)) -> 0 | J7: =IF(H7=0,0,J6+J6-16) -> 0
B9: N° de dossier | E9: Responsable Dossier | F9: Grégory MORA
B10: Ville de destination | E10: Client | F10: ESI
B11: N° de caisse | E11: Délai
B13: Type de Contreplaqué | C13: Peuplier 15 mm
H14: =VLOOKUP($F$10,'Infos Clients'!$B$2:$G$10,2) -> #VALUE!
B15: Barres | C15: Pin raboté 4 faces | E15: Garnissage Valsem | F15: Oui
B17: Type d'isolant | C17: Aucun
B19: Fermeture | C19: Vis bois | E19: Peinture | F19: Non
E20: =IF(F19="Oui","Type de Peinture",0) -> 0 | F20: =IF(F19="Non",0,VLOOKUP(F10,'Infos Clients'!B2:E10,4)) -> 0
B21: Poignées | C21: Bois | E21: Tyvek | F21: Non
B23: Skis | C23: 10 dessous en skis | E23: Option Calage | F23: Aucun
B24: =IF(F23="Aucun"," ",F23) | D24: =IF(F21="Oui","+",0) -> 0 | E24: =IF(F21="Oui","Mousse Garnie Tyvek",0) -> 0
B25: =IF(F10="Bovis","Attention retirer 2 mm aux dimensions transmises",0) -> 0
A27: =IF(B28="Aucun","Dimensions intérieures utiles","Dimensions de l'œuvre") -> Dimensions de l'œuvre | B27: Longueur | C27: Epaisseur | D27: Hauteur | E27: Mousse de Calage 1 | G27: =IF(H28="Aucun","Dimensions intérieures utiles","Dimensions de l'œuvre") -> Dimensions de l'œuvre | H27: Longueur | I27: Epaisseur | J27: Hauteur | K27: Mousse de Calage 2
A29: Type de calage | B29: Aucun | C29: N° d'inventaire | G29: Type de calage | H29: Aucun | I29: N° d'inventaire
B30: Largeur | C30: Longueur | D30: Epaisseur | E30: Quantité | H30: Largeur | I30: Longueur | J30: Epaisseur | K30: Quantité
A31: Dessus | G31: Dessus
A32: Dessous | G32: Dessous
A33: Ethafoam 50 mm | B33: =+IF(B28=0,0,IF(B28>70,12,6)) -> 0 | E33: =IF(B28>300,6,IF(B28>250,5,IF(B28>200,4,IF(B28>150,3,IF(B28>120,3,2))))) -> 2 | G33: Ethafoam 50 mm | H33: =+IF(H28=0,0,IF(H28>70,12,6)) -> 0 | K33: =IF(H28>300,6,IF(H28>250,5,IF(H28>200,4,IF(H28>150,3,IF(H28>120,3,2))))) -> 2
A34: Rattrapage | G34: Rattrapage
A35: Remplissage 1 | G35: Remplissage 1
A36: Remplissage 2 | G36: Remplissage 2
A37: Dims nécéssaires | B37: =IF(B28=0,0,B28+VLOOKUP(B29,$A$292:$L$297,2)) -> 0 | C37: =IF(C28=0,0,C28+VLOOKUP(B29,$A$292:$L$297,3)) -> 0 | D37: =IF(D28=0,0,D28+VLOOKUP(B29,$A$292:$L$297,4)) -> 0 | G37: Dims nécéssaires | H37: =IF(H28=0,0,H28+VLOOKUP(H29,$A$292:$L$297,2)) -> 0 | I37: =IF(I28=0,0,I28+VLOOKUP(H29,$A$292:$L$297,3)) -> 0 | J37: =IF(J28=0,0,J28+VLOOKUP(H29,$A$292:$L$297,4)) -> 0
G39: Dims int Caisson | H39: =IF(H41=0,0,H40-3) -> 0 | I39: =IF(I41=0,0,I40-3.5) -> 0 | J39: =IF(J41=0,0,J40-3) -> 0
A40: Dims necessaire Caissons 1 | B40: =B37+IF(H37=0,0,1.5+H37) -> 0 | C40: =MAX(C37,I37) -> 0 | D40: =MAX(D37,J37) -> 0 | G40: Dims ext Caisson | H40: =IF(H41=0,0,H41) -> 0 | I40: =IF(I41=0,0,I41) -> 0 | J40: =IF(J41=0,0,J41) -> 0
G41: Dims nec caisse | H41: =IF(B40=0,0,MAX(B40+3,B56+3,B72+3)) -> 0 | I41: =IF(C40=0,0,C40+3.5) -> 0 | J41: =IF(D40=0,0,MAX(D40+3,D56+3,D72+3)) -> 0
A43: =IF(B44="Aucun","Dimensions intérieures utiles","Dimensions de l'œuvre") -> Dimensions de l'œuvre | B43: Longueur | C43: Epaisseur | D43: Hauteur | E43: Mousse de Calage 3 | G43: =IF(H44="Aucun","Dimensions intérieures utiles","Dimensions de l'œuvre") -> Dimensions de l'œuvre | H43: Longueur | I43: Epaisseur | J43: Hauteur | K43: Mousse de Calage 4
A45: Type de calage | B45: Aucun | C45: N° d'inventaire | G45: Type de calage | H45: Aucun | I45: N° d'inventaire
B46: Largeur | C46: Longueur | D46: Epaisseur | E46: Quantité | H46: Largeur | I46: Longueur | J46: Epaisseur | K46: Quantité
A47: Dessus | G47: Dessus
A48: Dessous | G48: Dessous
A49: Ethafoam 50 mm | B49: =+IF(B44=0,0,IF(B44>70,12,6)) -> 0 | E49: =IF(B44>300,6,IF(B44>250,5,IF(B44>200,4,IF(B44>150,3,IF(B44>120,3,2))))) -> 2 | G49: Ethafoam 50 mm | H49: =+IF(H44=0,0,IF(H44>70,12,6)) -> 0 | K49: =IF(H44>300,6,IF(H44>250,5,IF(H44>200,4,IF(H44>150,3,IF(H44>120,3,2))))) -> 2
A50: Rattrapage | G50: Rattrapage
A51: Remplissage 1 | G51: Remplissage 1
A52: Remplissage 2 | G52: Remplissage 2
A53: Dims nécéssaires | B53: =IF(B44=0,0,B44+VLOOKUP(B45,$A$292:$L$297,2)) -> 0 | C53: =IF(C44=0,0,C44+VLOOKUP(B45,$A$292:$L$297,3)) -> 0 | D53: =IF(D44=0,0,D44+VLOOKUP(B45,$A$292:$L$297,4)) -> 0 | G53: Dims nécéssaires | H53: =IF(H44=0,0,H44+VLOOKUP(H45,$A$292:$L$297,2)) -> 0 | I53: =IF(I44=0,0,I44+VLOOKUP(H45,$A$292:$L$297,3)) -> 0 | J53: =IF(J44=0,0,J44+VLOOKUP(H45,$A$292:$L$297,4)) -> 0
G55: Dims int Caisson | H55: =IF(H57=0,0,H56-3) -> 0 | I55: =IF(I57=0,0,I56-3.5) -> 0 | J55: =IF(J57=0,0,J56-3) -> 0
A56: Dims nécéssaire Caisson 2 | B56: =B53+IF(H53=0,0,1.5+H53) -> 0 | C56: =MAX(C53,I53) -> 0 | D56: =MAX(D53,J53) -> 0 | G56: Dims ext Caisson | H56: =IF(H57=0,0,H57) -> 0 | I56: =IF(I57=0,0,I57) -> 0 | J56: =IF(J57=0,0,J57) -> 0
G57: Dims nec caisse | H57: =IF(B56=0,0,MAX(B40+3,B56+3,B72+3)) -> 0 | I57: =IF(C56=0,0,C56+3.5) -> 0 | J57: =IF(D56=0,0,MAX(D40+3,D56+3,D72+3)) -> 0
A59: =IF(B60="Aucun","Dimensions intérieures utiles","Dimensions de l'œuvre") -> Dimensions de l'œuvre | B59: Longueur | C59: Epaisseur | D59: Hauteur | E59: Mousse de Calage 5 | G59: =IF(H60="Aucun","Dimensions intérieures utiles","Dimensions de l'œuvre") -> Dimensions de l'œuvre | H59: Longueur | I59: Epaisseur | J59: Hauteur | K59: Mousse de Calage 6
A61: Type de calage | B61: Aucun | C61: N° d'inventaire | G61: Type de calage | H61: Aucun | I61: N° d'inventaire
B62: Largeur | C62: Longueur | D62: Epaisseur | E62: Quantité | H62: Largeur | I62: Longueur | J62: Epaisseur | K62: Quantité
A63: Dessus | G63: Dessus
A64: Dessous | G64: Dessous
A65: Ethafoam 50 mm | B65: =+IF(B60=0,0,IF(B60>70,12,6)) -> 0 | E65: =IF(B60>300,6,IF(B60>250,5,IF(B60>200,4,IF(B60>150,3,IF(B60>120,3,2))))) -> 2 | G65: Ethafoam 50 mm | H65: =+IF(H60=0,0,IF(H60>70,12,6)) -> 0 | K65: =IF(H60>300,6,IF(H60>250,5,IF(H60>200,4,IF(H60>150,3,IF(H60>120,3,2))))) -> 2
A66: Rattrapage | G66: Rattrapage
A67: Remplissage 1 | G67: Remplissage 1
A68: Remplissage 2 | G68: Remplissage 2
A69: Dims nécéssaires | B69: =IF(B60=0,0,B60+VLOOKUP(B61,$A$292:$L$297,2)) -> 0 | C69: =IF(C60=0,0,C60+VLOOKUP(B61,$A$292:$L$297,3)) -> 0 | D69: =IF(D60=0,0,D60+VLOOKUP(B61,$A$292:$L$297,4)) -> 0 | G69: Dims nécéssaires | H69: =IF(H60=0,0,H60+VLOOKUP(H61,$A$292:$L$297,2)) -> 0 | I69: =IF(I60=0,0,I60+VLOOKUP(H61,$A$292:$L$297,3)) -> 0 | J69: =IF(J60=0,0,J60+VLOOKUP(H61,$A$292:$L$297,4)) -> 0
G71: Dims int Caisson | H71: =IF(H73=0,0,H72-3) -> 0 | I71: =IF(I73=0,0,I72-3.5) -> 0 | J71: =IF(J73=0,0,J72-3) -> 0
A72: Dims nécéssaire Caisson 3 | B72: =B69+IF(H69=0,0,1.5+H69) -> 0 | C72: =MAX(C69,I69) -> 0 | D72: =MAX(D69,J69) -> 0 | G72: Dims ext Caisson | H72: =IF(H73=0,0,H73) -> 0 | I72: =IF(I73=0,0,I73) -> 0 | J72: =IF(J73=0,0,J73) -> 0
G73: Dims nec caisse | H73: =IF(B72=0,0,MAX(B40+3,B56+3,B72+3)) -> 0 | I73: =IF(C72=0,0,C72+3.5) -> 0 | J73: =IF(D72=0,0,MAX(D40+3,D56+3,D72+3)) -> 0
A75: Dims nécessaire caisse | C75: =MAX(H41,H57,H73) -> 0 | D75: =I41+I57+I73 -> 0 | E75: =MAX(J41,J57,J73) -> 0
B78: Dims intérieures caisse | C78: =IF(C75=0,0,C75+VLOOKUP(C17,$A$266:$P$272,2)) -> 0 | D78: =IF(D75=0,0,D75+VLOOKUP(C17,$A$266:$P$272,3)) -> 0 | E78: =IF(E75=0,0,E75+VLOOKUP(C17,$A$266:$P$272,4)) -> 0 | F78: Prix d'achat Arckx
B80: Dims extérieures caisse | C80: =C78+VLOOKUP(C21,A277:B279,2)+VLOOKUP(C13,A256:E258,5)*2+VLOOKUP(C15,A260:D261,4)*2 -> 11.4 | D80: =IF(OR($F$23="Aucun",$F$23="Stabilisateur"),$D$78+VLOOKUP($C$13,$A$256:$E$258,4)*2+VLOOKUP($C$15,$A$260:$D$261,4)*2+0.5,$E$78+VLOOKUP($C$13,$A$256:$E$258,5)*2+VLOOKUP($C$15,$A$260:$D$261,4)*2) -> 7.7 | E80: =IF(OR($F$23="Aucun",$F$23="Stabilisateur"),$E$78+VLOOKUP($C$13,$A$256:$E$258,5)*2+VLOOKUP($C$15,$A$260:$D$261,4)*2+VLOOKUP($C$23,$A$305:$B$307,2),$D$78+VLOOKUP($C$13,$A$256:$E$258,4)*2+VLOOKUP($C$15,$A$260:$D$261,4)*2+VLOOKUP($C$23,$A$305:$B$307,2)+VLOOKUP($F$23,$A$281:$D$284,4)+0.5) -> 17.2 | F80: =ROUNDUP(C253,0) -> 30
B82: Poids de la Caisse | C82: =Q245 -> -4.9159952 | D82: Kg | E82: Bilan Carbone
B83: Minutes de Production | C83: =D247 -> 34.217307 | D83: Min | E83: =R245 -> -2.3588791
B85: Commentaires
F90: Quantité | Q90: Poids KG | R90: CO²
A91: Grand côtés | B91: =VLOOKUP($C$13,$A$256:$E$258,2) -> Peuplier 15 mm | C91: =C78+2*(VLOOKUP(B91,$A$256:$E$257,4)+VLOOKUP($C$15,$A$260:$D$261,4)) -> 7.2 | D91: =E78+(VLOOKUP(B91,$A$256:$E$257,5)+VLOOKUP($C$15,$A$260:$D$261,4)) -> 3.6 | E91: =B91 -> Peuplier 15 mm | F91: 2 | J91: =IF(C91=0,0,(C91/100)*(D91/100)*F91) -> 0.005184 | K91: =J91/0.8 -> 0.00648 | L91: =IF(E91=0,0,VLOOKUP(E91,'Prix Matiere'!$A$4:$J$65,10)) -> 16.895876 | M91: =L91*K91-IF($F$15="Non",K91*0.75,0) -> 0.10948528 | N91: =IF(J91=0,0,IF($F$15="Oui",(7.0924*J91)+15,(6.0924*J91)+10)) -> 15.036767 | O91: =N91*MinuteMO -> 12.781252 | Q91: =IF(J91=0,0,J91*VLOOKUP(E91,'Prix Matiere'!$A$4:$L$60,12)) -> 0.0342144 | R91: =IF(J91=0,0,Q91*VLOOKUP(E91,'Prix Matiere'!$A$4:$L$60,11)) -> 0.026447731
A92: Couvercle | B92: =VLOOKUP($C$13,$A$256:$E$258,2) -> Peuplier 15 mm | C92: =C91 -> 7.2 | D92: =D78+2*(VLOOKUP(B92,A256:E257,4)+VLOOKUP($C$15,A260:D261,4))+0.5 -> 7.7 | E92: =B92 -> Peuplier 15 mm | F92: 1 | J92: =IF(C92=0,0,(C92/100)*(D92/100)*F92) -> 0.005544 | K92: =J92/0.8 -> 0.00693 | L92: =IF(E92=0,0,VLOOKUP(E92,'Prix Matiere'!$A$4:$J$65,10)) -> 16.895876 | M92: =L92*K92-IF($F$15="Non",K92*0.75,0) -> 0.11708842 | N92: =IF(J92=0,0,IF($F$15="Oui",(7.0924*J92)+15,(6.0924*J92)+10)) -> 15.03932 | O92: =N92*MinuteMO -> 12.783422 | Q92: =IF(J92=0,0,J92*VLOOKUP(E92,'Prix Matiere'!$A$4:$L$60,12)) -> 0.0365904 | R92: =IF(J92=0,0,Q92*VLOOKUP(E92,'Prix Matiere'!$A$4:$L$60,11)) -> 0.028284379
A93: Plateau | B93: =VLOOKUP($C$13,$A$256:$E$258,2) -> Peuplier 15 mm | C93: =C78 -> 0 | D93: =D78 -> 0 | E93: =B93 -> Peuplier 15 mm | F93: 1 | J93: =IF(C93=0,0,(C93/100)*(D93/100)*F93) -> 0 | K93: =J93/0.8 -> 0 | L93: =IF(E93=0,0,VLOOKUP(E93,'Prix Matiere'!$A$4:$J$65,10)) -> 16.895876 | M93: =L93*K93-IF($F$15="Non",K93*0.75,0) -> 0 | N93: =IF(J93=0,0,IF($F$15="Oui",(7.0924*J93)+15,(6.0924*J93)+10)) -> 0 | O93: =N93*MinuteMO -> 0 | Q93: =IF(J93=0,0,J93*VLOOKUP(E93,'Prix Matiere'!$A$4:$L$60,12)) -> 0 | R93: =IF(J93=0,0,Q93*VLOOKUP(E93,'Prix Matiere'!$A$4:$L$60,11)) -> 0
A94: Bouts | B94: =VLOOKUP($C$13,$A$256:$E$258,2) -> Peuplier 15 mm | C94: =D78 -> 0 | D94: =D91 -> 3.6 | E94: =B94 -> Peuplier 15 mm | F94: 2 | J94: =IF(C94=0,0,(C94/100)*(D94/100)*F94) -> 0 | K94: =J94/0.8 -> 0 | L94: =IF(E94=0,0,VLOOKUP(E94,'Prix Matiere'!$A$4:$J$65,10)) -> 16.895876 | M94: =L94*K94-IF($F$15="Non",K94*0.75,0) -> 0 | N94: =IF(J94=0,0,IF($F$15="Oui",(7.0924*J94)+15,(6.0924*J94)+10)) -> 0 | O94: =N94*MinuteMO -> 0 | Q94: =IF(J94=0,0,J94*VLOOKUP(E94,'Prix Matiere'!$A$4:$L$60,12)) -> 0 | R94: =IF(J94=0,0,Q94*VLOOKUP(E94,'Prix Matiere'!$A$4:$L$60,11)) -> 0
R95: =IF(Q95=0,0,J95*VLOOKUP(E95,'Prix Matiere'!$A$4:$L$60,11)) -> 0
R96: =IF(Q96=0,0,J96*VLOOKUP(E96,'Prix Matiere'!$A$4:$L$60,11)) -> 0
A97: Barres | B97: Barres de GC | C97: =C91 -> 7.2 | D97: =IF(D91>80,9.4,7) -> 7 | E97: =IF($C$15="Pin raboté 4 faces","Barres 21 R4F","Barres 19 mm") -> Barres 21 R4F | F97: 4 | J97: =IF(C97=0,0,(C97/100)*(D97/100)*F97) -> 0.02016 | K97: =J97/0.8 -> 0.0252 | L97: =IF(E97=0,0,VLOOKUP(E97,'Prix Matiere'!$A$4:$J$65,10)) -> 18.969072 | M97: =L97*K97 -> 0.47802062 | N97: =IF(J97=0,0,1+(11*J97)) -> 1.22176 | O97: =N97*MinuteMO -> 1.038496 | Q97: =IF(J97=0,0,J97*VLOOKUP(E97,'Prix Matiere'!$A$4:$L$60,12)) -> 0.2016 | R97: =IF(J97=0,0,Q97*VLOOKUP(E97,'Prix Matiere'!$A$4:$L$60,11)) -> 0.0975744
B98: Remplis GC | C98: =D91-2*D97 -> -10.4 | D98: =D97 -> 7 | E98: =IF($C$15="Pin raboté 4 faces","Barres 21 R4F","Barres 19 mm") -> Barres 21 R4F | F98: =4 -> 4 | J98: =IF(C98=0,0,(C98/100)*(D98/100)*F98) -> -0.02912 | K98: =J98/0.8 -> -0.0364 | L98: =IF(E98=0,0,VLOOKUP(E98,'Prix Matiere'!$A$4:$J$65,10)) -> 18.969072 | M98: =L98*K98 -> -0.69047423 | N98: =IF(J98=0,0,1+(11*J98)) -> 0.67968 | O98: =N98*MinuteMO -> 0.577728 | Q98: =IF(J98=0,0,J98*VLOOKUP(E98,'Prix Matiere'!$A$4:$L$60,12)) -> -0.2912 | R98: =IF(J98=0,0,Q98*VLOOKUP(E98,'Prix Matiere'!$A$4:$L$60,11)) -> -0.1409408
B99: Barres de CV | C99: =C97 -> 7.2 | D99: =IF($D$92<80,7,9.4) -> 7 | E99: =IF($C$15="Pin raboté 4 faces","Barres 21 R4F","Barres 19 mm") -> Barres 21 R4F | F99: =IF(D99<14.4,2,4) -> 2 | J99: =IF(C99=0,0,(C99/100)*(D99/100)*F99) -> 0.01008 | K99: =J99/0.8 -> 0.0126 | L99: =IF(E99=0,0,VLOOKUP(E99,'Prix Matiere'!$A$4:$J$65,10)) -> 18.969072 | M99: =L99*K99 -> 0.23901031 | N99: =IF(J99=0,0,1+(11*J99)) -> 1.11088 | O99: =N99*MinuteMO -> 0.944248 | Q99: =IF(J99=0,0,J99*VLOOKUP(E99,'Prix Matiere'!$A$4:$L$60,12)) -> 0.1008 | R99: =IF(J99=0,0,Q99*VLOOKUP(E99,'Prix Matiere'!$A$4:$L$60,11)) -> 0.0487872
B100: Remplis de CV | C100: =D92-2*D99 -> -6.3 | D100: =D99 -> 7 | E100: =IF($C$15="Pin raboté 4 faces","Barres 21 R4F","Barres 19 mm") -> Barres 21 R4F | F100: =IF(D100<14.4,2,4) -> 2 | J100: =IF(C100=0,0,(C100/100)*(D100/100)*F100) -> -0.00882 | K100: =J100/0.8 -> -0.011025 | L100: =IF(E100=0,0,VLOOKUP(E100,'Prix Matiere'!$A$4:$J$65,10)) -> 18.969072 | M100: =L100*K100 -> -0.20913402 | N100: =IF(J100=0,0,1+(11*J100)) -> 0.90298 | O100: =N100*MinuteMO -> 0.767533 | Q100: =IF(J100=0,0,J100*VLOOKUP(E100,'Prix Matiere'!$A$4:$L$60,12)) -> -0.0882 | R100: =IF(J100=0,0,Q100*VLOOKUP(E100,'Prix Matiere'!$A$4:$L$60,11)) -> -0.0426888
B101: Barres de plateau | C101: =C78 -> 0 | D101: 7 | E101: =IF($C$15="Pin raboté 4 faces","Barres 21 R4F","Barres 19 mm") -> Barres 21 R4F | F101: =IF(D83>70,3,2) -> 3 | J101: =IF(C101=0,0,(C101/100)*(D101/100)*F101) -> 0 | K101: =J101/0.8 -> 0 | L101: =IF(E101=0,0,VLOOKUP(E101,'Prix Matiere'!$A$4:$J$65,10)) -> 18.969072 | M101: =L101*K101 -> 0 | N101: =IF(J101=0,0,1+(11*J101)) -> 0 | O101: =N101*MinuteMO -> 0 | Q101: =IF(J101=0,0,J101*VLOOKUP(E101,'Prix Matiere'!$A$4:$L$60,12)) -> 0 | R101: =IF(J101=0,0,Q101*VLOOKUP(E101,'Prix Matiere'!$A$4:$L$60,11)) -> 0
B102: Remplis de plateau | C102: =(D78-(D101*F101))/(F101-1) -> -10.5 | D102: 7 | E102: =IF($C$15="Pin raboté 4 faces","Barres 21 R4F","Barres 19 mm") -> Barres 21 R4F | F102: =IF(F101=2,2,4) -> 4 | J102: =IF(C102=0,0,(C102/100)*(D102/100)*F102) -> -0.0294 | K102: =J102/0.8 -> -0.03675 | L102: =IF(E102=0,0,VLOOKUP(E102,'Prix Matiere'!$A$4:$J$65,10)) -> 18.969072 | M102: =L102*K102 -> -0.6971134 | N102: =IF(J102=0,0,1+(11*J102)) -> 0.6766 | O102: =N102*MinuteMO -> 0.57511 | Q102: =IF(J102=0,0,J102*VLOOKUP(E102,'Prix Matiere'!$A$4:$L$60,12)) -> -0.294 | R102: =IF(J102=0,0,Q102*VLOOKUP(E102,'Prix Matiere'!$A$4:$L$60,11)) -> -0.142296
B103: =C23 -> 10 dessous en skis | C103: =IF(B103="10 dessous en skis", (C97-70)/2,IF(B103="10 dessous en semelles",D92,C99-10)) -> -31.4 | D103: =IF($F$10="BOVIS",9.4,7) -> 7 | E103: =IF(B103="skis","Barres 30 R4F","Semelles R4F") -> Semelles R4F | F103: =IF(B103="10 dessous en skis",6,IF(B103="10 dessous en semelles",2,2)) -> 6 | J103: =IF(C103=0,0,(C103/100)*(D103/100)*F103) -> -0.13188 | K103: =J103/0.8 -> -0.16485 | L103: =IF(E103=0,0,VLOOKUP(E103,'Prix Matiere'!$A$4:$J$65,10)) -> 63.319588 | M103: =L103*K103 -> -10.438234 | N103: =IF(J103=0,0,1+(11*J103)) -> -0.45068 | O103: =N103*MinuteMO -> -0.383078 | Q103: =IF(J103=0,0,J103*VLOOKUP(E103,'Prix Matiere'!$A$4:$L$60,12)) -> -4.6158 | R103: =IF(J103=0,0,Q103*VLOOKUP(E103,'Prix Matiere'!$A$4:$L$60,11)) -> -2.2340472
B104: Longueur Bouts | C104: =IF($D$53<14.4,0,C94) -> 0 | D104: =IF(D83<14.4,0,D97) -> 7 | E104: =IF($C$15="Pin raboté 4 faces","Barres 21 R4F","Barres 19 mm") -> Barres 21 R4F | F104: =IF(D83<14.4,0,4) -> 4 | J104: =IF(C104=0,0,(C104/100)*(D104/100)*F104) -> 0 | K104: =J104/0.8 -> 0 | L104: =IF(E104=0,0,VLOOKUP(E104,'Prix Matiere'!$A$4:$J$65,10)) -> 18.969072 | M104: =L104*K104 -> 0 | N104: =IF(J104=0,0,1+(11*J104)) -> 0 | O104: =N104*MinuteMO -> 0 | Q104: =IF(J104=0,0,J104*VLOOKUP(E104,'Prix Matiere'!$A$4:$L$60,12)) -> 0 | R104: =IF(J104=0,0,Q104*VLOOKUP(E104,'Prix Matiere'!$A$4:$L$60,11)) -> 0
B105: Hauteur Bouts | C105: =IF(D83<14.4,E84,D94-2*D104) -> -10.4 | D105: =IF($D$78<14.4,$D$78,IF($D$78<20,5,7)) -> 0 | E105: =IF($C$15="Pin raboté 4 faces","Barres 21 R4F","Barres 19 mm") -> Barres 21 R4F | F105: =IF(D83<14.4,2,4) -> 4 | J105: =IF(C105=0,0,(C105/100)*(D105/100)*F105) -> 0 | K105: =J105/0.8 -> 0 | L105: =IF(E105=0,0,VLOOKUP(E105,'Prix Matiere'!$A$4:$J$65,10)) -> 18.969072 | M105: =L105*K105 -> 0 | N105: =IF(J105=0,0,1+(11*J105)) -> 0 | O105: =N105*MinuteMO -> 0 | Q105: =IF(J105=0,0,J105*VLOOKUP(E105,'Prix Matiere'!$A$4:$L$60,12)) -> 0 | R105: =IF(J105=0,0,Q105*VLOOKUP(E105,'Prix Matiere'!$A$4:$L$60,11)) -> 0
B106: =IF(D78<14.4,0,IF(C21="Bois","Poignées",IF(C21="Métal x 2 sur bouts","Supports poignées",0))) -> 0 | C106: =IF(B106="Poignées",D78+VLOOKUP(C13,A256:D257,4)*2+4.2,IF(B106="Supports poignées",D80-2*D105,0)) -> 0 | D106: =IF(B106="Poignées",7,IF(B106="Supports poignées",9.4,0)) -> 0 | E106: Barres 21 R4F | F106: =IF(B106=0,0,2) -> 0 | J106: =IF(C106=0,0,(C106/100)*(D106/100)*F106) -> 0 | K106: =J106/0.8 -> 0 | L106: =IF(E106=0,0,VLOOKUP(E106,'Prix Matiere'!$A$4:$J$65,10)) -> 18.969072 | M106: =L106*K106 -> 0 | N106: =IF(J106=0,0,1+(11*J106)) -> 0 | O106: =N106*MinuteMO -> 0 | Q106: =IF(J106=0,0,J106*VLOOKUP(E106,'Prix Matiere'!$A$4:$L$60,12)) -> 0 | R106: =IF(J106=0,0,Q106*VLOOKUP(E106,'Prix Matiere'!$A$4:$L$60,11)) -> 0
A109: Mousse 1 | B109: GC | C109: =IF(F109=0,0,C78) -> 0 | D109: =IF(F109=0,0,E113+VLOOKUP($C$17,A266:P272,5)) -> 0 | E109: =VLOOKUP($C$17,A266:P272,6) -> 0 | F109: =VLOOKUP($C$17,A266:P272,7) -> 0 | J109: =IF(C109=0,0,(C109/100)*(D109/100)*F109) -> 0 | K109: =J109/0.8 -> 0 | L109: =IF(E109=0,0,VLOOKUP(E109,'Prix Matiere'!$A$4:$J$65,10)) -> 0 | M109: =L109*K109 -> 0 | N109: =IF(J109=0,0,2+(6*J109)) -> 0 | O109: =N109*MinuteMO -> 0 | Q109: =IF(J109=0,0,J109*VLOOKUP(E109,'Prix Matiere'!$A$4:$L$60,12)) -> 0 | R109: =IF(J109=0,0,Q109*VLOOKUP(E109,'Prix Matiere'!$A$4:$L$60,11)) -> 0
B110: Dessus dessous | C110: =IF(F110=0,0,C78) -> 0 | D110: =IF(F110=0,0,D113) -> 0 | E110: =IF($C$17="Aucun",0,VLOOKUP($C$17,A266:P272,6)) -> 0 | F110: =VLOOKUP($C$17,A266:P272,7) -> 0 | J110: =IF(C110=0,0,(C110/100)*(D110/100)*F110) -> 0 | K110: =J110/0.8 -> 0 | L110: =IF(E110=0,0,VLOOKUP(E110,'Prix Matiere'!$A$4:$J$65,10)) -> 0 | M110: =L110*K110 -> 0 | N110: =IF(J110=0,0,2+(6*J110)) -> 0 | O110: =N110*MinuteMO -> 0 | Q110: =IF(J110=0,0,J110*VLOOKUP(E110,'Prix Matiere'!$A$4:$L$60,12)) -> 0 | R110: =IF(J110=0,0,Q110*VLOOKUP(E110,'Prix Matiere'!$A$4:$L$60,11)) -> 0
B111: Bouts | C111: =IF(F111=0,0,E113) -> 0 | D111: =IF(F111=0,0,D113) -> 0 | E111: =IF($C$17="Aucun",0,VLOOKUP($C$17,A266:P272,6)) -> 0 | F111: =VLOOKUP($C$17,A266:P272,7) -> 0 | J111: =IF(C111=0,0,(C111/100)*(D111/100)*F111) -> 0 | K111: =J111/0.8 -> 0 | L111: =IF(E111=0,0,VLOOKUP(E111,'Prix Matiere'!$A$4:$J$65,10)) -> 0 | M111: =L111*K111 -> 0 | N111: =IF(J111=0,0,2+(6*J111)) -> 0 | O111: =N111*MinuteMO -> 0 | Q111: =IF(J111=0,0,J111*VLOOKUP(E111,'Prix Matiere'!$A$4:$L$60,12)) -> 0 | R111: =IF(J111=0,0,Q111*VLOOKUP(E111,'Prix Matiere'!$A$4:$L$60,11)) -> 0
A113: Dimensions intérieures mousse | C113: =C78-VLOOKUP(C17,A266:P272,5) -> 0 | D113: =D78-VLOOKUP(C17,A266:P272,5) -> 0 | E113: =E78-VLOOKUP(C17,A266:P272,5) -> 0
A115: Extrudé 1 | B115: GC | C115: =IF(F115=0,0,C119+VLOOKUP(C17,A266:P272,8))-0.5 -> -0.5 | D115: =IF(F115=0,0,E119+VLOOKUP(C17,A266:P272,8))-0.5 -> -0.5 | E115: =VLOOKUP(C17,A266:P272,9) -> 0 | F115: =VLOOKUP($C$17,A266:P272,10) -> 0 | J115: =IF(C115=0,0,(C115/100)*(D115/100)*F115) -> 0 | K115: =J115/0.8 -> 0 | L115: =IF(E115=0,0,VLOOKUP(E115,'Prix Matiere'!A4:J60,10)) -> 0 | M115: =L115*K115 -> 0 | N115: =IF(J115=0,0,4+(5*J115)) -> 0 | O115: =N115*MinuteMO -> 0 | Q115: =IF(J115=0,0,J115*VLOOKUP(E115,'Prix Matiere'!$A$4:$L$60,12)) -> 0 | R115: =IF(J115=0,0,Q115*VLOOKUP(E115,'Prix Matiere'!$A$4:$L$60,11)) -> 0
B116: Dessus dessous | C116: =IF(F116=0,0,C119+VLOOKUP(C17,A266:P272,8)) -> 0 | D116: =IF(F116=0,0,D119) -> 0 | E116: =VLOOKUP(C17,A266:P272,9) -> 0 | F116: =VLOOKUP($C$17,A266:P272,10) -> 0 | J116: =IF(C116=0,0,(C116/100)*(D116/100)*F116) -> 0 | K116: =J116/0.8 -> 0 | L116: =IF(E116=0,0,VLOOKUP(E116,'Prix Matiere'!A5:J61,10)) -> 0 | M116: =L116*K116 -> 0 | N116: =IF(J116=0,0,4+(5*J116)) -> 0 | O116: =N116*MinuteMO -> 0 | Q116: =IF(J116=0,0,J116*VLOOKUP(E116,'Prix Matiere'!$A$4:$L$60,12)) -> 0 | R116: =IF(J116=0,0,Q116*VLOOKUP(E116,'Prix Matiere'!$A$4:$L$60,11)) -> 0
B117: Bouts | C117: =IF(F117=0,0,E119) -> 0 | D117: =IF(F117=0,0,D119) -> 0 | E117: =VLOOKUP(C17,A266:P272,9) -> 0 | F117: =VLOOKUP($C$17,A266:P272,10) -> 0 | J117: =IF(C117=0,0,(C117/100)*(D117/100)*F117) -> 0 | K117: =J117/0.8 -> 0 | L117: =IF(E117=0,0,VLOOKUP(E117,'Prix Matiere'!A6:J62,10)) -> 0 | M117: =L117*K117 -> 0 | N117: =IF(J117=0,0,4+(5*J117)) -> 0 | O117: =N117*MinuteMO -> 0 | Q117: =IF(J117=0,0,J117*VLOOKUP(E117,'Prix Matiere'!$A$4:$L$60,12)) -> 0 | R117: =IF(J117=0,0,Q117*VLOOKUP(E117,'Prix Matiere'!$A$4:$L$60,11)) -> 0
A119: Dimensions intérieures styro | C119: =C113-VLOOKUP(C17,A266:P272,8) -> 0 | D119: =D113-VLOOKUP(C17,A266:P272,8) -> 0 | E119: =E113-VLOOKUP(C17,A266:P272,8) -> 0
A121: Plaquettes | B121: GC | C121: =IF(F121=0,0,C124) -> 0 | D121: =IF(F121=0,0,10) -> 0 | E121: =VLOOKUP(C17,A266:P272,12) -> 0 | F121: =VLOOKUP(C17,A266:P272,13) -> 0 | J121: =IF(C121=0,0,(C121/100)*(D121/100)*F121) -> 0 | K121: =J121/0.8 -> 0 | L121: =IF(E121=0,0,VLOOKUP(E121,'Prix Matiere'!$A$4:$J$65,10)) -> 0 | M121: =L121*K121 -> 0 | N121: =IF(J121=0,0,1+(6*J121)) -> 0 | O121: =N121*MinuteMO -> 0 | Q121: =IF(J121=0,0,J121*VLOOKUP(E121,'Prix Matiere'!$A$4:$L$60,12)) -> 0 | R121: =IF(J121=0,0,Q121*VLOOKUP(E121,'Prix Matiere'!$A$4:$L$60,11)) -> 0
B122: Dessus dessous | C122: =IF(F122=0,0,D119) -> 0 | D122: =IF(F121=0,0,D121) -> 0 | E122: =VLOOKUP(C17,A266:P272,12) -> 0 | F122: =VLOOKUP(C17,A266:P272,13)*2 -> 0 | J122: =IF(C122=0,0,(C122/100)*(D122/100)*F122) -> 0 | K122: =J122/0.8 -> 0 | L122: =IF(E122=0,0,VLOOKUP(E122,'Prix Matiere'!$A$4:$J$65,10)) -> 0 | M122: =L122*K122 -> 0 | N122: =IF(J122=0,0,1+(6*J122)) -> 0 | O122: =N122*MinuteMO -> 0 | Q122: =IF(J122=0,0,J122*VLOOKUP(E122,'Prix Matiere'!$A$4:$L$60,12)) -> 0 | R122: =IF(J122=0,0,Q122*VLOOKUP(E122,'Prix Matiere'!$A$4:$L$60,11)) -> 0
A124: Dimensions intérieures plaquettes | C124: =C119-VLOOKUP($C$17,A266:P272,11) -> 0 | D124: =D119-VLOOKUP($C$17,A266:P272,11) -> 0 | E124: =E119-VLOOKUP($C$17,A266:P272,11) -> 0
A126: Extrudé 2 | B126: GC | C126: =IF(F126=0,0,C130+VLOOKUP($C$17,A266:P272,14)) -> 0 | D126: =IF(F126=0,0,E130+VLOOKUP($C$17,A266:P272,14)) -> 0 | E126: =VLOOKUP($C$17,A266:P272,15) -> 0 | F126: =VLOOKUP($C$17,A266:P272,16) -> 0 | J126: =IF(C126=0,0,(C126/100)*(D126/100)*F126) -> 0 | K126: =J126/0.8 -> 0 | L126: =IF(E126=0,0,VLOOKUP(E126,'Prix Matiere'!A4:J60,10)) -> 0 | M126: =L126*K126 -> 0 | N126: =IF(J126=0,0,4+(5*J126)) -> 0 | O126: =N126*MinuteMO -> 0 | Q126: =IF(J126=0,0,J126*VLOOKUP(E126,'Prix Matiere'!$A$4:$L$60,12)) -> 0 | R126: =IF(J126=0,0,Q126*VLOOKUP(E126,'Prix Matiere'!$A$4:$L$60,11)) -> 0
B127: Dessus dessous | C127: =IF(F127=0,0,C130+VLOOKUP($C$17,A266:P272,14)) -> 0 | D127: =IF(F127=0,0,D130) -> 0 | E127: =VLOOKUP($C$17,A266:P272,15) -> 0 | F127: =VLOOKUP($C$17,A266:P272,16) -> 0 | J127: =IF(C127=0,0,(C127/100)*(D127/100)*F127) -> 0 | K127: =J127/0.8 -> 0 | L127: =IF(E127=0,0,VLOOKUP(E127,'Prix Matiere'!A5:J61,10)) -> 0 | M127: =L127*K127 -> 0 | N127: =IF(J127=0,0,4+(5*J127)) -> 0 | O127: =N127*MinuteMO -> 0 | Q127: =IF(J127=0,0,J127*VLOOKUP(E127,'Prix Matiere'!$A$4:$L$60,12)) -> 0 | R127: =IF(J127=0,0,Q127*VLOOKUP(E127,'Prix Matiere'!$A$4:$L$60,11)) -> 0
B128: Bouts | C128: =IF(F128=0,0,E130) -> 0 | D128: =IF(F128=0,0,D130) -> 0 | E128: =VLOOKUP($C$17,A266:P272,15) -> 0 | F128: =VLOOKUP($C$17,A266:P272,16) -> 0 | J128: =IF(C128=0,0,(C128/100)*(D128/100)*F128) -> 0 | K128: =J128/0.8 -> 0 | L128: =IF(E128=0,0,VLOOKUP(E128,'Prix Matiere'!A6:J62,10)) -> 0 | M128: =L128*K128 -> 0 | N128: =IF(J128=0,0,4+(5*J128)) -> 0 | O128: =N128*MinuteMO -> 0 | Q128: =IF(J128=0,0,J128*VLOOKUP(E128,'Prix Matiere'!$A$4:$L$60,12)) -> 0 | R128: =IF(J128=0,0,Q128*VLOOKUP(E128,'Prix Matiere'!$A$4:$L$60,11)) -> 0
A130: Dimensions intérieures styro | C130: =C124-VLOOKUP($C$17,A266:P272,14) -> 0 | D130: =D124-VLOOKUP($C$17,A266:P272,14) -> 0 | E130: =E124-VLOOKUP($C$17,A266:P272,14) -> 0
A132: Caisson 1 | B132: =IF(B40=0,0,"Dessus/Dessous") -> 0 | C132: =IF(B40=0,0,H40) -> 0 | D132: =IF(B40=0,0,I39) -> 0 | E132: =IF(B40=0,0,"Peuplier 15 mm") -> 0 | F132: =IF(B40=0,0,2) -> 0 | J132: =IF(C132=0,0,(C132/100)*(D132/100)*F132) -> 0 | K132: =J132/0.8 -> 0 | L132: =IF(E132=0,0,VLOOKUP(E132,'Prix Matiere'!$A$4:$J$65,10)) -> 0 | M132: =L132*K132 -> 0 | N132: =IF(J132=0,0,5+(6*J132)) -> 0 | O132: =N132*MinuteMO -> 0 | Q132: =IF(J132=0,0,J132*VLOOKUP(E132,'Prix Matiere'!$A$4:$L$60,12)) -> 0 | R132: =IF(J132=0,0,Q132*VLOOKUP(E132,'Prix Matiere'!$A$4:$L$60,11)) -> 0
B133: =IF(B40=0,0,"Bouts") -> 0 | C133: =IF(B40=0,0,J39) -> 0 | D133: =D132 -> 0 | E133: =IF(B40=0,0,"Peuplier 15 mm") -> 0 | F133: =IF(B40=0,0,2) -> 0 | J133: =IF(C133=0,0,(C133/100)*(D133/100)*F133) -> 0 | K133: =J133/0.8 -> 0 | L133: =IF(E133=0,0,VLOOKUP(E133,'Prix Matiere'!$A$4:$J$65,10)) -> 0 | M133: =L133*K133 -> 0 | N133: =IF(J133=0,0,5+(6*J133)) -> 0 | O133: =N133*MinuteMO -> 0 | Q133: =IF(J133=0,0,J133*VLOOKUP(E133,'Prix Matiere'!$A$4:$L$60,12)) -> 0 | R133: =IF(J133=0,0,Q133*VLOOKUP(E133,'Prix Matiere'!$A$4:$L$60,11)) -> 0
B134: =IF(B40=0,0,"GC") -> 0 | C134: =IF(B40=0,0,C132) -> 0 | D134: =IF(B40=0,0,C133+3) -> 0 | E134: =IF(B40=0,0,"Peuplier 15 mm") -> 0 | F134: =IF(B40=0,0,2) -> 0 | J134: =IF(C134=0,0,(C134/100)*(D134/100)*F134) -> 0 | K134: =J134/0.8 -> 0 | L134: =IF(E134=0,0,VLOOKUP(E134,'Prix Matiere'!$A$4:$J$65,10)) -> 0 | M134: =L134*K134 -> 0 | N134: =IF(J134=0,0,5+(6*J134)) -> 0 | O134: =N134*MinuteMO -> 0 | Q134: =IF(J134=0,0,J134*VLOOKUP(E134,'Prix Matiere'!$A$4:$L$60,12)) -> 0 | R134: =IF(J134=0,0,Q134*VLOOKUP(E134,'Prix Matiere'!$A$4:$L$60,11)) -> 0
O135: =N135*MinuteMO -> 0
...

Sheet T1-T3 MRT
A1: Caisse Tableau de 1 à 3 MRT
E3: =IF(C19="Boulons et platines","Boulons et Platines",0) -> 0 | F3: =IF(E3="Boulons et Platines","Nbre de Trous",0) -> 0 | G3: =IF(E3="Boulons et Platines","Dim du Bord",0) -> 0
E4: =IF(C19="Vis bois",0,"Trous dans la Longueur") -> 0 | F4: =IF(E4=0,0,IF(C52<100,2,IF(C52<150,3,IF(C52<200,4,IF(C52<250,5,IF(C52<300,6,7)))))) -> 0 | G4: =IF(F4=0,0,IF(F4=3,0,(($C$52-32)/(F4-1))+16)) -> 0
E5: =IF(F4=6,"2ème Trou",IF(F4=7,"2ème Trou",0)) -> 0 | G5: =IF(E5=0,0,G4+G4-16) -> 0
E6: =IF(C19="Vis bois",0,"Trous dans la Hauteur") -> 0 | F6: =IF(E6=0,0,IF(D52<100,2,IF(D52<150,3,IF(D52<200,4,IF(D52<250,5,IF(D52<310,6,7)))))) -> 0 | G6: =IF(F6=0,0,IF(F6=3,0,(($D$52-32)/(F6-1))+16)) -> 0
E7: =IF(F6=6,"2ème Trou",IF(F6=7,"2ème Trou",0)) -> 0 | G7: =IF(E7=0,0,G6+G6-16) -> 0
B9: N° de dossier | E9: Responsable Dossier | F9: Grégory MORA
B10: Ville de destination | E10: Client | F10: ESI
B11: N° de caisse | E11: Délai
B13: Type de Contreplaqué | C13: Peuplier 15 mm
B15: Barres | C15: Pin raboté 4 faces | E15: Garnissage Valsem | F15: Oui | H15: =VLOOKUP($F$10,'Infos Clients'!$B$2:$G$10,2) -> #VALUE!
B17: Type d'isolant | C17: Isotherme en 30
B19: Fermeture | C19: Vis bois | E19: Peinture | F19: Non
E20: =IF(F19="Oui","Type de Peinture",0) -> 0 | F20: =IF(F19="Non",0,VLOOKUP(F10,'Infos Clients'!B2:E10,4)) -> 0
B21: Poignées | C21: Bois
B23: Skis | C23: Skis | E23: Option Calage | F23: Aucun
B24: =IF(F23="Aucun"," ",F23)
C26: Longueur | D26: Epaisseur | E26: Hauteur | F26: =IF(B27="Dimensions de l'œuvre","Face du MRT",0) -> Face du MRT | G26: =IF(B27="Dimensions de l'œuvre","Arrière du MRT",0) -> Arrière du MRT | H26: Prix du MRT
B27: Dimensions de l'oeuvre | C27: 207.2 | D27: 4.2 | E27: 166.5 | F27: Mrt Ouvert | G27: Mrt Ouvert | H27: =S72 -> 190.90207 | J27: =IF($B$27="Dimensions ext MRT existant",C27,IF($B$27="Aucun",0,C27+24.2)) -> 231.4 | K27: =IF($B$27="Dimensions ext MRT existant",K28,IF($B$27="Aucun",0,K28+1.5+VLOOKUP($G$27,$A$170:$C$174,3)+VLOOKUP($F$27,A170:C174,3))) -> 13.9 | L27: =IF($B$27="Dimensions ext MRT existant",E27,IF($B$27="Aucun",0,E27+14.2)) -> 180.7
K28: =IF(B27="Dimensions ext MRT existant",D27,IF(B27="Aucun",0,IF(D27<6,9.4,IF(D27<11,14.4,D27+9.4)))) -> 9.4
C29: Longueur | D29: Epaisseur | E29: Hauteur | F29: =IF(B30="Dimensions de l'œuvre","Type de MRT",0) -> 0 | G29: Prix du MRT | H29: Prix du MRT
B30: Aucun | F30: Mrt Ouvert | G30: Mrt Ouvert | H30: =S80 -> 0 | J30: =IF($B$30="Dimensions ext MRT existant",C30,IF($B$30="Aucun",0,C30+24.2)) -> 0 | K30: =IF($B$30="Dimensions ext MRT existant",D30,IF($B$30="Aucun",0,K31+1.5+VLOOKUP($G$30,$A$170:$C$174,3)+VLOOKUP($F$30,$A$170:$C$174,3))) -> 0 | L30: =IF($B$30="Dimensions ext MRT existant",E30,IF($B$30="Aucun",0,E30+14.2)) -> 0
K31: =IF(B30="Dimensions ext MRT existant",D30,IF(B30="Aucun",0,IF(D30<6,9.4,IF(D30<11,14.4,D30+9.4)))) -> 0
C32: Longueur | D32: Epaisseur | E32: Hauteur | F32: =IF(B33="Dimensions de l'œuvre","Type de MRT",0) -> 0 | G32: Prix du MRT | H32: Prix du MRT
B33: Aucun | F33: Mrt Ouvert | G33: Mrt Ouvert | H33: =S88 -> 0 | J33: =IF($B$33="Dimensions ext MRT existant",C33,IF($B$33="Aucun",0,C33+24.2)) -> 0 | K33: =IF($B$33="Dimensions ext MRT existant",D33,IF($B$33="Aucun",0,K34+1.5+VLOOKUP($G$33,$A$170:$C$174,3)+VLOOKUP($F$33,$A$170:$C$174,3))) -> 0 | L33: =IF($B$33="Dimensions ext MRT existant",E33,IF($B$33="Aucun",0,E33+14.2)) -> 0
K34: =IF(B33="Dimensions ext MRT existant",D33,IF(B33="Aucun",0,IF(D33<6,9.4,IF(D33<11,14.4,D33+9.4)))) -> 0
B36: Type de calage
B37: Aucun
B39: Dimensions intérieures caisse | C39: =IF(J27=0,0,MAX(J27:J33)+VLOOKUP(C17,A146:P152,2)+VLOOKUP(B37,A178:D180,2)) -> 239.9 | D39: =K27+K30+K33+VLOOKUP($B$37,A178:D180,3)+VLOOKUP($C$17,A146:P152,3) -> 19.9 | E39: =IF(L27=0,0,MAX(L27:L33)+VLOOKUP($B$37,A178:D180,4)+VLOOKUP($C$17,A146:P152,4)) -> 189.2 | F39: Prix d'achat Arckx (y compris MRT à réaliser)
B41: Dimensions extérieures caisse | C41: =C39+VLOOKUP(C21,A157:B159,2)+VLOOKUP(C13,A136:E138,5)*2+VLOOKUP(C15,A140:D141,4)*2 -> 251.3 | D41: =IF(OR($F$23="Aucun",$F$23="Stabilisateur"),$D$39+VLOOKUP($C$13,$A$136:$E$138,4)*2+VLOOKUP($C$15,$A$140:$D$141,4)*2+0.5,$E$39+VLOOKUP($C$13,$A$136:$E$138,5)*2+VLOOKUP($C$15,$A$140:$D$141,4)*2) -> 27.6 | E41: =IF(OR($F$23="Aucun",$F$23="Stabilisateur"),$E$39+VLOOKUP($C$13,$A$136:$E$138,5)*2+VLOOKUP($C$15,$A$140:$D$141,4)*2+VLOOKUP($C$23,$A$186:$B$188,2),$D$39+VLOOKUP($C$13,$A$136:$E$138,4)*2+VLOOKUP($C$15,$A$140:$D$141,4)*2+VLOOKUP($C$23,$A$186:$B$188,2)+VLOOKUP($F$23,$A$161:$D$164,4)+0.5) -> 199.4 | F41: =ROUNDUP(C133,0) -> 1209
B43: Poids de la Caisse | C43: =P125 -> 141.64269 | D43: Kg | E43: Bilan Carbone
B44: Minutes de Production | C44: =D127 -> 284.60457 | D44: Min | E44: =Q125 -> 121.06331
B46: Commentaires
F51: Quantité | P51: Poids KG | Q51: CO²
A52: Grand côtés | B52: =VLOOKUP(C13,A136:D138,2) -> Peuplier 15 mm | C52: =IF(C39=0,0,C39+2*(VLOOKUP(B53,A136:D138,4)+VLOOKUP(C15,A140:D141,4))) -> 247.1 | D52: =IF(E39=0,0,E39+2*(VLOOKUP(B54,A136:D138,4)+VLOOKUP(C15,A140:D141,4))) -> 196.4 | E52: =B52 -> Peuplier 15 mm | F52: 2 | J52: =IF(C52=0,0,(C52/100)*(D52/100)*F52) -> 9.706088 | K52: =J52/0.8 -> 12.13261 | L52: =IF(E52=0,0,VLOOKUP(E52,'Prix Matiere'!$A$4:$J$65,10)) -> 16.895876 | M52: =L52*K52-IF($F$15="Non",K52*0.75,0) -> 204.99108 | N52: =IF(J52=0,0,IF($F$15="Oui",(7.0924*J52)+15,(6.0924*J52)+10)) -> 83.839459 | O52: =N52*MinuteMO -> 71.26354 | P52: =IF(J52=0,0,J52*VLOOKUP(E52,'Prix Matiere'!$A$4:$L$60,12)) -> 64.060181 | Q52: =IF(J52=0,0,P52*VLOOKUP(E52,'Prix Matiere'!$A$4:$L$60,11)) -> 49.51852
A53: Dessus dessous | B53: =VLOOKUP(C13,A136:D138,3) -> Peuplier 15 mm | C53: =C52 -> 247.1 | D53: =D39 -> 19.9 | E53: =B53 -> Peuplier 15 mm | F53: 2 | J53: =IF(C53=0,0,(C53/100)*(D53/100)*F53) -> 0.983458 | K53: =J53/0.8 -> 1.2293225 | L53: =IF(E53=0,0,VLOOKUP(E53,'Prix Matiere'!$A$4:$J$65,10)) -> 16.895876 | M53: =L53*K53-IF($F$15="Non",K53*0.75,0) -> 20.770481 | N53: =IF(J53=0,0,IF($F$15="Oui",(7.0924*J53)+15,(6.0924*J53)+10)) -> 21.975078 | O53: =N53*MinuteMO -> 18.678816 | P53: =IF(J53=0,0,J53*VLOOKUP(E53,'Prix Matiere'!$A$4:$L$60,12)) -> 6.4908228 | Q53: =IF(J53=0,0,P53*VLOOKUP(E53,'Prix Matiere'!$A$4:$L$60,11)) -> 5.017406
A54: Bouts | B54: =VLOOKUP(C13,A136:D138,3) -> Peuplier 15 mm | C54: =E39 -> 189.2 | D54: =D39 -> 19.9 | E54: =B54 -> Peuplier 15 mm | F54: 2 | J54: =IF(C54=0,0,(C54/100)*(D54/100)*F54) -> 0.753016 | K54: =J54/0.8 -> 0.94127 | L54: =IF(E54=0,0,VLOOKUP(E54,'Prix Matiere'!$A$4:$J$65,10)) -> 16.895876 | M54: =L54*K54-IF($F$15="Non",K54*0.75,0) -> 15.903581 | N54: =IF(J54=0,0,IF($F$15="Oui",(7.0924*J54)+15,(6.0924*J54)+10)) -> 20.340691 | O54: =N54*MinuteMO -> 17.289587 | P54: =IF(J54=0,0,J54*VLOOKUP(E54,'Prix Matiere'!$A$4:$L$60,12)) -> 4.9699056 | Q54: =IF(J54=0,0,P54*VLOOKUP(E54,'Prix Matiere'!$A$4:$L$60,11)) -> 3.841737
J55: =IF(C55=0,0,(C55/100)*(D55/100)*F55) -> 0 | K55: =J55/0.8 -> 0 | P55: =IF(J55=0,0,J55*VLOOKUP(E55,'Prix Matiere'!$A$4:$L$60,12)) -> 0 | Q55: =IF(J55=0,0,P55*VLOOKUP(E55,'Prix Matiere'!$A$4:$L$60,11)) -> 0
J56: =IF(C56=0,0,(C56/100)*(D56/100)*F56) -> 0 | K56: =J56/0.8 -> 0 | P56: =IF(J56=0,0,J56*VLOOKUP(E56,'Prix Matiere'!$A$4:$L$60,12)) -> 0 | Q56: =IF(J56=0,0,P56*VLOOKUP(E56,'Prix Matiere'!$A$4:$L$60,11)) -> 0
A57: Barres | B57: Barres de GC | C57: =C52 -> 247.1 | D57: =IF(D52>80,9.4,7) -> 9.4 | E57: =IF($C$15="Pin raboté 4 faces","Barres 21 R4F","Barres 19 mm") -> Barres 21 R4F | F57: 4 | J57: =IF(C57=0,0,(C57/100)*(D57/100)*F57) -> 0.929096 | K57: =J57/0.8 -> 1.16137 | L57: =IF(E57=0,0,VLOOKUP(E57,'Prix Matiere'!$A$4:$J$65,10)) -> 18.969072 | M57: =L57*K57 -> 22.030111 | N57: =IF(J57=0,0,1+(11*J57)) -> 11.220056 | O57: =N57*MinuteMO -> 9.5370476 | P57: =IF(J57=0,0,J57*VLOOKUP(E57,'Prix Matiere'!$A$4:$L$60,12)) -> 9.29096 | Q57: =IF(J57=0,0,P57*VLOOKUP(E57,'Prix Matiere'!$A$4:$L$60,11)) -> 4.4968246
B58: Remplis GC | C58: =IF(D52=0,0,D52-2*D57) -> 177.6 | D58: =D57 -> 9.4 | E58: =IF($C$15="Pin raboté 4 faces","Barres 21 R4F","Barres 19 mm") -> Barres 21 R4F | F58: =4 -> 4 | J58: =IF(C58=0,0,(C58/100)*(D58/100)*F58) -> 0.667776 | K58: =J58/0.8 -> 0.83472 | L58: =IF(E58=0,0,VLOOKUP(E58,'Prix Matiere'!$A$4:$J$65,10)) -> 18.969072 | M58: =L58*K58 -> 15.833864 | N58: =IF(J58=0,0,1+(11*J58)) -> 8.345536 | O58: =N58*MinuteMO -> 7.0937056 | P58: =IF(J58=0,0,J58*VLOOKUP(E58,'Prix Matiere'!$A$4:$L$60,12)) -> 6.67776 | Q58: =IF(J58=0,0,P58*VLOOKUP(E58,'Prix Matiere'!$A$4:$L$60,11)) -> 3.2320358
B59: Dessus / Dessous | C59: =C57 -> 247.1 | D59: =IF($D$39<14.4,$D$39,7) -> 7 | E59: =IF($C$15="Pin raboté 4 faces","Barres 21 R4F","Barres 19 mm") -> Barres 21 R4F | F59: =IF(D39<14.4,2,4) -> 4 | J59: =IF(C59=0,0,(C59/100)*(D59/100)*F59) -> 0.69188 | K59: =J59/0.8 -> 0.86485 | L59: =IF(E59=0,0,VLOOKUP(E59,'Prix Matiere'!$A$4:$J$65,10)) -> 18.969072 | M59: =L59*K59 -> 16.405402 | N59: =IF(J59=0,0,1+(11*J59)) -> 8.61068 | O59: =N59*MinuteMO -> 7.319078 | P59: =IF(J59=0,0,J59*VLOOKUP(E59,'Prix Matiere'!$A$4:$L$60,12)) -> 6.9188 | Q59: =IF(J59=0,0,P59*VLOOKUP(E59,'Prix Matiere'!$A$4:$L$60,11)) -> 3.3486992
B60: =C23 -> Skis | C60: =IF(C52=0,0,IF(B60="Skis",C52-10,IF(B60="10 dessous en semelles",D41,IF(B60="10 dessous en skis",(C57-70)/2)))) -> 237.1 | D60: =IF($F$10="BOVIS",9.4,7) -> 7 | E60: =IF($C$23="Skis","Barres 30 R4F","Semelles R4F") -> Barres 30 R4F | F60: =IF(B60="Skis",2,IF(B60="10 dessous en semelles",2,F59)) -> 2 | J60: =IF(C60=0,0,(C60/100)*(D60/100)*F60) -> 0.33194 | K60: =J60/0.8 -> 0.414925 | L60: =IF(E60=0,0,VLOOKUP(E60,'Prix Matiere'!$A$4:$J$65,10)) -> 45.43299 | M60: =L60*K60 -> 18.851283 | N60: =IF(J60=0,0,1+(11*J60)) -> 4.65134 | O60: =N60*MinuteMO -> 3.953639 | P60: =IF(J60=0,0,J60*VLOOKUP(E60,'Prix Matiere'!$A$4:$L$60,12)) -> 3.3194 | Q60: =IF(J60=0,0,P60*VLOOKUP(E60,'Prix Matiere'!$A$4:$L$60,11)) -> 1.6065896
B61: Longueur Bouts | C61: =IF(D39<14.4,0,D39) -> 19.9 | D61: =IF(D39<14.4,0,D57) -> 9.4 | E61: =IF($C$15="Pin raboté 4 faces","Barres 21 R4F","Barres 19 mm") -> Barres 21 R4F | F61: =IF(D39<14.4,0,4) -> 4 | J61: =IF(C61=0,0,(C61/100)*(D61/100)*F61) -> 0.074824 | K61: =J61/0.8 -> 0.09353 | L61: =IF(E61=0,0,VLOOKUP(E61,'Prix Matiere'!$A$4:$J$65,10)) -> 18.969072 | M61: =L61*K61 -> 1.7741773 | N61: =IF(J61=0,0,1+(11*J61)) -> 1.823064 | O61: =N61*MinuteMO -> 1.5496044 | P61: =IF(J61=0,0,J61*VLOOKUP(E61,'Prix Matiere'!$A$4:$L$60,12)) -> 0.74824 | Q61: =IF(J61=0,0,P61*VLOOKUP(E61,'Prix Matiere'!$A$4:$L$60,11)) -> 0.36214816
B62: Hauteur Bouts | C62: =IF(D39<14.4,E39,C54-2*D61) -> 170.4 | D62: =IF($D$39<14.4,$D$39,IF($D$39<20,5,7)) -> 5 | E62: =IF($C$15="Pin raboté 4 faces","Barres 21 R4F","Barres 19 mm") -> Barres 21 R4F | F62: =IF(D39<14.4,2,4) -> 4 | J62: =IF(C62=0,0,(C62/100)*(D62/100)*F62) -> 0.3408 | K62: =J62/0.8 -> 0.426 | L62: =IF(E62=0,0,VLOOKUP(E62,'Prix Matiere'!$A$4:$J$65,10)) -> 18.969072 | M62: =L62*K62 -> 8.0808247 | N62: =IF(J62=0,0,1+(11*J62)) -> 4.7488 | O62: =N62*MinuteMO -> 4.03648 | P62: =IF(J62=0,0,J62*VLOOKUP(E62,'Prix Matiere'!$A$4:$L$60,12)) -> 3.408 | Q62: =IF(J62=0,0,P62*VLOOKUP(E62,'Prix Matiere'!$A$4:$L$60,11)) -> 1.649472
B63: =IF(D39<14.4,0,IF(C21="Bois","Poignées",IF(C21="Métal x 2 sur bouts","Supports poignées",0))) -> Poignées | C63: =IF(B63="Poignées",D54+VLOOKUP(C13,A136:D138,4)*2+4.2,IF(B63="Supports poignées",D54-2*D62,0)) -> 27.1 | D63: =IF(B63="Poignées",7,IF(B63="Supports poignées",9.4,0)) -> 7 | E63: Barres 21 R4F | F63: =IF(B63=0,0,2) -> 2 | J63: =IF(C63=0,0,(C63/100)*(D63/100)*F63) -> 0.03794 | K63: =J63/0.8 -> 0.047425 | L63: =IF(E63=0,0,VLOOKUP(E63,'Prix Matiere'!$A$4:$J$65,10)) -> 18.969072 | M63: =L63*K63 -> 0.89960825 | N63: =IF(J63=0,0,1+(11*J63)) -> 1.41734 | O63: =N63*MinuteMO -> 1.204739 | P63: =IF(J63=0,0,J63*VLOOKUP(E63,'Prix Matiere'!$A$4:$L$60,12)) -> 0.3794 | Q63: =IF(J63=0,0,P63*VLOOKUP(E63,'Prix Matiere'!$A$4:$L$60,11)) -> 0.1836296
P64: =IF(J64=0,0,J64*VLOOKUP(E64,'Prix Matiere'!$A$4:$L$60,12)) -> 0 | Q64: =IF(J64=0,0,P64*VLOOKUP(E64,'Prix Matiere'!$A$4:$L$60,11)) -> 0
P65: =IF(J65=0,0,J65*VLOOKUP(E65,'Prix Matiere'!$A$4:$L$60,12)) -> 0 | Q65: =IF(J65=0,0,P65*VLOOKUP(E65,'Prix Matiere'!$A$4:$L$60,11)) -> 0
A66: MRT 1 | B66: Dessus dessous bois massif | C66: =IF(B27="Dimensions ext MRT existant",0,J27) -> 231.4 | D66: =IF(B27="Dimensions ext MRT existant",0,K28) -> 9.4 | E66: Barres 21 R4F | F66: =IF(C66=0,0,2) -> 2 | J66: =IF(C66=0,0,(C66/100)*(D66/100)*F66) -> 0.435032 | K66: =J66/0.8 -> 0.54379 | L66: =IF(E66=0,0,VLOOKUP(E66,'Prix Matiere'!$A$4:$J$65,10)) -> 18.969072 | M66: =L66*K66 -> 10.315192 | N66: =IF(C66=0,0,4+(11*J66)) -> 8.785352 | O66: =N66*MinuteMO -> 7.4675492 | P66: =IF(J66=0,0,J66*VLOOKUP(E66,'Prix Matiere'!$A$4:$L$60,12)) -> 4.35032 | Q66: =IF(J66=0,0,P66*VLOOKUP(E66,'Prix Matiere'!$A$4:$L$60,11)) -> 2.1055549 | R66: Total matière | S66: =SUM($M$66:$M$72) -> 73.527643
B67: Bouts bois massif avec poignées métalliques | C67: =IF(B27="Dimensions ext MRT existant",0,IF(E27=0,0,L27-4.2)) -> 176.5 | D67: =D66 -> 9.4 | E67: Barres 21 R4F | F67: =F66 -> 2 | J67: =IF(C67=0,0,(C67/100)*(D67/100)*F67) -> 0.33182 | K67: =J67/0.8 -> 0.414775 | L67: =IF(E67=0,0,VLOOKUP(E67,'Prix Matiere'!$A$4:$J$65,10)) -> 18.969072 | M67: =L67*K67 -> 7.8678969 | N67: =IF(C67=0,0,4+(11*J67)) -> 7.65002 | O67: =N67*MinuteMO -> 6.502517 | P67: =IF(J67=0,0,J67*VLOOKUP(E67,'Prix Matiere'!$A$4:$L$60,12)) -> 3.3182 | Q67: =IF(J67=0,0,P67*VLOOKUP(E67,'Prix Matiere'!$A$4:$L$60,11)) -> 1.6060088 | R67: Total MO | S67: =SUM($O$66:$O$72) -> 53.04043 | T67: =AC65 -> 0
B68: =E68 -> Peuplier 15 mm | C68: =IF(C66=0,0,C66) -> 231.4 | D68: =IF(C68=0,0,25) -> 25 | E68: ="Peuplier 15 mm" -> Peuplier 15 mm | F68: =IF(C68=0,0,2) -> 2 | J68: =IF(C68=0,0,(C68/100)*(D68/100)*F68) -> 1.157 | K68: =J68/0.8 -> 1.44625 | L68: =IF(E68=0,0,VLOOKUP(E68,'Prix Matiere'!$A$4:$J$65,10)) -> 16.895876 | M68: =L68*K68 -> 24.435661 | N68: =IF(C68=0,0,(6.0924*J68)+10) -> 17.048907 | O68: =N68*MinuteMO -> 14.491571 | P68: =IF(J68=0,0,J68*VLOOKUP(E68,'Prix Matiere'!$A$4:$L$60,12)) -> 7.6362 | Q68: =IF(J68=0,0,P68*VLOOKUP(E68,'Prix Matiere'!$A$4:$L$60,11)) -> 5.9027826 | R68: Total frais généraux | S68: =((S66+S67)/0.78)-(S66+S67) -> 35.698687
B69: =E69 -> Peuplier 15 mm | C69: =IF(C68=0,0,L27-2*D68) -> 130.7 | D69: =D68 -> 25 | E69: ="Peuplier 15 mm" -> Peuplier 15 mm | F69: =IF(C69=0,0,2) -> 2 | J69: =IF(C69=0,0,(C69/100)*(D69/100)*F69) -> 0.6535 | K69: =J69/0.8 -> 0.816875 | L69: =IF(E69=0,0,VLOOKUP(E69,'Prix Matiere'!$A$4:$J$65,10)) -> 16.895876 | M69: =L69*K69 -> 13.801819 | N69: =IF(C69=0,0,(6.0924*J69)+10) -> 13.981383 | O69: =N69*MinuteMO -> 11.884176 | P69: =IF(J69=0,0,J69*VLOOKUP(E69,'Prix Matiere'!$A$4:$L$60,12)) -> 4.3131 | Q69: =IF(J69=0,0,P69*VLOOKUP(E69,'Prix Matiere'!$A$4:$L$60,11)) -> 3.3340263 | R69: Total revient | S69: =SUM(S66:S68) -> 162.26676
B70: Angles cp 15 | C70: =IF(C66=0,0,45) -> 45 | D70: =IF(C70=0,0,45) -> 45 | E70: Peuplier 15 mm | F70: =IF(C70=0,0,4) -> 4 | J70: =IF(C70=0,0,(C70/100)*(D70/100)*F70) -> 0.81 | K70: =J70/0.8 -> 1.0125 | L70: =IF(E70=0,0,VLOOKUP(E70,'Prix Matiere'!$A$4:$J$65,10)) -> 16.895876 | M70: =L70*K70 -> 17.107075 | N70: =IF(C70=0,0,(6.0924*J70)+10) -> 14.934844 | O70: =N70*MinuteMO -> 12.694617 | P70: =IF(J70=0,0,J70*VLOOKUP(E70,'Prix Matiere'!$A$4:$L$60,12)) -> 5.346 | Q70: =IF(J70=0,0,P70*VLOOKUP(E70,'Prix Matiere'!$A$4:$L$60,11)) -> 4.132458 | R70: Marge | S70: =(S69/(1-0.15))-S69 -> 28.635311
B71: =G27 -> Mrt Ouvert | C71: =IF(B71=0,0,IF(B71="Mrt Ouvert",0,J27)) -> 0 | D71: =IF(B71=0,0,IF(B71="Mrt Ouvert",0,L27)) -> 0 | E71: =VLOOKUP(G27,$A$170:$C$174,2) -> 0 | F71: =IF(C71=0,0,1) -> 0 | J71: =IF(C71=0,0,(C71/100)*(D71/100)*F71) -> 0 | K71: =J71/0.8 -> 0 | L71: =IF(E71=0,0,VLOOKUP(E71,'Prix Matiere'!$A$4:$J$65,10)) -> 0 | M71: =L71*K71 -> 0 | N71: =IF(C71=0,0,1+(11*J71)) -> 0 | O71: =N71*MinuteMO -> 0 | P71: =IF(J71=0,0,J71*VLOOKUP(E71,'Prix Matiere'!$A$4:$L$60,12)) -> 0 | Q71: =IF(J71=0,0,P71*VLOOKUP(E71,'Prix Matiere'!$A$4:$L$60,11)) -> 0
B72: =F27 -> Mrt Ouvert | C72: =IF(B72=0,0,IF(B72="Mrt Ouvert",0,J27)) -> 0 | D72: =IF(B72=0,0,IF(B72="Mrt Ouvert",0,L27)) -> 0 | E72: =VLOOKUP($F$27,$A$170:$C$174,2) -> 0 | F72: =IF(C72=0,0,1) -> 0 | J72: =IF(C72=0,0,(C72/100)*(D72/100)*F72) -> 0 | K72: =J72/0.8 -> 0 | L72: =IF(E72=0,0,VLOOKUP(E72,'Prix Matiere'!$A$4:$J$65,10)) -> 0 | M72: =L72*K72 -> 0 | N72: =IF(C72=0,0,1+(11*J72)) -> 0 | O72: =N72*MinuteMO -> 0 | P72: =IF(J72=0,0,J72*VLOOKUP(E72,'Prix Matiere'!$A$4:$L$60,12)) -> 0 | Q72: =IF(J72=0,0,P72*VLOOKUP(E72,'Prix Matiere'!$A$4:$L$60,11)) -> 0 | R72: Prix de vente | S72: =SUM(S69:S70) -> 190.90207
P73: =IF(J73=0,0,J73*VLOOKUP(E73,'Prix Matiere'!$A$4:$L$60,12)) -> 0 | Q73: =IF(J73=0,0,P73*VLOOKUP(E73,'Prix Matiere'!$A$4:$L$60,11)) -> 0
A74: MRT 2 | B74: Dessus dessous bois massif | C74: =IF(B30="Dimensions ext MRT existant",0,J30) -> 0 | D74: =IF(B30="Dimensions ext MRT existant",0,K31) -> 0 | E74: Barres 21 R4F | F74: =IF(C74=0,0,2) -> 0 | J74: =IF(C74=0,0,(C74/100)*(D74/100)*F74) -> 0 | K74: =J74/0.8 -> 0 | L74: =IF(E74=0,0,VLOOKUP(E74,'Prix Matiere'!$A$4:$J$65,10)) -> 18.969072 | M74: =L74*K74 -> 0 | N74: =IF(C74=0,0,4+(11*J74)) -> 0 | O74: =N74*MinuteMO -> 0 | P74: =IF(J74=0,0,J74*VLOOKUP(E74,'Prix Matiere'!$A$4:$L$60,12)) -> 0 | Q74: =IF(J74=0,0,P74*VLOOKUP(E74,'Prix Matiere'!$A$4:$L$60,11)) -> 0 | R74: Total matière | S74: =SUM($M$74:$M$80) -> 0
B75: Bouts bois massif avec poignées métalliques | C75: =IF(B30="Dimensions ext MRT existant",0,IF(E30=0,0,L30-4.2)) -> 0 | D75: =D74 -> 0 | E75: Barres 21 R4F | F75: =F74 -> 0 | J75: =IF(C75=0,0,(C75/100)*(D75/100)*F75) -> 0 | K75: =J75/0.8 -> 0 | L75: =IF(E75=0,0,VLOOKUP(E75,'Prix Matiere'!$A$4:$J$65,10)) -> 18.969072 | M75: =L75*K75 -> 0 | N75: =IF(J75=0,0,4+(11*J75)) -> 0 | O75: =N75*MinuteMO -> 0 | P75: =IF(J75=0,0,J75*VLOOKUP(E75,'Prix Matiere'!$A$4:$L$60,12)) -> 0 | Q75: =IF(J75=0,0,P75*VLOOKUP(E75,'Prix Matiere'!$A$4:$L$60,11)) -> 0 | R75: Total MO | S75: =SUM($O$74:$O$80) -> 0 | T75: =AC73 -> 0
B76: =E76 -> Peuplier 15 mm | C76: =IF(C74=0,0,C74) -> 0 | D76: =IF(C76=0,0,25) -> 0 | E76: ="Peuplier 15 mm" -> Peuplier 15 mm | F76: =IF(C76=0,0,2) -> 0 | J76: =IF(C76=0,0,(C76/100)*(D76/100)*F76) -> 0 | K76: =J76/0.8 -> 0 | L76: =IF(E76=0,0,VLOOKUP(E76,'Prix Matiere'!$A$4:$J$65,10)) -> 16.895876 | M76: =L76*K76 -> 0 | N76: =IF(C76=0,0,(6.0924*J76)+10) -> 0 | O76: =N76*MinuteMO -> 0 | P76: =IF(J76=0,0,J76*VLOOKUP(E76,'Prix Matiere'!$A$4:$L$60,12)) -> 0 | Q76: =IF(J76=0,0,P76*VLOOKUP(E76,'Prix Matiere'!$A$4:$L$60,11)) -> 0 | R76: Total frais généraux | S76: =((S74+S75)/0.78)-(S74+S75) -> 0
B77: =E77 -> Peuplier 15 mm | C77: =IF(C76=0,0,L30-2*D76) -> 0 | D77: =D76 -> 0 | E77: ="Peuplier 15 mm" -> Peuplier 15 mm | F77: =IF(C77=0,0,2) -> 0 | J77: =IF(C77=0,0,(C77/100)*(D77/100)*F77) -> 0 | K77: =J77/0.8 -> 0 | L77: =IF(E77=0,0,VLOOKUP(E77,'Prix Matiere'!$A$4:$J$65,10)) -> 16.895876 | M77: =L77*K77 -> 0 | N77: =IF(C77=0,0,(6.0924*J77)+10) -> 0 | O77: =N77*MinuteMO -> 0 | P77: =IF(J77=0,0,J77*VLOOKUP(E77,'Prix Matiere'!$A$4:$L$60,12)) -> 0 | Q77: =IF(J77=0,0,P77*VLOOKUP(E77,'Prix Matiere'!$A$4:$L$60,11)) -> 0 | R77: Total revient | S77: =SUM(S74:S76) -> 0
B78: Angles cp 15 | C78: =IF(C74=0,0,45) -> 0 | D78: =IF(C78=0,0,45) -> 0 | E78: Peuplier 15 mm | F78: =IF(C78=0,0,4) -> 0 | J78: =IF(C78=0,0,(C78/100)*(D78/100)*F78) -> 0 | K78: =J78/0.8 -> 0 | L78: =IF(E78=0,0,VLOOKUP(E78,'Prix Matiere'!$A$4:$J$65,10)) -> 16.895876 | M78: =L78*K78 -> 0 | N78: =IF(C78=0,0,(6.0924*J78)+10) -> 0 | O78: =N78*MinuteMO -> 0 | P78: =IF(J78=0,0,J78*VLOOKUP(E78,'Prix Matiere'!$A$4:$L$60,12)) -> 0 | Q78: =IF(J78=0,0,P78*VLOOKUP(E78,'Prix Matiere'!$A$4:$L$60,11)) -> 0 | R78: Marge | S78: =(S77/(1-0.15))-S77 -> 0
B79: =G30 -> Mrt Ouvert | C79: =IF(B79=0,0,IF(B79="Mrt Ouvert",0,J30)) -> 0 | D79: =IF(B79=0,0,IF(B79="Mrt Ouvert",0,L30)) -> 0 | E79: =VLOOKUP(G30,$A$170:$C$174,2) -> 0 | F79: =IF(C79=0,0,1) -> 0 | J79: =IF(C79=0,0,(C79/100)*(D79/100)*F79) -> 0 | K79: =J79/0.8 -> 0 | L79: =IF(E79=0,0,VLOOKUP(E79,'Prix Matiere'!$A$4:$J$65,10)) -> 0 | M79: =L79*K79 -> 0 | N79: =IF(C79=0,0,1+(11*J79)) -> 0 | O79: =N79*MinuteMO -> 0 | P79: =IF(J79=0,0,J79*VLOOKUP(E79,'Prix Matiere'!$A$4:$L$60,12)) -> 0 | Q79: =IF(J79=0,0,P79*VLOOKUP(E79,'Prix Matiere'!$A$4:$L$60,11)) -> 0
B80: =F30 -> Mrt Ouvert | C80: =IF(B80=0,0,IF(B80="Mrt Ouvert",0,J30)) -> 0 | D80: =IF(B80=0,0,IF(B80="Mrt Ouvert",0,L30)) -> 0 | E80: =VLOOKUP($F$30,$A$170:$C$174,2) -> 0 | F80: =IF(C80=0,0,1) -> 0 | J80: =IF(C80=0,0,(C80/100)*(D80/100)*F80) -> 0 | K80: =J80/0.8 -> 0 | L80: =IF(E80=0,0,VLOOKUP(E80,'Prix Matiere'!$A$4:$J$65,10)) -> 0 | M80: =L80*K80 -> 0 | N80: =IF(C80=0,0,1+(11*J80)) -> 0 | O80: =N80*MinuteMO -> 0 | P80: =IF(J80=0,0,J80*VLOOKUP(E80,'Prix Matiere'!$A$4:$L$60,12)) -> 0 | Q80: =IF(J80=0,0,P80*VLOOKUP(E80,'Prix Matiere'!$A$4:$L$60,11)) -> 0 | R80: Prix de vente | S80: =SUM(S77:S78) -> 0
P81: =IF(J81=0,0,J81*VLOOKUP(E81,'Prix Matiere'!$A$4:$L$60,12)) -> 0 | Q81: =IF(J81=0,0,P81*VLOOKUP(E81,'Prix Matiere'!$A$4:$L$60,11)) -> 0
A82: MRT 3 | B82: Dessus dessous bois massif | C82: =IF(B33="Dimensions ext MRT existant",0,J33) -> 0 | D82: =IF(B33="Dimensions ext MRT existant",0,K34) -> 0 | E82: Barres 21 R4F | F82: =IF(C82=0,0,2) -> 0 | J82: =IF(C82=0,0,(C82/100)*(D82/100)*F82) -> 0 | K82: =J82/0.8 -> 0 | L82: =IF(E82=0,0,VLOOKUP(E82,'Prix Matiere'!$A$4:$J$65,10)) -> 18.969072 | M82: =L82*K82 -> 0 | N82: =IF(C82=0,0,4+(11*J82)) -> 0 | O82: =N82*MinuteMO -> 0 | P82: =IF(J82=0,0,J82*VLOOKUP(E82,'Prix Matiere'!$A$4:$L$60,12)) -> 0 | Q82: =IF(J82=0,0,P82*VLOOKUP(E82,'Prix Matiere'!$A$4:$L$60,11)) -> 0 | R82: Total matière | S82: =SUM($M$82:$M$88) -> 0
B83: Bouts bois massif avec poignées métalliques | C83: =IF(B33="Dimensions ext MRT existant",0,IF(E33=0,0,L33-4.2)) -> 0 | D83: =D82 -> 0 | E83: Barres 21 R4F | F83: =F82 -> 0 | J83: =IF(C83=0,0,(C83/100)*(D83/100)*F83) -> 0 | K83: =J83/0.8 -> 0 | L83: =IF(E83=0,0,VLOOKUP(E83,'Prix Matiere'!$A$4:$J$65,10)) -> 18.969072 | M83: =L83*K83 -> 0 | N83: =IF(J83=0,0,4+(11*J83)) -> 0 | O83: =N83*MinuteMO -> 0 | P83: =IF(J83=0,0,J83*VLOOKUP(E83,'Prix Matiere'!$A$4:$L$60,12)) -> 0 | Q83: =IF(J83=0,0,P83*VLOOKUP(E83,'Prix Matiere'!$A$4:$L$60,11)) -> 0 | R83: Total MO | S83: =SUM($O$82:$O$88) -> 0 | T83: =AC81 -> 0
B84: =E84 -> Peuplier 15 mm | C84: =IF(C82=0,0,C82) -> 0 | D84: =IF(C84=0,0,25) -> 0 | E84: ="Peuplier 15 mm" -> Peuplier 15 mm | F84: =IF(C84=0,0,2) -> 0 | J84: =IF(C84=0,0,(C84/100)*(D84/100)*F84) -> 0 | K84: =J84/0.8 -> 0 | L84: =IF(E84=0,0,VLOOKUP(E84,'Prix Matiere'!$A$4:$J$65,10)) -> 16.895876 | M84: =L84*K84 -> 0 | N84: =IF(C84=0,0,(6.0924*J84)+10) -> 0 | O84: =N84*MinuteMO -> 0 | P84: =IF(J84=0,0,J84*VLOOKUP(E84,'Prix Matiere'!$A$4:$L$60,12)) -> 0 | Q84: =IF(J84=0,0,P84*VLOOKUP(E84,'Prix Matiere'!$A$4:$L$60,11)) -> 0 | R84: Total frais généraux | S84: =((S82+S83)/0.78)-(S82+S83) -> 0
B85: =E85 -> Peuplier 15 mm | C85: =IF(C84=0,0,L33-2*D84) -> 0 | D85: =D84 -> 0 | E85: ="Peuplier 15 mm" -> Peuplier 15 mm | F85: =IF(C85=0,0,2) -> 0 | J85: =IF(C85=0,0,(C85/100)*(D85/100)*F85) -> 0 | K85: =J85/0.8 -> 0 | L85: =IF(E85=0,0,VLOOKUP(E85,'Prix Matiere'!$A$4:$J$65,10)) -> 16.895876 | M85: =L85*K85 -> 0 | N85: =IF(C85=0,0,(6.0924*J85)+10) -> 0 | O85: =N85*MinuteMO -> 0 | P85: =IF(J85=0,0,J85*VLOOKUP(E85,'Prix Matiere'!$A$4:$L$60,12)) -> 0 | Q85: =IF(J85=0,0,P85*VLOOKUP(E85,'Prix Matiere'!$A$4:$L$60,11)) -> 0 | R85: Total revient | S85: =SUM(S82:S84) -> 0
B86: Angles cp 15 | C86: =IF(C82=0,0,45) -> 0 | D86: =IF(C86=0,0,45) -> 0 | E86: Peuplier 15 mm | F86: =IF(C86=0,0,4) -> 0 | J86: =IF(C86=0,0,(C86/100)*(D86/100)*F86) -> 0 | K86: =J86/0.8 -> 0 | L86: =IF(E86=0,0,VLOOKUP(E86,'Prix Matiere'!$A$4:$J$65,10)) -> 16.895876 | M86: =L86*K86 -> 0 | N86: =IF(C86=0,0,(6.0924*J86)+10) -> 0 | O86: =N86*MinuteMO -> 0 | P86: =IF(J86=0,0,J86*VLOOKUP(E86,'Prix Matiere'!$A$4:$L$60,12)) -> 0 | Q86: =IF(J86=0,0,P86*VLOOKUP(E86,'Prix Matiere'!$A$4:$L$60,11)) -> 0 | R86: Marge | S86: =(S85/(1-0.15))-S85 -> 0
B87: =G33 -> Mrt Ouvert | C87: =IF(B87=0,0,IF(B87="Mrt Ouvert",0,J33)) -> 0 | D87: =IF(B87=0,0,IF(B87="Mrt Ouvert",0,L33)) -> 0 | E87: =VLOOKUP(G33,$A$170:$C$174,2) -> 0 | F87: =IF(C87=0,0,1) -> 0 | J87: =IF(C87=0,0,(C87/100)*(D87/100)*F87) -> 0 | K87: =J87/0.8 -> 0 | L87: =IF(E87=0,0,VLOOKUP(E87,'Prix Matiere'!$A$4:$J$65,10)) -> 0 | M87: =L87*K87 -> 0 | N87: =IF(C87=0,0,1+(11*J87)) -> 0 | O87: =N87*MinuteMO -> 0 | P87: =IF(J87=0,0,J87*VLOOKUP(E87,'Prix Matiere'!$A$4:$L$60,12)) -> 0 | Q87: =IF(J87=0,0,P87*VLOOKUP(E87,'Prix Matiere'!$A$4:$L$60,11)) -> 0
B88: =F33 -> Mrt Ouvert | C88: =IF(B88=0,0,IF(B88="Mrt Ouvert",0,J33)) -> 0 | D88: =IF(B88=0,0,IF(B88="Mrt Ouvert",0,L33)) -> 0 | E88: =VLOOKUP($F$33,$A$170:$C$174,2) -> 0 | F88: =IF(C88=0,0,1) -> 0 | J88: =IF(C88=0,0,(C88/100)*(D88/100)*F88) -> 0 | K88: =J88/0.8 -> 0 | L88: =IF(E88=0,0,VLOOKUP(E88,'Prix Matiere'!$A$4:$J$65,10)) -> 0 | M88: =L88*K88 -> 0 | N88: =IF(C88=0,0,1+(11*J88)) -> 0 | O88: =N88*MinuteMO -> 0 | P88: =IF(J88=0,0,J88*VLOOKUP(E88,'Prix Matiere'!$A$4:$L$60,12)) -> 0 | Q88: =IF(J88=0,0,P88*VLOOKUP(E88,'Prix Matiere'!$A$4:$L$60,11)) -> 0 | R88: Prix de vente | S88: =SUM(S85:S86) -> 0
P89: =IF(J89=0,0,J89*VLOOKUP(E89,'Prix Matiere'!$A$4:$L$60,12)) -> 0 | Q89: =IF(J89=0,0,P89*VLOOKUP(E89,'Prix Matiere'!$A$4:$L$60,11)) -> 0
A90: Mousse 1 | B90: GC | C90: =IF(F90=0,0,C39) -> 0 | D90: =IF(F90=0,0,E94+VLOOKUP($C$17,A146:P152,5)) -> 0 | E90: =VLOOKUP($C$17,A146:P152,6) -> 0 | F90: =VLOOKUP($C$17,A146:P152,7) -> 0 | J90: =IF(C90=0,0,(C90/100)*(D90/100)*F90) -> 0 | K90: =J90/0.8 -> 0 | L90: =IF(E90=0,0,VLOOKUP(E90,'Prix Matiere'!$A$4:$J$65,10)) -> 0 | M90: =L90*K90 -> 0 | N90: =IF(J90=0,0,(4.7283*J90)+3) -> 0 | O90: =N90*MinuteMO -> 0 | P90: =IF(J90=0,0,J90*VLOOKUP(E90,'Prix Matiere'!$A$4:$L$60,12)) -> 0 | Q90: =IF(J90=0,0,P90*VLOOKUP(E90,'Prix Matiere'!$A$4:$L$60,11)) -> 0
B91: Dessus dessous | C91: =IF(F91=0,0,C39) -> 0 | D91: =IF(F91=0,0,D94) -> 0 | E91: =IF($C$17="Aucun",0,VLOOKUP($C$17,A146:P152,6)) -> 0 | F91: =VLOOKUP($C$17,A146:P152,7) -> 0 | J91: =IF(C91=0,0,(C91/100)*(D91/100)*F91) -> 0 | K91: =J91/0.8 -> 0 | L91: =IF(E91=0,0,VLOOKUP(E91,'Prix Matiere'!$A$4:$J$65,10)) -> 0 | M91: =L91*K91 -> 0 | N91: =IF(J91=0,0,(4.7283*J91)+3) -> 0 | O91: =N91*MinuteMO -> 0 | P91: =IF(J91=0,0,J91*VLOOKUP(E91,'Prix Matiere'!$A$4:$L$60,12)) -> 0 | Q91: =IF(J91=0,0,P91*VLOOKUP(E91,'Prix Matiere'!$A$4:$L$60,11)) -> 0
B92: Bouts | C92: =IF(F92=0,0,E94) -> 0 | D92: =IF(F92=0,0,D94) -> 0 | E92: =IF($C$17="Aucun",0,VLOOKUP($C$17,A146:P152,6)) -> 0 | F92: =VLOOKUP($C$17,A146:P152,7) -> 0 | J92: =IF(C92=0,0,(C92/100)*(D92/100)*F92) -> 0 | K92: =J92/0.8 -> 0 | L92: =IF(E92=0,0,VLOOKUP(E92,'Prix Matiere'!$A$4:$J$65,10)) -> 0 | M92: =L92*K92 -> 0 | N92: =IF(J92=0,0,(4.7283*J92)+3) -> 0 | O92: =N92*MinuteMO -> 0 | P92: =IF(J92=0,0,J92*VLOOKUP(E92,'Prix Matiere'!$A$4:$L$60,12)) -> 0 | Q92: =IF(J92=0,0,P92*VLOOKUP(E92,'Prix Matiere'!$A$4:$L$60,11)) -> 0
P93: =IF(J93=0,0,J93*VLOOKUP(E93,'Prix Matiere'!$A$4:$L$60,12)) -> 0 | Q93: =IF(J93=0,0,P93*VLOOKUP(E93,'Prix Matiere'!$A$4:$L$60,11)) -> 0
B94: Dimensions intérieures mousse | C94: =C39-VLOOKUP(C17,A146:P152,5) -> 239.9 | D94: =D39-VLOOKUP(C17,A146:P152,5) -> 19.9 | E94: =E39-VLOOKUP(C17,A146:P152,5) -> 189.2 | P94: =IF(J94=0,0,J94*VLOOKUP(E94,'Prix Matiere'!$A$4:$L$60,12)) -> 0 | Q94: =IF(J94=0,0,P94*VLOOKUP(E94,'Prix Matiere'!$A$4:$L$60,11)) -> 0
P95: =IF(J95=0,0,J95*VLOOKUP(E95,'Prix Matiere'!$A$4:$L$60,12)) -> 0 | Q95: =IF(J95=0,0,P95*VLOOKUP(E95,'Prix Matiere'!$A$4:$L$60,11)) -> 0
A96: Extrudé 1 | B96: GC | C96: =IF(F96=0,0,C100+VLOOKUP(C17,A146:P152,8))-0.5 -> 239.4 | D96: =IF(F96=0,0,E100+VLOOKUP(C17,A146:P152,8))-0.5 -> 188.7 | E96: =VLOOKUP(C17,A146:P152,9) -> Styro 30 mm | F96: =VLOOKUP($C$17,A146:P152,10) -> 2 | J96: =IF(C96=0,0,(C96/100)*(D96/100)*F96) -> 9.034956 | K96: =J96/0.8 -> 11.293695 | L96: =IF(E96=0,0,VLOOKUP(E96,'Prix Matiere'!A4:J60,10)) -> 7.014433 | M96: =L96*K96 -> 79.218867 | N96: =IF(J96=0,0,(3.94*J96)+5) -> 40.597727 | O96: =N96*MinuteMO -> 34.508068 | P96: =IF(J96=0,0,J96*VLOOKUP(E96,'Prix Matiere'!$A$4:$L$60,12)) -> 9.2156551 | Q96: =IF(J96=0,0,P96*VLOOKUP(E96,'Prix Matiere'!$A$4:$L$60,11)) -> 27.186183
B97: Dessus dessous | C97: =IF(F97=0,0,C100+VLOOKUP(C17,A146:P152,8)) -> 239.9 | D97: =IF(F97=0,0,D100) -> 13.9 | E97: =VLOOKUP(C17,A146:P152,9) -> Styro 30 mm | F97: =VLOOKUP($C$17,A146:P152,10) -> 2 | J97: =IF(C97=0,0,(C97/100)*(D97/100)*F97) -> 0.666922 | K97: =J97/0.8 -> 0.8336525 | L97: =IF(E97=0,0,VLOOKUP(E97,'Prix Matiere'!A5:J61,10)) -> 7.014433 | M97: =L97*K97 -> 5.8475996 | N97: =IF(J97=0,0,(3.94*J97)+5) -> 7.6276727 | O97: =N97*MinuteMO -> 6.4835218 | P97: =IF(J97=0,0,J97*VLOOKUP(E97,'Prix Matiere'!$A$4:$L$60,12)) -> 0.68026044 | Q97: =IF(J97=0,0,P97*VLOOKUP(E97,'Prix Matiere'!$A$4:$L$60,11)) -> 2.0067683
B98: Bouts | C98: =IF(F98=0,0,E100) -> 183.2 | D98: =IF(F98=0,0,D100) -> 13.9 | E98: =VLOOKUP(C17,A146:P152,9) -> Styro 30 mm | F98: =VLOOKUP($C$17,A146:P152,10) -> 2 | J98: =IF(C98=0,0,(C98/100)*(D98/100)*F98) -> 0.509296 | K98: =J98/0.8 -> 0.63662 | L98: =IF(E98=0,0,VLOOKUP(E98,'Prix Matiere'!A6:J62,10)) -> 7.014433 | M98: =L98*K98 -> 4.4655283 | N98: =IF(J98=0,0,(3.94*J98)+5) -> 7.0066262 | O98: =N98*MinuteMO -> 5.9556323 | P98: =IF(J98=0,0,J98*VLOOKUP(E98,'Prix Matiere'!$A$4:$L$60,12)) -> 0.51948192 | Q98: =IF(J98=0,0,P98*VLOOKUP(E98,'Prix Matiere'!$A$4:$L$60,11)) -> 1.5324717
P99: =IF(J99=0,0,J99*VLOOKUP(E99,'Prix Matiere'!$A$4:$L$60,12)) -> 0 | Q99: =IF(J99=0,0,P99*VLOOKUP(E99,'Prix Matiere'!$A$4:$L$60,11)) -> 0
B100: Dimensions intérieures styro | C100: =C94-VLOOKUP(C17,A146:P152,8) -> 233.9 | D100: =D94-VLOOKUP(C17,A146:P152,8) -> 13.9 | E100: =E94-VLOOKUP(C17,A146:P152,8) -> 183.2 | P100: =IF(J100=0,0,J100*VLOOKUP(E100,'Prix Matiere'!$A$4:$L$60,12)) -> 0 | Q100: =IF(J100=0,0,P100*VLOOKUP(E100,'Prix Matiere'!$A$4:$L$60,11)) -> 0
J101: =IF(C101=0,0,(C101/100)*(D101/100)*F101) -> 0 | K101: =J101/0.8 -> 0 | P101: =IF(J101=0,0,J101*VLOOKUP(E101,'Prix Matiere'!$A$4:$L$60,12)) -> 0 | Q101: =IF(J101=0,0,P101*VLOOKUP(E101,'Prix Matiere'!$A$4:$L$60,11)) -> 0
A102: Plaquettes | B102: GC | C102: =IF(F102=0,0,C105) -> 0 | D102: =IF(F102=0,0,10) -> 0 | E102: =VLOOKUP(C17,A146:P152,12) -> 0 | F102: =VLOOKUP(C17,A146:P152,13) -> 0 | J102: =IF(C102=0,0,(C102/100)*(D102/100)*F102) -> 0 | K102: =J102/0.8 -> 0 | L102: =IF(E102=0,0,VLOOKUP(E102,'Prix Matiere'!$A$4:$J$65,10)) -> 0 | M102: =L102*K102 -> 0 | N102: =IF(J102=0,0,1+(6*J102)) -> 0 | O102: =N102*MinuteMO -> 0 | P102: =IF(J102=0,0,J102*VLOOKUP(E102,'Prix Matiere'!$A$4:$L$60,12)) -> 0 | Q102: =IF(J102=0,0,P102*VLOOKUP(E102,'Prix Matiere'!$A$4:$L$60,11)) -> 0
B103: Dessus dessous | C103: =IF(F103=0,0,D100) -> 0 | D103: =IF(F102=0,0,D102) -> 0 | E103: =VLOOKUP(C17,A146:P152,12) -> 0 | F103: =VLOOKUP(C17,A146:P152,13)*2 -> 0 | J103: =IF(C103=0,0,(C103/100)*(D103/100)*F103) -> 0 | K103: =J103/0.8 -> 0 | L103: =IF(E103=0,0,VLOOKUP(E103,'Prix Matiere'!$A$4:$J$65,10)) -> 0 | M103: =L103*K103 -> 0 | N103: =IF(J103=0,0,1+(6*J103)) -> 0 | O103: =N103*MinuteMO -> 0 | P103: =IF(J103=0,0,J103*VLOOKUP(E103,'Prix Matiere'!$A$4:$L$60,12)) -> 0 | Q103: =IF(J103=0,0,P103*VLOOKUP(E103,'Prix Matiere'!$A$4:$L$60,11)) -> 0
J104: =IF(C104=0,0,(C104/100)*(D104/100)*F104) -> 0 | K104: =J104/0.8 -> 0 | P104: =IF(J104=0,0,J104*VLOOKUP(E104,'Prix Matiere'!$A$4:$L$60,12)) -> 0 | Q104: =IF(J104=0,0,P104*VLOOKUP(E104,'Prix Matiere'!$A$4:$L$60,11)) -> 0
B105: Dimensions intérieures plaquettes | C105: =C100-VLOOKUP($C$17,A146:P152,11) -> 233.9 | D105: =D100-VLOOKUP($C$17,A146:P152,11) -> 13.9 | E105: =E100-VLOOKUP($C$17,A146:P152,11) -> 183.2 | J105: =IF(C105=0,0,(C105/100)*(D105/100)*F105) -> 0 | K105: =J105/0.8 -> 0 | P105: =IF(J105=0,0,J105*VLOOKUP(E105,'Prix Matiere'!$A$4:$L$60,12)) -> 0 | Q105: =IF(J105=0,0,P105*VLOOKUP(E105,'Prix Matiere'!$A$4:$L$60,11)) -> 0
J106: =IF(C106=0,0,(C106/100)*(D106/100)*F106) -> 0 | K106: =J106/0.8 -> 0 | P106: =IF(J106=0,0,J106*VLOOKUP(E106,'Prix Matiere'!$A$4:$L$60,12)) -> 0 | Q106: =IF(J106=0,0,P106*VLOOKUP(E106,'Prix Matiere'!$A$4:$L$60,11)) -> 0
A107: Extrudé 2 | B107: GC | C107: =IF(F107=0,0,C111+VLOOKUP($C$17,A146:P152,14)) -> 0 | D107: =IF(F107=0,0,E111+VLOOKUP($C$17,A146:P152,14)) -> 0 | E107: =VLOOKUP($C$17,A146:P152,15) -> 0 | F107: =VLOOKUP($C$17,A146:P152,16) -> 0 | J107: =IF(C107=0,0,(C107/100)*(D107/100)*F107) -> 0 | K107: =J107/0.8 -> 0 | L107: =IF(E107=0,0,VLOOKUP(E107,'Prix Matiere'!A4:J60,10)) -> 0 | M107: =L107*K107 -> 0 | N107: =IF(J107=0,0,(3.94*J107)+5) -> 0 | O107: =N107*MinuteMO -> 0 | P107: =IF(J107=0,0,J107*VLOOKUP(E107,'Prix Matiere'!$A$4:$L$60,12)) -> 0 | Q107: =IF(J107=0,0,P107*VLOOKUP(E107,'Prix Matiere'!$A$4:$L$60,11)) -> 0
B108: Dessus dessous | C108: =IF(F108=0,0,C111+VLOOKUP($C$17,A146:P152,14)) -> 0 | D108: =IF(F108=0,0,D111) -> 0 | E108: =VLOOKUP($C$17,A146:P152,15) -> 0 | F108: =VLOOKUP($C$17,A146:P152,16) -> 0 | J108: =IF(C108=0,0,(C108/100)*(D108/100)*F108) -> 0 | K108: =J108/0.8 -> 0 | L108: =IF(E108=0,0,VLOOKUP(E108,'Prix Matiere'!A5:J61,10)) -> 0 | M108: =L108*K108 -> 0 | N108: =IF(J108=0,0,(3.94*J108)+5) -> 0 | O108: =N108*MinuteMO -> 0 | P108: =IF(J108=0,0,J108*VLOOKUP(E108,'Prix Matiere'!$A$4:$L$60,12)) -> 0 | Q108: =IF(J108=0,0,P108*VLOOKUP(E108,'Prix Matiere'!$A$4:$L$60,11)) -> 0
B109: Bouts | C109: =IF(F109=0,0,E111) -> 0 | D109: =IF(F109=0,0,D111) -> 0 | E109: =VLOOKUP($C$17,A146:P152,15) -> 0 | F109: =VLOOKUP($C$17,A146:P152,16) -> 0 | J109: =IF(C109=0,0,(C109/100)*(D109/100)*F109) -> 0 | K109: =J109/0.8 -> 0 | L109: =IF(E109=0,0,VLOOKUP(E109,'Prix Matiere'!A6:J62,10)) -> 0 | M109: =L109*K109 -> 0 | N109: =IF(J109=0,0,(3.94*J109)+5) -> 0 | O109: =N109*MinuteMO -> 0 | P109: =IF(J109=0,0,J109*VLOOKUP(E109,'Prix Matiere'!$A$4:$L$60,12)) -> 0 | Q109: =IF(J109=0,0,P109*VLOOKUP(E109,'Prix Matiere'!$A$4:$L$60,11)) -> 0
J110: =IF(C110=0,0,(C110/100)*(D110/100)*F110) -> 0 | K110: =J110/0.8 -> 0 | P110: =IF(J110=0,0,J110*VLOOKUP(E110,'Prix Matiere'!$A$4:$L$60,12)) -> 0 | Q110: =IF(J110=0,0,P110*VLOOKUP(E110,'Prix Matiere'!$A$4:$L$60,11)) -> 0
B111: Dimensions intérieures styro | C111: =C105-VLOOKUP($C$17,A146:P152,14) -> 233.9 | D111: =D105-VLOOKUP($C$17,A146:P152,14) -> 13.9 | E111: =E105-VLOOKUP($C$17,A146:P152,14) -> 183.2 | J111: =IF(C111=0,0,(C111/100)*(D111/100)*F111) -> 0 | K111: =J111/0.8 -> 0 | P111: =IF(J111=0,0,J111*VLOOKUP(E111,'Prix Matiere'!$A$4:$L$60,12)) -> 0 | Q111: =IF(J111=0,0,P111*VLOOKUP(E111,'Prix Matiere'!$A$4:$L$60,11)) -> 0
J112: =IF(C112=0,0,(C112/100)*(D112/100)*F112) -> 0 | K112: =J112/0.8 -> 0 | P112: =IF(J112=0,0,J112*VLOOKUP(E112,'Prix Matiere'!$A$4:$L$60,12)) -> 0 | Q112: =IF(J112=0,0,P112*VLOOKUP(E112,'Prix Matiere'!$A$4:$L$60,11)) -> 0
A113: Mousse de calage | J113: =IF(C113=0,0,(C113/100)*(D113/100)*F113) -> 0 | K113: =J113/0.8 -> 0 | P113: =IF(J113=0,0,J113*VLOOKUP(E113,'Prix Matiere'!$A$4:$L$60,12)) -> 0 | Q113: =IF(J113=0,0,P113*VLOOKUP(E113,'Prix Matiere'!$A$4:$L$60,11)) -> 0
J114: =IF(C114=0,0,(C114/100)*(D114/100)*F114) -> 0 | K114: =J114/0.8 -> 0 | P114: =IF(J114=0,0,J114*VLOOKUP(E114,'Prix Matiere'!$A$4:$L$60,12)) -> 0 | Q114: =IF(J114=0,0,P114*VLOOKUP(E114,'Prix Matiere'!$A$4:$L$60,11)) -> 0
B115: =IF(B37="Aucun",0,"Plots Dessus/Dessous") -> 0 | C115: =IF(B37="Aucun",0,46) -> 0 | D115: =IF(B37="Aucun",0,D111) -> 0 | E115: =IF(B37="Aucun",0,B37) -> 0 | F115: =IF(B37="Aucun",0,IF(C111<150,6,IF(C111<300,10,12))) -> 0 | J115: =IF(C115=0,0,(C115/100)*(D115/100)*F115) -> 0 | K115: =J115/0.8 -> 0 | L115: =IF(E115=0,0,VLOOKUP(E115,'Prix Matiere'!$A$4:$J$65,10)) -> 0 | M115: =L115*K115 -> 0 | N115: =IF(J115=0,0,4.7283*J115+2) -> 0 | O115: =N115*MinuteMO -> 0 | P115: =IF(J115=0,0,J115*VLOOKUP(E115,'Prix Matiere'!$A$4:$L$60,12)) -> 0 | Q115: =IF(J115=0,0,P115*VLOOKUP(E115,'Prix Matiere'!$A$4:$L$60,11)) -> 0
B116: =IF(B37="Aucun",0,"Plots Bouts") -> 0 | C116: =IF(B37="Aucun",0,45) -> 0 | D116: =IF(B37="Aucun",0,D111) -> 0 | E116: =IF(B37="Aucun",0,B37) -> 0 | F116: =IF(B37="Aucun",0,IF(E11<150,6,IF(E111<300,10,12))) -> 0 | J116: =IF(C116=0,0,(C116/100)*(D116/100)*F116) -> 0 | K116: =J116/0.8 -> 0 | L116: =IF(E116=0,0,VLOOKUP(E116,'Prix Matiere'!$A$4:$J$65,10)) -> 0 | M116: =L116*K116 -> 0 | N116: =IF(J116=0,0,4.7283*J116+2) -> 0 | O116: =N116*MinuteMO -> 0 | P116: =IF(J116=0,0,J116*VLOOKUP(E116,'Prix Matiere'!$A$4:$L$60,12)) -> 0 | Q116: =IF(J116=0,0,P116*VLOOKUP(E116,'Prix Matiere'!$A$4:$L$60,11)) -> 0
B117: =IF(B37="Aucun",0,"Angles") -> 0 | C117: =IF(B37="Aucun",0,45) -> 0 | D117: =C117 -> 0 | E117: =IF(B37="Aucun",0,B37) -> 0 | F117: =IF(B37="Aucun",0,4) -> 0 | J117: =IF(C117=0,0,(C117/100)*(D117/100)*F117) -> 0 | K117: =J117/0.8 -> 0 | L117: =IF(E117=0,0,VLOOKUP(E117,'Prix Matiere'!$A$4:$J$65,10)) -> 0 | M117: =L117*K117 -> 0 | N117: =IF(J117=0,0,4.7283*J117+2) -> 0 | O117: =N117*MinuteMO -> 0 | P117: =IF(J117=0,0,J117*VLOOKUP(E117,'Prix Matiere'!$A$4:$L$60,12)) -> 0 | Q117: =IF(J117=0,0,P117*VLOOKUP(E117,'Prix Matiere'!$A$4:$L$60,11)) -> 0
...

Sheet MRT
A1: MRT
B4: N° de dossier | E4: Responsable Dossier | F4: Grégory MORA
B5: Ville de destination | E5: Client | F5: ESI
B6: N° de caisse | E6: Délai
B8: Type de Contreplaqué | C8: Peuplier 15 mm | E8: Catégorie | F8: MRT
E9: Clouage
B10: Barres | C10: Pin raboté 4 faces
B12: Fermeture | C12: Vis bois | E12: =VLOOKUP($F$5,'Infos Clients'!$B$2:$G$10,2) -> #VALUE!
B14: Poignées | C14: Métal x 2 sur bouts
C18: Longueur | D18: Epaisseur | E18: Hauteur | F18: =IF(B19="Dimensions de l'œuvre","Face du MRT",0) -> Face du MRT | G18: =IF(B19="Dimensions de l'œuvre","Arrière du MRT",0) -> Arrière du MRT
B19: Dimensions de l'oeuvre | C19: 244 | D19: 3.5 | E19: 246 | F19: Mrt Ouvert | G19: Mrt Ouvert
B23: Dimensions intérieures caisse | C23: =C25-4.2 -> 264 | D23: =IF(D19<6,9.4,IF(D19<11,14.4,D19+9.4)) -> 9.4 | E23: =E25-4.2 -> 256 | F23: Prix d'achat Arckx
B25: Dimensions extérieures caisse | C25: =IF($B$19="Dimensions ext MRT existant",C19,IF($B$19="Aucun",0,C19+24.2)) -> 268.2 | D25: =IF($B$19="Dimensions ext MRT existant",D19,IF($B$19="Aucun",0,D23+1.5+VLOOKUP($G$19,$A$77:$C$81,3)+VLOOKUP($F$19,A77:C81,3))) -> 13.9 | E25: =IF($B$19="Dimensions ext MRT existant",E19,IF($B$19="Aucun",0,E19+14.2)) -> 260.2 | F25: =C55 -> 246.63234
B27: Poids de la Caisse | C27: =P47 -> 30.98816 | D27: Kg | E27: Bilan Carbone
B28: Minutes de Production | C28: =D49 -> 68.348321 | D28: Min | E28: =Q47 -> 21.105764
B30: Commentaires
A34: MRT 1
P35: Poids KG | Q35: CO²
B36: Dessus dessous bois massif | C36: =IF(B19="Dimensions ext MRT existant",0,C25) -> 268.2 | D36: =IF(B19="Dimensions ext MRT existant",0,D23) -> 9.4 | E36: Barres 21 R4F | F36: =IF(C36=0,0,2) -> 2 | J36: =IF(C36=0,0,(C36/100)*(D36/100)*F36) -> 0.504216 | K36: =J36/0.8 -> 0.63027 | L36: =IF(E36=0,0,VLOOKUP(E36,'Prix Matiere'!$A$4:$J$65,10)) -> 18.969072 | M36: =L36*K36 -> 11.955637 | N36: =IF(C36=0,0,4+(11*J36)) -> 9.546376 | O36: =N36*MinuteMO -> 8.1144196 | P36: =IF(J36=0,0,J36*VLOOKUP(E36,'Prix Matiere'!$A$4:$L$60,12)) -> 5.04216 | Q36: =IF(J36=0,0,P36*VLOOKUP(E36,'Prix Matiere'!$A$4:$L$60,11)) -> 2.4404054
B37: Bouts bois massif avec poignées métalliques | C37: =IF(B19="Dimensions ext MRT existant",0,IF(E25=0,0,E25-4.2)) -> 256 | D37: =D36 -> 9.4 | E37: Barres 21 R4F | F37: =F36 -> 2 | J37: =IF(C37=0,0,(C37/100)*(D37/100)*F37) -> 0.48128 | K37: =J37/0.8 -> 0.6016 | L37: =IF(E37=0,0,VLOOKUP(E37,'Prix Matiere'!$A$4:$J$65,10)) -> 18.969072 | M37: =L37*K37 -> 11.411794 | N37: =IF(C37=0,0,4+(11*J37)) -> 9.29408 | O37: =N37*MinuteMO -> 7.899968 | P37: =IF(J37=0,0,J37*VLOOKUP(E37,'Prix Matiere'!$A$4:$L$60,12)) -> 4.8128 | Q37: =IF(J37=0,0,P37*VLOOKUP(E37,'Prix Matiere'!$A$4:$L$60,11)) -> 2.3293952
B38: =E38 -> Peuplier 15 mm | C38: =IF(C36=0,0,C36) -> 268.2 | D38: =IF(C38=0,0,25) -> 25 | E38: ="Peuplier 15 mm" -> Peuplier 15 mm | F38: =IF(C38=0,0,2) -> 2 | J38: =IF(C38=0,0,(C38/100)*(D38/100)*F38) -> 1.341 | K38: =J38/0.8 -> 1.67625 | L38: =IF(E38=0,0,VLOOKUP(E38,'Prix Matiere'!$A$4:$J$65,10)) -> 16.895876 | M38: =L38*K38 -> 28.321713 | N38: =IF(C38=0,0,(6.0924*J38)+10) -> 18.169908 | O38: =N38*MinuteMO -> 15.444422 | P38: =IF(J38=0,0,J38*VLOOKUP(E38,'Prix Matiere'!$A$4:$L$60,12)) -> 8.8506 | Q38: =IF(J38=0,0,P38*VLOOKUP(E38,'Prix Matiere'!$A$4:$L$60,11)) -> 6.8415138
B39: =E39 -> Peuplier 15 mm | C39: =IF(C38=0,0,E25-2*D38) -> 210.2 | D39: =D38 -> 25 | E39: ="Peuplier 15 mm" -> Peuplier 15 mm | F39: =IF(C39=0,0,2) -> 2 | J39: =IF(C39=0,0,(C39/100)*(D39/100)*F39) -> 1.051 | K39: =J39/0.8 -> 1.31375 | L39: =IF(E39=0,0,VLOOKUP(E39,'Prix Matiere'!$A$4:$J$65,10)) -> 16.895876 | M39: =L39*K39 -> 22.196957 | N39: =IF(C39=0,0,(6.0924*J39)+10) -> 16.403112 | O39: =N39*MinuteMO -> 13.942646 | P39: =IF(J39=0,0,J39*VLOOKUP(E39,'Prix Matiere'!$A$4:$L$60,12)) -> 6.9366 | Q39: =IF(J39=0,0,P39*VLOOKUP(E39,'Prix Matiere'!$A$4:$L$60,11)) -> 5.3619918
B40: Angles cp 15 | C40: =IF(C36=0,0,45) -> 45 | D40: =IF(C40=0,0,45) -> 45 | E40: Peuplier 15 mm | F40: =IF(C40=0,0,4) -> 4 | J40: =IF(C40=0,0,(C40/100)*(D40/100)*F40) -> 0.81 | K40: =J40/0.8 -> 1.0125 | L40: =IF(E40=0,0,VLOOKUP(E40,'Prix Matiere'!$A$4:$J$65,10)) -> 16.895876 | M40: =L40*K40 -> 17.107075 | N40: =IF(C40=0,0,(6.0924*J40)+10) -> 14.934844 | O40: =N40*MinuteMO -> 12.694617 | P40: =IF(J40=0,0,J40*VLOOKUP(E40,'Prix Matiere'!$A$4:$L$60,12)) -> 5.346 | Q40: =IF(J40=0,0,P40*VLOOKUP(E40,'Prix Matiere'!$A$4:$L$60,11)) -> 4.132458
B41: =G19 -> Mrt Ouvert | C41: =IF(B41=0,0,IF(B41="Mrt Ouvert",0,C25)) -> 0 | D41: =IF(B41=0,0,IF(B41="Mrt Ouvert",0,E25)) -> 0 | E41: =VLOOKUP(G19,$A$77:$C$81,2) -> 0 | F41: =IF(C41=0,0,1) -> 0 | J41: =IF(C41=0,0,(C41/100)*(D41/100)*F41) -> 0 | K41: =J41/0.8 -> 0 | L41: =IF(E41=0,0,IF(E41="Carton",Carton,VLOOKUP(E41,'Prix Matiere'!$A$4:$J$65,10))) -> 0 | M41: =L41*K41 -> 0 | N41: =IF(C41=0,0,1+(11*J41)) -> 0 | O41: =N41*MinuteMO -> 0 | P41: =IF(J41=0,0,IF(E41="Carton",Poids_Carton*J41,J41*VLOOKUP(E41,'Prix Matiere'!$A$4:$L$60,12))) -> 0 | Q41: =IF(J41=0,0,P41*VLOOKUP(E41,'Prix Matiere'!$A$4:$L$60,11)) -> 0
B42: =F19 -> Mrt Ouvert | C42: =IF(B42=0,0,IF(B42="Mrt Ouvert",0,C25)) -> 0 | D42: =IF(B42=0,0,IF(B42="Mrt Ouvert",0,E25)) -> 0 | E42: =VLOOKUP($F$19,$A$77:$C$81,2) -> 0 | F42: =IF(C42=0,0,1) -> 0 | J42: =IF(C42=0,0,(C42/100)*(D42/100)*F42) -> 0 | K42: =J42/0.8 -> 0 | L42: =IF(E42=0,0,IF(E42="Carton",Carton,VLOOKUP(E42,'Prix Matiere'!$A$4:$J$65,10))) -> 0 | M42: =L42*K42 -> 0 | N42: =IF(C42=0,0,1+(11*J42)) -> 0 | O42: =N42*MinuteMO -> 0 | P42: =IF(J42=0,0,IF(E42="Carton",Poids_Carton*J42,J42*VLOOKUP(E42,'Prix Matiere'!$A$4:$L$60,12))) -> 0 | Q42: =IF(J42=0,0,P42*VLOOKUP(E42,'Prix Matiere'!$A$4:$L$60,11)) -> 0
O45: =N45*MinuteMO -> 0
L47: =IF(E47=0,0,VLOOKUP(E47,'Prix Matiere'!$A$4:$J$65,10)) -> 0 | M47: =SUM(M34:M46) -> 90.993176 | N47: =SUM(N34:N46) -> 68.348321 | O47: =N47*MinuteMO -> 58.096073 | P47: =SUM(P36:P46) -> 30.98816 | Q47: =SUM(Q36:Q46) -> 21.105764
B48: Total matière | C48: =IF($F$4=0,0,SUM(M36:M42)) -> 90.993176 | E48: Contreplaqué | F48: =CONCATENATE(ROUNDUP(SUM(J38:J40),2)," m²") -> 3,21 m² | G48: =(SUM(M38:M40)) -> 67.625745
B49: Total MO | C49: =IF($F$4=0,0,SUM(O36:O42)) -> 58.096073 | D49: =IF($F$4=0,0,SUM(N36:N42)) -> 68.348321 | E49: Bois massif | F49: =CONCATENATE(ROUNDUP(SUM(J36:J37),2)," m²") -> 0,99 m² | G49: =(SUM(M36:M37)) -> 23.367431
B50: Total frais généraux | C50: =IF($F$4=0,0,((C48+C49)/Frais_Généraux)-(C48+C49)) -> 80.278826
B51: Total revient | C51: =IF($F$4=0,0,SUM(C48:C50)) -> 229.36807
B52: Marge | C52: =IF($F$4=0,0,(C51/(1-Marge)-C51)) -> 17.264264 | D52: =C51+C52 -> 246.63234
B53: Remise (-) ou Majoration (+) en % | C53: =IF($F$5="BOVIS",((C51+C52)*(1+C54))-(C51+C52),((C51+C52)*(1+D53))-(C51+C52)) -> 0
C54: =IF($F$5="BOVIS",0.03,0) -> 0
B55: Prix de vente | C55: =SUM(C51:C54) -> 246.63234 | E55: Divers | G55: =C48-SUM(G48:G52) -> 0
A58: Peuplier 15 mm | B58: Peuplier 15 mm | C58: Peuplier 15 mm | D58: 1.5
A60: Pin raboté 4 faces | B60: Pin 21 mm | C60: Pin 21 mm | D60: 2.1
A63: Bois | B63: 4.2
A64: Métal x 2 sur bouts | B64: 2
A65: Métal x 4 sur GC | B65: 0
A67: A Plat | B67: 0 | D67: 0
A68: A Plat + Chapeau | B68: 10 | C68: 30 | D68: 10
A69: Aucun | B69: 0 | D69: 0
A70: Carton Fleur Melinex | B70: 5 | C70: 15 | D70: 0
A71: Tyvek | B71: 10 | C71: 30 | D71: 0
A73: Aucun
A74: Dimensions de l'oeuvre
A75: Dimensions ext MRT existant
A77: Mrt Fermé Carton Double | B77: Carton | C77: =0.9+1.5 -> 2.4
A78: Mrt Fermé Carton Triple | B78: Carton Triple | C78: =1.4+1.5 -> 2.9
A79: Mrt Fermé cp 10 mm | B79: Peuplier 10 mm | C79: =1+1.5 -> 2.5
A80: Mrt Fermé Macrolon 10 mm | B80: Marcrolon | C80: 1
A81: Mrt Ouvert | C81: 1.5

Sheet T1 LOUVRE
A1: Caisse Tableau Louvre
E3: =IF(C19="Boulons et platines","Boulons et Platines",0) -> 0 | F3: =IF(E3="Boulons et Platines","Nbre de Trous",0) -> 0 | G3: =IF(E3="Boulons et Platines","Dim du Bord",0) -> 0
E4: =IF(C19="Vis bois",0,"Trous dans la Longueur") -> 0 | F4: =IF(E4=0,0,IF(C54<100,2,IF(C54<150,3,IF(C54<200,4,IF(C54<250,5,IF(C54<300,6,7)))))) -> 0 | G4: =IF(F4=0,0,IF(F4=3,0,(($C$54-32)/(F4-1))+16)) -> 0
E5: =IF(F4=6,"2ème Trou",IF(F4=7,"2ème Trou",0)) -> 0 | G5: =IF(E5=0,0,G4+G4-16) -> 0
E6: =IF(C19="Vis bois",0,"Trous dans la Hauteur") -> 0 | F6: =IF(E6=0,0,IF(D54<100,2,IF(D54<150,3,IF(D54<200,4,IF(D54<250,5,IF(D54<310,6,7)))))) -> 0 | G6: =IF(F6=0,0,IF(F6=3,0,(($D$54-32)/(F6-1))+16)) -> 0
E7: =IF(F6=6,"2ème Trou",IF(F6=7,"2ème Trou",0)) -> 0 | G7: =IF(E7=0,0,G6+G6-16) -> 0
B9: N° de dossier | E9: Responsable Dossier | F9: Grégory MORA
B10: Ville de destination | E10: Client | F10: ESI
B11: N° de caisse | E11: Délai
B13: Type de Contreplaqué | C13: Peuplier 15 mm | I13: =VLOOKUP($F$10,'Infos Clients'!$B$2:$G$10,2) -> #VALUE!
B15: Barres | C15: Pin raboté 4 faces | E15: Garnissage | F15: Valsem
B17: Type d'isolant | C17: Isotherme en 50
B19: Fermeture | C19: Vis bois | E19: Peinture | F19: Non
E20: =IF(F19="Oui","Type de Peinture",0) -> 0 | F20: =IF(F19="Non",0,VLOOKUP(F10,'Infos Clients'!B2:E10,4)) -> 0
B21: Poignées | C21: Bois | E21: Tyvek | F21: Non
B23: Skis | C23: Skis en 30 mm | E23: Option Calage | F23: Aucun
B25: =IF(F23="Aucun"," ",F23) | D25: =IF(F21="Oui","+",0) -> 0 | E25: =IF(F21="Oui","Mousse Garnie Tyvek",0) -> 0
B26: =IF(F10="Bovis","Attention retirer 2 mm aux dimensions transmises",0) -> 0
C28: Longueur | D28: Epaisseur | E28: Hauteur
B29: =IF(B31="Aucun","Dimensions intérieures utiles","Dimensions de l'œuvre") -> Dimensions de l'œuvre | C29: 21.7 | D29: 16.5 | E29: 3.5
A31: Type de calage | B31: Bandes de mousse
C32: Largeur | D32: Longueur | E32: Epaisseur | F32: Quantité
B33: Dessus | C33: 10
B34: Dessous | C34: 10
B35: Agglocelle 50 mm | C35: =+IF(C29=0,0,IF(C29>70,12,6)) -> 6 | F35: =IF(C29>300,6,IF(C29>250,5,IF(C29>200,4,IF(C29>150,3,IF(C29>120,3,2))))) -> 2
B36: Rattrapage
B38: Remplissage 1
B39: Remplissage 2
B41: Dimensions intérieures caisse | C41: =C29+VLOOKUP(C17,A132:P138,2)+VLOOKUP(B31,A161:L166,2) -> 41.9 | D41: =D29+VLOOKUP($B$31,A161:L166,3)+VLOOKUP($C$17,A132:P138,3) -> 41.5 | E41: =E29+VLOOKUP($B$31,A161:L166,4)+VLOOKUP($C$17,A132:P138,4) -> 23.7 | F41: Prix d'achat Arckx
B43: Dimensions extérieures caisse | C43: =C41+VLOOKUP(C21,A146:B148,2)+VLOOKUP(C13,A125:D125,4)*2+VLOOKUP(C15,A127:D127,4)*2 -> 53.3 | D43: =IF(OR($F$23="Aucun",$F$23="Stabilisateur"),$D$41+VLOOKUP($C$13,$A$125:$D$125,4)*2+VLOOKUP($C$15,$A$127:$D$127,4)*2+0.5,$E$41+VLOOKUP($C$13,$A$125:$D$125,5)*2+VLOOKUP($C$15,$A$127:$D$127,4)*2) -> 49.2 | E43: =IF(OR($F$23="Aucun",$F$23="Stabilisateur"),$E$41+VLOOKUP($C$13,$A$125:$D$125,4)*2+VLOOKUP($C$15,$A$127:$D$127,4)*2+VLOOKUP($C$23,$A$168:$B$170,2),$D$41+VLOOKUP($C$13,$A$125:$D$125,4)*2+VLOOKUP($C$15,$A$127:$D$127,4)*2+VLOOKUP($C$23,$A$168:$B$170,2)+VLOOKUP($F$23,$A$150:$D$153,4)+0.5) -> 33.9 | F43: =ROUNDUP(C122,0) -> 222
B45: Poids de la Caisse | C45: =Q114 -> 13.167892 | D45: Kg | E45: Bilan Carbone
B46: Minutes de Production | C46: =D116 -> 104.25419 | D46: Min | E46: =R114 -> 10.759756
B48: Commentaires
F53: Quantité | Q53: Poids KG | R53: CO²
A54: Grand côtés | B54: =VLOOKUP(C13,A125:D125,2) -> Peuplier 15 mm | C54: =IF(C41=0,0,C41+2*(VLOOKUP(B54,A125:D125,4)+VLOOKUP(C15,A127:D127,4))) -> 49.1 | D54: =IF(E41=0,0,E41+2*(VLOOKUP(B54,A125:D125,4)+VLOOKUP(C15,A127:D127,4))) -> 30.9 | E54: =B54 -> Peuplier 15 mm | F54: 2 | J54: =IF(C54=0,0,(C54/100)*(D54/100)*F54) -> 0.303438 | K54: =J54/0.8 -> 0.3792975 | L54: =IF(E54=0,0,VLOOKUP(E54,'Prix Matiere'!$A$4:$J$65,10)) -> 16.895876 | M54: =L54*K54 -> 6.4085636 | N54: =IF(J54=0,0,(7.0924*J54)+15) -> 17.152104 | O54: =N54*MinuteMO -> 14.579288 | Q54: =IF(J54=0,0,J54*VLOOKUP(E54,'Prix Matiere'!$A$4:$L$60,12)) -> 2.0026908 | R54: =IF(J54=0,0,Q54*VLOOKUP(E54,'Prix Matiere'!$A$4:$L$60,11)) -> 1.54808
A55: Dessus dessous | B55: =VLOOKUP(C13,A125:D125,3) -> Peuplier 15 mm | C55: =C54 -> 49.1 | D55: =D41 -> 41.5 | E55: =B55 -> Peuplier 15 mm | F55: 2 | J55: =IF(C55=0,0,(C55/100)*(D55/100)*F55) -> 0.40753 | K55: =J55/0.8 -> 0.5094125 | L55: =IF(E55=0,0,VLOOKUP(E55,'Prix Matiere'!$A$4:$J$65,10)) -> 16.895876 | M55: =L55*K55 -> 8.6069706 | N55: =IF(J55=0,0,(7.0924*J55)+15) -> 17.890366 | O55: =N55*MinuteMO -> 15.206811 | Q55: =IF(J55=0,0,J55*VLOOKUP(E55,'Prix Matiere'!$A$4:$L$60,12)) -> 2.689698 | R55: =IF(J55=0,0,Q55*VLOOKUP(E55,'Prix Matiere'!$A$4:$L$60,11)) -> 2.0791366
A56: Bouts | B56: =VLOOKUP(C13,A125:D125,3) -> Peuplier 15 mm | C56: =E41 -> 23.7 | D56: =D41 -> 41.5 | E56: =B56 -> Peuplier 15 mm | F56: 2 | J56: =IF(C56=0,0,(C56/100)*(D56/100)*F56) -> 0.19671 | K56: =J56/0.8 -> 0.2458875 | L56: =IF(E56=0,0,VLOOKUP(E56,'Prix Matiere'!$A$4:$J$65,10)) -> 16.895876 | M56: =L56*K56 -> 4.1544848 | N56: =IF(J56=0,0,(7.0924*J56)+15) -> 16.395146 | O56: =N56*MinuteMO -> 13.935874 | Q56: =IF(J56=0,0,J56*VLOOKUP(E56,'Prix Matiere'!$A$4:$L$60,12)) -> 1.298286 | R56: =IF(J56=0,0,Q56*VLOOKUP(E56,'Prix Matiere'!$A$4:$L$60,11)) -> 1.0035751
J57: =IF(C57=0,0,(C57/100)*(D57/100)*F57) -> 0 | K57: =J57/0.8 -> 0 | Q57: =IF(J57=0,0,J57*VLOOKUP(E57,'Prix Matiere'!$A$4:$L$60,12)) -> 0
J58: =IF(C58=0,0,(C58/100)*(D58/100)*F58) -> 0 | K58: =J58/0.8 -> 0 | Q58: =IF(J58=0,0,J58*VLOOKUP(E58,'Prix Matiere'!$A$4:$L$60,12)) -> 0
A59: Barres | B59: Barres de GC | C59: =C54 -> 49.1 | D59: =IF(D54>80,9.4,7) -> 7 | E59: =IF($C$15="Pin raboté 4 faces","Barres 21 R4F","Barres 19 mm") -> Barres 21 R4F | F59: 4 | J59: =IF(C59=0,0,(C59/100)*(D59/100)*F59) -> 0.13748 | K59: =J59/0.8 -> 0.17185 | L59: =IF(E59=0,0,VLOOKUP(E59,'Prix Matiere'!$A$4:$J$65,10)) -> 18.969072 | M59: =L59*K59 -> 3.2598351 | N59: =IF(J59=0,0,1+(11*J59)) -> 2.51228 | O59: =N59*MinuteMO -> 2.135438 | Q59: =IF(J59=0,0,J59*VLOOKUP(E59,'Prix Matiere'!$A$4:$L$60,12)) -> 1.3748 | R59: =IF(J59=0,0,Q59*VLOOKUP(E59,'Prix Matiere'!$A$4:$L$60,11)) -> 0.6654032
B60: Remplis GC | C60: =IF(D54=0,0,D54-2*D59) -> 16.9 | D60: =D59 -> 7 | E60: =IF($C$15="Pin raboté 4 faces","Barres 21 R4F","Barres 19 mm") -> Barres 21 R4F | F60: 4 | J60: =IF(C60=0,0,(C60/100)*(D60/100)*F60) -> 0.04732 | K60: =J60/0.8 -> 0.05915 | L60: =IF(E60=0,0,VLOOKUP(E60,'Prix Matiere'!$A$4:$J$65,10)) -> 18.969072 | M60: =L60*K60 -> 1.1220206 | N60: =IF(J60=0,0,1+(11*J60)) -> 1.52052 | O60: =N60*MinuteMO -> 1.292442 | Q60: =IF(J60=0,0,J60*VLOOKUP(E60,'Prix Matiere'!$A$4:$L$60,12)) -> 0.4732 | R60: =IF(J60=0,0,Q60*VLOOKUP(E60,'Prix Matiere'!$A$4:$L$60,11)) -> 0.2290288
B61: Dessus / Dessous | C61: =C59 -> 49.1 | D61: =IF($D$41<14.4,$D$41,7) -> 7 | E61: =IF($C$15="Pin raboté 4 faces","Barres 21 R4F","Barres 19 mm") -> Barres 21 R4F | F61: =IF(D41<14.4,2,4) -> 4 | J61: =IF(C61=0,0,(C61/100)*(D61/100)*F61) -> 0.13748 | K61: =J61/0.8 -> 0.17185 | L61: =IF(E61=0,0,VLOOKUP(E61,'Prix Matiere'!$A$4:$J$65,10)) -> 18.969072 | M61: =L61*K61 -> 3.2598351 | N61: =IF(J61=0,0,1+(11*J61)) -> 2.51228 | O61: =N61*MinuteMO -> 2.135438 | Q61: =IF(J61=0,0,J61*VLOOKUP(E61,'Prix Matiere'!$A$4:$L$60,12)) -> 1.3748 | R61: =IF(J61=0,0,Q61*VLOOKUP(E61,'Prix Matiere'!$A$4:$L$60,11)) -> 0.6654032
B62: =C23 -> Skis en 30 mm | C62: =IF(C54>120,((C54-75)/2),C54) -> 49.1 | D62: =IF($F$10="BOVIS",9.4,7) -> 7 | E62: =IF($B$62="Skis en 30 mm","Barres 30 R4F","Semelles R4F") -> Barres 30 R4F | F62: =IF(C54>120,4,2) -> 2 | J62: =IF(C62=0,0,(C62/100)*(D62/100)*F62) -> 0.06874 | K62: =J62/0.8 -> 0.085925 | L62: =IF(E62=0,0,VLOOKUP(E62,'Prix Matiere'!$A$4:$J$65,10)) -> 45.43299 | M62: =L62*K62 -> 3.9038296 | N62: =IF(J62=0,0,1+(11*J62)) -> 1.75614 | O62: =N62*MinuteMO -> 1.492719 | Q62: =IF(J62=0,0,J62*VLOOKUP(E62,'Prix Matiere'!$A$4:$L$60,12)) -> 0.6874 | R62: =IF(J62=0,0,Q62*VLOOKUP(E62,'Prix Matiere'!$A$4:$L$60,11)) -> 0.3327016
B63: Longueur Bouts | C63: =IF(D41<14.4,0,D41) -> 41.5 | D63: =IF(D41<14.4,0,D59) -> 7 | E63: =IF($C$15="Pin raboté 4 faces","Barres 21 R4F","Barres 19 mm") -> Barres 21 R4F | F63: =IF(D41<14.4,0,4) -> 4 | J63: =IF(C63=0,0,(C63/100)*(D63/100)*F63) -> 0.1162 | K63: =J63/0.8 -> 0.14525 | L63: =IF(E63=0,0,VLOOKUP(E63,'Prix Matiere'!$A$4:$J$65,10)) -> 18.969072 | M63: =L63*K63 -> 2.7552577 | N63: =IF(J63=0,0,1+(11*J63)) -> 2.2782 | O63: =N63*MinuteMO -> 1.93647 | Q63: =IF(J63=0,0,J63*VLOOKUP(E63,'Prix Matiere'!$A$4:$L$60,12)) -> 1.162 | R63: =IF(J63=0,0,Q63*VLOOKUP(E63,'Prix Matiere'!$A$4:$L$60,11)) -> 0.562408
B64: Hauteur Bouts | C64: =IF(D41<14.4,E41,C56-2*D63) -> 9.7 | D64: =IF($D$41<14.4,$D$41,IF($D$41<20,5,7)) -> 7 | E64: =IF($C$15="Pin raboté 4 faces","Barres 21 R4F","Barres 19 mm") -> Barres 21 R4F | F64: =IF(D41<14.4,2,4) -> 4 | J64: =IF(C64=0,0,(C64/100)*(D64/100)*F64) -> 0.02716 | K64: =J64/0.8 -> 0.03395 | L64: =IF(E64=0,0,VLOOKUP(E64,'Prix Matiere'!$A$4:$J$65,10)) -> 18.969072 | M64: =L64*K64 -> 0.644 | N64: =IF(J64=0,0,1+(11*J64)) -> 1.29876 | O64: =N64*MinuteMO -> 1.103946 | Q64: =IF(J64=0,0,J64*VLOOKUP(E64,'Prix Matiere'!$A$4:$L$60,12)) -> 0.2716 | R64: =IF(J64=0,0,Q64*VLOOKUP(E64,'Prix Matiere'!$A$4:$L$60,11)) -> 0.1314544
B65: =IF(D41<14.4,0,IF(C21="Bois","Poignées",IF(C21="Métal x 2 sur bouts","Supports poignées",0))) -> Poignées | C65: =IF(B65="Poignées",D56+VLOOKUP(C13,A125:D125,4)*2+4.2,IF(B65="Supports poignées",D56-2*D64,0)) -> 48.7 | D65: =IF(B65="Poignées",7,IF(B65="Supports poignées",9.4,0)) -> 7 | E65: Barres 21 R4F | F65: =IF(B65=0,0,2) -> 2 | J65: =IF(C65=0,0,(C65/100)*(D65/100)*F65) -> 0.06818 | K65: =J65/0.8 -> 0.085225 | L65: =IF(E65=0,0,VLOOKUP(E65,'Prix Matiere'!$A$4:$J$65,10)) -> 18.969072 | M65: =L65*K65 -> 1.6166392 | N65: =IF(J65=0,0,1+(11*J65)) -> 1.74998 | O65: =N65*MinuteMO -> 1.487483 | Q65: =IF(J65=0,0,J65*VLOOKUP(E65,'Prix Matiere'!$A$4:$L$60,12)) -> 0.6818 | R65: =IF(J65=0,0,Q65*VLOOKUP(E65,'Prix Matiere'!$A$4:$L$60,11)) -> 0.3299912
Q66: =IF(J66=0,0,J66*VLOOKUP(E66,'Prix Matiere'!$A$4:$L$60,12)) -> 0
Q67: =IF(J67=0,0,J67*VLOOKUP(E67,'Prix Matiere'!$A$4:$L$60,12)) -> 0
A68: Mousse 1 | B68: GC | C68: =IF(F68=0,0,C41) -> 0 | D68: =IF(F68=0,0,E72+VLOOKUP($C$17,A132:P138,5)) -> 0 | E68: =VLOOKUP($C$17,A132:P138,6) -> 0 | F68: =VLOOKUP($C$17,A132:P138,7) -> 0 | J68: =IF(C68=0,0,(C68/100)*(D68/100)*F68) -> 0 | K68: =J68/0.8 -> 0 | L68: =IF(E68=0,0,VLOOKUP(E68,'Prix Matiere'!$A$4:$J$65,10)) -> 0 | M68: =L68*K68 -> 0 | N68: =IF(J68=0,0,(4.7283*J68)+3) -> 0 | O68: =N68*MinuteMO -> 0 | Q68: =IF(J68=0,0,J68*VLOOKUP(E68,'Prix Matiere'!$A$4:$L$60,12)) -> 0 | R68: =IF(J68=0,0,Q68*VLOOKUP(E68,'Prix Matiere'!$A$4:$L$60,11)) -> 0
B69: Dessus dessous | C69: =IF(F69=0,0,C41) -> 0 | D69: =IF(F69=0,0,D72) -> 0 | E69: =IF($C$17="Aucun",0,VLOOKUP($C$17,A132:P138,6)) -> 0 | F69: =VLOOKUP($C$17,A132:P138,7) -> 0 | J69: =IF(C69=0,0,(C69/100)*(D69/100)*F69) -> 0 | K69: =J69/0.8 -> 0 | L69: =IF(E69=0,0,VLOOKUP(E69,'Prix Matiere'!$A$4:$J$65,10)) -> 0 | M69: =L69*K69 -> 0 | N69: =IF(J69=0,0,(4.7283*J69)+3) -> 0 | O69: =N69*MinuteMO -> 0 | Q69: =IF(J69=0,0,J69*VLOOKUP(E69,'Prix Matiere'!$A$4:$L$60,12)) -> 0 | R69: =IF(J69=0,0,Q69*VLOOKUP(E69,'Prix Matiere'!$A$4:$L$60,11)) -> 0
B70: Bouts | C70: =IF(F70=0,0,E72) -> 0 | D70: =IF(F70=0,0,D72) -> 0 | E70: =IF($C$17="Aucun",0,VLOOKUP($C$17,A132:P138,6)) -> 0 | F70: =VLOOKUP($C$17,A132:P138,7) -> 0 | J70: =IF(C70=0,0,(C70/100)*(D70/100)*F70) -> 0 | K70: =J70/0.8 -> 0 | L70: =IF(E70=0,0,VLOOKUP(E70,'Prix Matiere'!$A$4:$J$65,10)) -> 0 | M70: =L70*K70 -> 0 | N70: =IF(J70=0,0,(4.7283*J70)+3) -> 0 | O70: =N70*MinuteMO -> 0 | Q70: =IF(J70=0,0,J70*VLOOKUP(E70,'Prix Matiere'!$A$4:$L$60,12)) -> 0 | R70: =IF(J70=0,0,Q70*VLOOKUP(E70,'Prix Matiere'!$A$4:$L$60,11)) -> 0
Q71: =IF(J71=0,0,J71*VLOOKUP(E71,'Prix Matiere'!$A$4:$L$60,12)) -> 0
B72: Dimensions intérieures mousse | C72: =C41-VLOOKUP(C17,A132:P138,5) -> 41.9 | D72: =D41-VLOOKUP(C17,A132:P138,5) -> 41.5 | E72: =E41-VLOOKUP(C17,A132:P138,5) -> 23.7 | Q72: =IF(J72=0,0,J72*VLOOKUP(E72,'Prix Matiere'!$A$4:$L$60,12)) -> 0
Q73: =IF(J73=0,0,J73*VLOOKUP(E73,'Prix Matiere'!$A$4:$L$60,12)) -> 0
A74: Extrudé 1 | B74: GC | C74: =IF(F74=0,0,C78+VLOOKUP(C17,A132:P138,8))-0.5 -> 41.4 | D74: =IF(F74=0,0,E78+VLOOKUP(C17,A132:P138,8))-0.5 -> 23.2 | E74: =VLOOKUP(C17,A132:P138,9) -> Styro 50 mm | F74: =VLOOKUP($C$17,A132:P138,10) -> 2 | J74: =IF(C74=0,0,(C74/100)*(D74/100)*F74) -> 0.192096 | K74: =J74/0.8 -> 0.24012 | L74: =IF(E74=0,0,VLOOKUP(E74,'Prix Matiere'!A4:J60,10)) -> 10.313402 | M74: =L74*K74 -> 2.4764541 | N74: =IF(J74=0,0,(3.94*J74)+5) -> 5.7568582 | O74: =N74*MinuteMO -> 4.8933295 | Q74: =IF(J74=0,0,J74*VLOOKUP(E74,'Prix Matiere'!$A$4:$L$60,12)) -> 0.288144 | R74: =IF(J74=0,0,Q74*VLOOKUP(E74,'Prix Matiere'!$A$4:$L$60,11)) -> 0.8500248
B75: Dessus dessous | C75: =IF(F75=0,0,C78+VLOOKUP(C17,A132:P138,8)) -> 41.9 | D75: =IF(F75=0,0,D78) -> 31.5 | E75: =VLOOKUP(C17,A132:P138,9) -> Styro 50 mm | F75: =VLOOKUP($C$17,A132:P138,10) -> 2 | J75: =IF(C75=0,0,(C75/100)*(D75/100)*F75) -> 0.26397 | K75: =J75/0.8 -> 0.3299625 | L75: =IF(E75=0,0,VLOOKUP(E75,'Prix Matiere'!A5:J61,10)) -> 10.313402 | M75: =L75*K75 -> 3.4030359 | N75: =IF(J75=0,0,(3.94*J75)+5) -> 6.0400418 | O75: =N75*MinuteMO -> 5.1340355 | Q75: =IF(J75=0,0,J75*VLOOKUP(E75,'Prix Matiere'!$A$4:$L$60,12)) -> 0.395955 | R75: =IF(J75=0,0,Q75*VLOOKUP(E75,'Prix Matiere'!$A$4:$L$60,11)) -> 1.1680673
B76: Bouts | C76: =IF(F76=0,0,E78) -> 13.7 | D76: =IF(F76=0,0,D78) -> 31.5 | E76: =VLOOKUP(C17,A132:P138,9) -> Styro 50 mm | F76: =VLOOKUP($C$17,A132:P138,10) -> 2 | J76: =IF(C76=0,0,(C76/100)*(D76/100)*F76) -> 0.08631 | K76: =J76/0.8 -> 0.1078875 | L76: =IF(E76=0,0,VLOOKUP(E76,'Prix Matiere'!A6:J62,10)) -> 10.313402 | M76: =L76*K76 -> 1.1126872 | N76: =IF(J76=0,0,(3.94*J76)+5) -> 5.3400614 | O76: =N76*MinuteMO -> 4.5390522 | Q76: =IF(J76=0,0,J76*VLOOKUP(E76,'Prix Matiere'!$A$4:$L$60,12)) -> 0.129465 | R76: =IF(J76=0,0,Q76*VLOOKUP(E76,'Prix Matiere'!$A$4:$L$60,11)) -> 0.38192175
Q77: =IF(J77=0,0,J77*VLOOKUP(E77,'Prix Matiere'!$A$4:$L$60,12)) -> 0
B78: Dimensions intérieures styro | C78: =C72-VLOOKUP(C17,A132:P138,8) -> 31.9 | D78: =D72-VLOOKUP(C17,A132:P138,8) -> 31.5 | E78: =E72-VLOOKUP(C17,A132:P138,8) -> 13.7 | Q78: =IF(J78=0,0,J78*VLOOKUP(E78,'Prix Matiere'!$A$4:$L$60,12)) -> 0
J79: =IF(C79=0,0,(C79/100)*(D79/100)*F79) -> 0 | K79: =J79/0.8 -> 0 | Q79: =IF(J79=0,0,J79*VLOOKUP(E79,'Prix Matiere'!$A$4:$L$60,12)) -> 0
A80: Plaquettes | B80: GC | C80: =IF(F80=0,0,C83) -> 0 | D80: =IF(F80=0,0,10) -> 0 | E80: =VLOOKUP(C17,A132:P138,12) -> 0 | F80: =VLOOKUP(C17,A132:P138,13) -> 0 | J80: =IF(C80=0,0,(C80/100)*(D80/100)*F80) -> 0 | K80: =J80/0.8 -> 0 | L80: =IF(E80=0,0,VLOOKUP(E80,'Prix Matiere'!$A$4:$J$65,10)) -> 0 | M80: =L80*K80 -> 0 | N80: =IF(J80=0,0,1+(6*J80)) -> 0 | O80: =N80*MinuteMO -> 0 | Q80: =IF(J80=0,0,J80*VLOOKUP(E80,'Prix Matiere'!$A$4:$L$60,12)) -> 0 | R80: =IF(J80=0,0,Q80*VLOOKUP(E80,'Prix Matiere'!$A$4:$L$60,11)) -> 0
B81: Dessus dessous | C81: =IF(F81=0,0,D78) -> 0 | D81: =IF(F80=0,0,D80) -> 0 | E81: =VLOOKUP(C17,A132:P138,12) -> 0 | F81: =VLOOKUP(C17,A132:P138,13)*2 -> 0 | J81: =IF(C81=0,0,(C81/100)*(D81/100)*F81) -> 0 | K81: =J81/0.8 -> 0 | L81: =IF(E81=0,0,VLOOKUP(E81,'Prix Matiere'!$A$4:$J$65,10)) -> 0 | M81: =L81*K81 -> 0 | N81: =IF(J81=0,0,1+(6*J81)) -> 0 | O81: =N81*MinuteMO -> 0 | Q81: =IF(J81=0,0,J81*VLOOKUP(E81,'Prix Matiere'!$A$4:$L$60,12)) -> 0 | R81: =IF(J81=0,0,Q81*VLOOKUP(E81,'Prix Matiere'!$A$4:$L$60,11)) -> 0
J82: =IF(C82=0,0,(C82/100)*(D82/100)*F82) -> 0 | K82: =J82/0.8 -> 0 | Q82: =IF(J82=0,0,J82*VLOOKUP(E82,'Prix Matiere'!$A$4:$L$60,12)) -> 0
B83: Dimensions intérieures plaquettes | C83: =C78-VLOOKUP($C$17,A132:P138,11) -> 31.9 | D83: =D78-VLOOKUP($C$17,A132:P138,11) -> 31.5 | E83: =E78-VLOOKUP($C$17,A132:P138,11) -> 13.7 | J83: =IF(C83=0,0,(C83/100)*(D83/100)*F83) -> 0 | K83: =J83/0.8 -> 0 | Q83: =IF(J83=0,0,J83*VLOOKUP(E83,'Prix Matiere'!$A$4:$L$60,12)) -> 0
J84: =IF(C84=0,0,(C84/100)*(D84/100)*F84) -> 0 | K84: =J84/0.8 -> 0 | Q84: =IF(J84=0,0,J84*VLOOKUP(E84,'Prix Matiere'!$A$4:$L$60,12)) -> 0
A85: Extrudé 2 | B85: GC | C85: =IF(F85=0,0,C89+VLOOKUP($C$17,A132:P138,14)) -> 0 | D85: =IF(F85=0,0,E89+VLOOKUP($C$17,A132:P138,14)) -> 0 | E85: =VLOOKUP($C$17,A132:P138,15) -> 0 | F85: =VLOOKUP($C$17,A132:P138,16) -> 0 | J85: =IF(C85=0,0,(C85/100)*(D85/100)*F85) -> 0 | K85: =J85/0.8 -> 0 | L85: =IF(E85=0,0,VLOOKUP(E85,'Prix Matiere'!A4:J60,10)) -> 0 | M85: =L85*K85 -> 0 | N85: =IF(J85=0,0,(3.94*J85)+5) -> 0 | O85: =N85*MinuteMO -> 0 | Q85: =IF(J85=0,0,J85*VLOOKUP(E85,'Prix Matiere'!$A$4:$L$60,12)) -> 0 | R85: =IF(J85=0,0,Q85*VLOOKUP(E85,'Prix Matiere'!$A$4:$L$60,11)) -> 0
B86: Dessus dessous | C86: =IF(F86=0,0,C89+VLOOKUP($C$17,A132:P138,14)) -> 0 | D86: =IF(F86=0,0,D89) -> 0 | E86: =VLOOKUP($C$17,A132:P138,15) -> 0 | F86: =VLOOKUP($C$17,A132:P138,16) -> 0 | J86: =IF(C86=0,0,(C86/100)*(D86/100)*F86) -> 0 | K86: =J86/0.8 -> 0 | L86: =IF(E86=0,0,VLOOKUP(E86,'Prix Matiere'!A5:J61,10)) -> 0 | M86: =L86*K86 -> 0 | N86: =IF(J86=0,0,(3.94*J86)+5) -> 0 | O86: =N86*MinuteMO -> 0 | Q86: =IF(J86=0,0,J86*VLOOKUP(E86,'Prix Matiere'!$A$4:$L$60,12)) -> 0 | R86: =IF(J86=0,0,Q86*VLOOKUP(E86,'Prix Matiere'!$A$4:$L$60,11)) -> 0
B87: Bouts | C87: =IF(F87=0,0,E89) -> 0 | D87: =IF(F87=0,0,D89) -> 0 | E87: =VLOOKUP($C$17,A132:P138,15) -> 0 | F87: =VLOOKUP($C$17,A132:P138,16) -> 0 | J87: =IF(C87=0,0,(C87/100)*(D87/100)*F87) -> 0 | K87: =J87/0.8 -> 0 | L87: =IF(E87=0,0,VLOOKUP(E87,'Prix Matiere'!A6:J62,10)) -> 0 | M87: =L87*K87 -> 0 | N87: =IF(J87=0,0,(3.94*J87)+5) -> 0 | O87: =N87*MinuteMO -> 0 | Q87: =IF(J87=0,0,J87*VLOOKUP(E87,'Prix Matiere'!$A$4:$L$60,12)) -> 0 | R87: =IF(J87=0,0,Q87*VLOOKUP(E87,'Prix Matiere'!$A$4:$L$60,11)) -> 0
J88: =IF(C88=0,0,(C88/100)*(D88/100)*F88) -> 0 | K88: =J88/0.8 -> 0 | Q88: =IF(J88=0,0,J88*VLOOKUP(E88,'Prix Matiere'!$A$4:$L$60,12)) -> 0
B89: Dimensions intérieures styro | C89: =C83-VLOOKUP($C$17,A132:P138,14) -> 31.9 | D89: =D83-VLOOKUP($C$17,A132:P138,14) -> 31.5 | E89: =E83-VLOOKUP($C$17,A132:P138,14) -> 13.7 | J89: =IF(C89=0,0,(C89/100)*(D89/100)*F89) -> 0 | K89: =J89/0.8 -> 0 | Q89: =IF(J89=0,0,J89*VLOOKUP(E89,'Prix Matiere'!$A$4:$L$60,12)) -> 0
J90: =IF(C90=0,0,(C90/100)*(D90/100)*F90) -> 0 | K90: =J90/0.8 -> 0 | Q90: =IF(J90=0,0,J90*VLOOKUP(E90,'Prix Matiere'!$A$4:$L$60,12)) -> 0
B91: Mousse de calage | J91: =IF(C91=0,0,(C91/100)*(D91/100)*F91) -> 0 | K91: =J91/0.8 -> 0 | Q91: =IF(J91=0,0,J91*VLOOKUP(E91,'Prix Matiere'!$A$4:$L$60,12)) -> 0
B92: =IF(B31="Aucun",0,"Dessus") -> Dessus | C92: =IF(B31="Aucun",0,C89) -> 31.9 | D92: =IF(B31="Aucun",0,D29+VLOOKUP(B31,A161:L166,5)) -> 27.5 | E92: =VLOOKUP(B31,A161:L166,9) -> PU 50 mm | F92: =IF(B31="Aucun",0,1) -> 1 | J92: =IF(C92=0,0,(C92/100)*(D92/100)*F92) -> 0.087725 | K92: =J92/0.8 -> 0.10965625 | L92: =IF(E92=0,0,VLOOKUP(E92,'Prix Matiere'!$A$4:$J$65,10)) -> 9.5670103 | M92: =L92*K92 -> 1.0490825 | N92: =IF(J92=0,0,4.7283*J92+2) -> 2.4147901 | O92: =N92*MinuteMO -> 2.0525716 | Q92: =IF(J92=0,0,J92*VLOOKUP(E92,'Prix Matiere'!$A$4:$L$60,12)) -> 0.10965625 | R92: =IF(J92=0,0,Q92*VLOOKUP(E92,'Prix Matiere'!$A$4:$L$60,11)) -> 0.29607188
B93: =IF(B31="Aucun",0,"Extrémité") -> Extrémité | C93: =IF(B31="Aucun",0,IF(C29<60,10,IF(C29<80,15,20))) -> 10 | D93: =D92 -> 27.5 | E93: =VLOOKUP(B31,A161:L166,9) -> PU 50 mm | F93: =IF(B31="Aucun",0,2) -> 2 | J93: =IF(C93=0,0,(C93/100)*(D93/100)*F93) -> 0.055 | K93: =J93/0.8 -> 0.06875 | L93: =IF(E93=0,0,VLOOKUP(E93,'Prix Matiere'!$A$4:$J$65,10)) -> 9.5670103 | M93: =L93*K93 -> 0.65773196 | N93: =IF(J93=0,0,4.7283*J93+2) -> 2.2600565 | O93: =N93*MinuteMO -> 1.921048 | Q93: =IF(J93=0,0,J93*VLOOKUP(E93,'Prix Matiere'!$A$4:$L$60,12)) -> 0.06875 | R93: =IF(J93=0,0,Q93*VLOOKUP(E93,'Prix Matiere'!$A$4:$L$60,11)) -> 0.185625
B94: =IF(B31="Aucun",0,B35) -> Agglocelle 50 mm | C94: =C35 -> 6 | D94: =D93 -> 27.5 | E94: =IF(B31="Aucun",0,IF(B94="Ethafoam 50 mm","Ethafoam 50 mm","Agglocelle 50 mm")) -> Agglocelle 50 mm | F94: =F35 -> 2 | J94: =IF(C94=0,0,(C94/100)*(D94/100)*F94) -> 0.033 | K94: =J94/0.8 -> 0.04125 | L94: =IF(E94=0,0,VLOOKUP(E94,'Prix Matiere'!$A$4:$J$65,10)) -> 20.325783 | M94: =L94*K94 -> 0.83843856 | N94: =IF(J94=0,0,4.7283*J94+2) -> 2.1560339 | O94: =N94*MinuteMO -> 1.8326288 | Q94: =IF(J94=0,0,J94*VLOOKUP(E94,'Prix Matiere'!$A$4:$L$60,12)) -> 0.10725 | R94: =IF(J94=0,0,Q94*VLOOKUP(E94,'Prix Matiere'!$A$4:$L$60,11)) -> 0.33033
B95: =IF(B31="Aucun",0,"Milieu") -> Milieu | C95: =(C92-((C93*F93)+(C94*F94)))/(F94-1) -> -0.1 | D95: =D94 -> 27.5 | E95: =VLOOKUP(B31,A161:L166,9) -> PU 50 mm | F95: =IF(B31="Aucun",0,F94-1) -> 1 | J95: =IF(C95=0,0,(C95/100)*(D95/100)*F95) -> -0.000275 | K95: =J95/0.8 -> -0.00034375 | L95: =IF(E95=0,0,VLOOKUP(E95,'Prix Matiere'!$A$4:$J$65,10)) -> 9.5670103 | M95: =L95*K95 -> -0.0032886598 | N95: =IF(J95=0,0,4.7283*J95+2) -> 1.9986997 | O95: =N95*MinuteMO -> 1.6988948 | Q95: =IF(J95=0,0,J95*VLOOKUP(E95,'Prix Matiere'!$A$4:$L$60,12)) -> -0.00034375 | R95: =IF(J95=0,0,Q95*VLOOKUP(E95,'Prix Matiere'!$A$4:$L$60,11)) -> -0.000928125
B96: =IF(B31="Aucun",0,"Bouts avec passage de main") -> Bouts avec passage de main | C96: =IF(B31="Aucun",0,(E29-IF(E29>120,30,15))/(F96/2)) -> -5.75 | D96: =D95 -> 27.5 | E96: =VLOOKUP(B31,A161:L166,9) -> PU 50 mm | F96: =IF(B31="Aucun",0,IF(E29>120,6,4)) -> 4 | J96: =IF(C96=0,0,(C96/100)*(D96/100)*F96) -> -0.06325 | K96: =J96/0.8 -> -0.0790625 | L96: =IF(E96=0,0,VLOOKUP(E96,'Prix Matiere'!$A$4:$J$65,10)) -> 9.5670103 | M96: =L96*K96 -> -0.75639175 | N96: =IF(J96=0,0,4.7283*J96+2) -> 1.700935 | O96: =N96*MinuteMO -> 1.4457948 | Q96: =IF(J96=0,0,J96*VLOOKUP(E96,'Prix Matiere'!$A$4:$L$60,12)) -> -0.0790625 | R96: =IF(J96=0,0,Q96*VLOOKUP(E96,'Prix Matiere'!$A$4:$L$60,11)) -> -0.21346875
B97: =IF(B31="Aucun",0,"Fond") -> Fond | C97: =IF(B31="Aucun",0,C29+VLOOKUP(B31,A161:L166,6)) -> 21.9 | D97: =IF(B31="Sous verre 2 faces",E29+VLOOKUP(B31,A161:L166,6),C34) -> 10 | E97: =VLOOKUP(B31,A161:L166,8) -> PU 50 mm | F97: =VLOOKUP(B31,A161:L166,7) -> 2 | J97: =IF(C97=0,0,(C97/100)*(D97/100)*F97) -> 0.0438 | K97: =J97/0.8 -> 0.05475 | L97: =IF(E97=0,0,VLOOKUP(E97,'Prix Matiere'!$A$4:$J$65,10)) -> 9.5670103 | M97: =L97*K97 -> 0.52379381 | N97: =IF(J97=0,0,4.7283*J97+2) -> 2.2070995 | O97: =N97*MinuteMO -> 1.8760346 | Q97: =IF(J97=0,0,J97*VLOOKUP(E97,'Prix Matiere'!$A$4:$L$60,12)) -> 0.05475 | R97: =IF(J97=0,0,Q97*VLOOKUP(E97,'Prix Matiere'!$A$4:$L$60,11)) -> 0.147825
B98: =IF(B31="Aucun",0,"Remplis de fond") -> Remplis de fond | C98: =IF(B31="Aucun",0,IF(B31="Sous verre 2 faces",0,E29-D97*2+VLOOKUP(B31,A161:L166,6))) -> -16.3 | D98: =IF(B31="Sous verre 2 faces",0,C34) -> 10 | E98: =IF(C98=0,0,VLOOKUP(B31,A161:L166,8)) -> PU 50 mm | F98: =IF(B31="Aucun",0,IF(B31="Sous verre 2 faces",0,2)) -> 2 | J98: =IF(C98=0,0,(C98/100)*(D98/100)*F98) -> -0.0326 | K98: =J98/0.8 -> -0.04075 | L98: =IF(E98=0,0,VLOOKUP(E98,'Prix Matiere'!$A$4:$J$65,10)) -> 9.5670103 | M98: =L98*K98 -> -0.38985567 | N98: =IF(J98=0,0,4.7283*J98+2) -> 1.8458574 | O98: =N98*MinuteMO -> 1.5689788 | Q98: =IF(J98=0,0,J98*VLOOKUP(E98,'Prix Matiere'!$A$4:$L$60,12)) -> -0.04075 | R98: =IF(J98=0,0,Q98*VLOOKUP(E98,'Prix Matiere'!$A$4:$L$60,11)) -> -0.110025
B99: =IF(B31="Aucun",0,"Dessus") -> Dessus | C99: =IF(B31="Aucun",0,C29+VLOOKUP(B31,A161:L166,10)) -> 21.2 | D99: =IF(B31="Sous verre 2 faces",E29+VLOOKUP(B31,A161:L166,10),IF(B31="Sous verre / bandes de mousse",E29+VLOOKUP(B31,A161:L166,10),C33)) -> 10 | E99: =VLOOKUP(B31,A161:L166,9) -> PU 50 mm | F99: =VLOOKUP(B31,A161:L166,11) -> 2 | J99: =IF(C99=0,0,(C99/100)*(D99/100)*F99) -> 0.0424 | K99: =J99/0.8 -> 0.053 | L99: =IF(E99=0,0,VLOOKUP(E99,'Prix Matiere'!$A$4:$J$65,10)) -> 9.5670103 | M99: =L99*K99 -> 0.50705155 | N99: =IF(J99=0,0,4.7283*J99+2) -> 2.2004799 | O99: =N99*MinuteMO -> 1.8704079 | Q99: =IF(J99=0,0,J99*VLOOKUP(E99,'Prix Matiere'!$A$4:$L$60,12)) -> 0.053 | R99: =IF(J99=0,0,Q99*VLOOKUP(E99,'Prix Matiere'!$A$4:$L$60,11)) -> 0.1431
B100: =IF(B31="Aucun",0,"Remplis de dessus") -> Remplis de dessus | C100: =IF(B31="Aucun",0,IF(B31="Sous verre 2 faces",0,IF(B31="Sous verre / bandes de mousse",0,E29-2*D99+VLOOKUP(B31,A161:L166,10)))) -> -17 | D100: =IF(B31="Sous verre / bandes de mousse",0,IF(B31="Sous verre 2 faces",0,C33)) -> 10 | E100: =IF(C100=0,0,VLOOKUP(B31,A161:L166,9)) -> PU 50 mm | F100: =IF(B31="Aucun",0,IF(B31="Sous verre 2 faces",0,IF(B31="Sous verre / bandes de mousse",0,2))) -> 2 | J100: =IF(C100=0,0,(C100/100)*(D100/100)*F100) -> -0.034 | K100: =J100/0.8 -> -0.0425 | L100: =IF(E100=0,0,VLOOKUP(E100,'Prix Matiere'!$A$4:$J$65,10)) -> 9.5670103 | M100: =L100*K100 -> -0.40659794 | N100: =IF(J100=0,0,4.7283*J100+2) -> 1.8392378 | O100: =N100*MinuteMO -> 1.5633521 | Q100: =IF(J100=0,0,J100*VLOOKUP(E100,'Prix Matiere'!$A$4:$L$60,12)) -> -0.0425 | R100: =IF(J100=0,0,Q100*VLOOKUP(E100,'Prix Matiere'!$A$4:$L$60,11)) -> -0.11475
B101: =IF(B31="Sous verre 2 faces",0,IF(B31="Aucun",0,"PU 20 mm")) -> PU 20 mm | C101: =IF(B101=0,0,C89) -> 31.9 | D101: =IF(B101=0,0,E89) -> 13.7 | E101: =B101 -> PU 20 mm | F101: =IF(B31="Sous verre 2 faces",0,IF(B31="Aucun",0,IF(B31="Sous verre / bandes de mousse",1,2))) -> 2 | J101: =IF(C101=0,0,(C101/100)*(D101/100)*F101) -> 0.087406 | K101: =J101/0.8 -> 0.1092575 | L101: =IF(E101=0,0,VLOOKUP(E101,'Prix Matiere'!$A$4:$J$65,10)) -> 5.3924872 | M101: =L101*K101 -> 0.58916967 | N101: =IF(J101=0,0,4.7283*J101+2) -> 2.4132818 | O101: =N101*MinuteMO -> 2.0512895 | Q101: =IF(J101=0,0,J101*VLOOKUP(E101,'Prix Matiere'!$A$4:$L$60,12)) -> 0.043703 | R101: =IF(J101=0,0,Q101*VLOOKUP(E101,'Prix Matiere'!$A$4:$L$60,11)) -> 0.1179981
B102: =IF(B31="Aucun",0,"Rattrapage 1") -> Rattrapage 1 | C102: =IF(C36=0,0,C29+0.2) -> 0 | D102: =IF(C36=0,0,C36) -> 0 | E102: =IF(C102=0,0,CONCATENATE("PU ",$E$36*10," mm")) -> 0 | F102: =IF(C36=0,0,2) -> 0 | J102: =IF(C102=0,0,(C102/100)*(D102/100)*F102) -> 0 | K102: =J102/0.8 -> 0 | L102: =IF(E102=0,0,VLOOKUP(E102,'Prix Matiere'!$A$4:$J$65,10)) -> 0 | M102: =L102*K102 -> 0 | N102: =IF(J102=0,0,4.7283*J102+2) -> 0 | O102: =N102*MinuteMO -> 0 | Q102: =IF(J102=0,0,J102*VLOOKUP(E102,'Prix Matiere'!$A$4:$L$60,12)) -> 0 | R102: =IF(J102=0,0,Q102*VLOOKUP(E102,'Prix Matiere'!$A$4:$L$60,11)) -> 0
B103: =IF(B31="Aucun",0,"Rattrapage 2") -> Rattrapage 2 | C103: =IF(C36=0,0,E29+0.2-2*D102) -> 0 | D103: =IF(C28=0,0,D102) -> 0 | E103: =IF(C103=0,0,CONCATENATE("PU ",$E$36*10," mm")) -> 0 | F103: =IF(C36=0,0,2) -> 0 | J103: =IF(C103=0,0,(C103/100)*(D103/100)*F103) -> 0 | K103: =J103/0.8 -> 0 | L103: =IF(E103=0,0,VLOOKUP(E103,'Prix Matiere'!$A$4:$J$65,10)) -> 0 | M103: =L103*K103 -> 0 | N103: =IF(J103=0,0,4.7283*J103+2) -> 0 | O103: =N103*MinuteMO -> 0 | Q103: =IF(J103=0,0,J103*VLOOKUP(E103,'Prix Matiere'!$A$4:$L$60,12)) -> 0 | R103: =IF(J103=0,0,Q103*VLOOKUP(E103,'Prix Matiere'!$A$4:$L$60,11)) -> 0
B104: =IF(B31="Aucun",0,"Remplissage 1") -> Remplissage 1 | C104: =IF(C38=0,0,C38) -> 0 | D104: =IF(D38=0,0,D38) -> 0 | E104: =IF(C104=0,0,CONCATENATE("PU ",$E$38*10," mm")) -> 0 | F104: =IF(C38=0,0,1) -> 0 | J104: =IF(C104=0,0,(C104/100)*(D104/100)*F104) -> 0 | K104: =J104/0.8 -> 0 | L104: =IF(E104=0,0,VLOOKUP(E104,'Prix Matiere'!$A$4:$J$65,10)) -> 0 | M104: =L104*K104 -> 0 | N104: =IF(J104=0,0,4.7283*J104+2) -> 0 | O104: =N104*MinuteMO -> 0 | Q104: =IF(J104=0,0,J104*VLOOKUP(E104,'Prix Matiere'!$A$4:$L$60,12)) -> 0 | R104: =IF(J104=0,0,Q104*VLOOKUP(E104,'Prix Matiere'!$A$4:$L$60,11)) -> 0
B105: =IF(B31="Aucun",0,"Remplissage 2") -> Remplissage 2 | C105: =IF(C39=0,0,C39) -> 0 | D105: =IF(D39=0,0,D39) -> 0 | E105: =IF(C105=0,0,CONCATENATE("PU ",$E$39*10," mm")) -> 0 | F105: =IF(C39=0,0,1) -> 0 | J105: =IF(C105=0,0,(C105/100)*(D105/100)*F105) -> 0 | K105: =J105/0.8 -> 0 | L105: =IF(E105=0,0,VLOOKUP(E105,'Prix Matiere'!$A$4:$J$65,10)) -> 0 | M105: =L105*K105 -> 0 | N105: =IF(J105=0,0,4.7283*J105+2) -> 0 | O105: =N105*MinuteMO -> 0 | Q105: =IF(J105=0,0,J105*VLOOKUP(E105,'Prix Matiere'!$A$4:$L$60,12)) -> 0 | R105: =IF(J105=0,0,Q105*VLOOKUP(E105,'Prix Matiere'!$A$4:$L$60,11)) -> 0
B106: =IF(B31="Aucun",0,"Carton") -> Carton | C106: =IF(F106=0,0,C29+VLOOKUP(B31,A161:L166,10)) -> 21.2 | D106: =IF(F106=0,0,E29+VLOOKUP(B31,A159:L167,10)) -> 3 | E106: =IF(C106=0,0,"Carton") -> Carton | F106: =VLOOKUP(B31,A161:L166,12) -> 1 | J106: =IF(C106=0,0,(C106/100)*(D106/100)*F106) -> 0.00636 | K106: =J106/0.8 -> 0.00795 | L106: =IF(E106=0,0,Carton) -> 2.324775 | M106: =L106*K106 -> 0.018481961 | N106: =IF(J106=0,0,2.356*J106+1) -> 1.0149842 | O106: =N106*MinuteMO -> 0.86273654 | Q106: =IF(J106=0,0,J106*VLOOKUP(E106,'Prix Matiere'!$A$4:$L$60,12)) -> 0.0636 | R106: =IF(J106=0,0,Q106*VLOOKUP(E106,'Prix Matiere'!$A$4:$L$60,11)) -> 0.0307824
O107: =N107*MinuteMO -> 0
A108: Option | B108: =IF(F23="Aucun"," ",F23) | M108: =VLOOKUP($F$23,$A$150:$D$153,3) -> 0 | N108: =IF(M108=0,0,12.5) -> 0 | O108: =N108*MinuteMO -> 0
A109: Tyvek | B109: =IF($F$21="Oui","Tyvek",0) -> 0 | K109: =IF(B109="Tyvek",SUM(K92:K105)/0.7,0) -> 0 | L109: =IF(B109=0,0,2.75) -> 0 | M109: =K109*L109 -> 0 | N109: =IF(K109=0,0,7*K109+2) -> 0 | O109: =N109*MinuteMO -> 0 | Q109: =IF(K109=0,0,K109*VLOOKUP(B109,'Prix Matiere'!$A$4:$L$60,12)) -> 0 | R109: =IF(K109=0,0,Q109*VLOOKUP(B109,'Prix Matiere'!$A$4:$L$60,11)) -> 0
A110: Peinture | B110: =IF(F19="Non",0,"Peinture") -> 0 | J110: =IF(B110=0,0,(((C43/100)*(D43/100))+((C43/100)*(E43/100))+((D43/100)*(E43/100)))*2) -> 0 | K110: =J110*0.5 -> 0 | L110: =IF(B110=0,0,VLOOKUP(B110,'Prix Matiere'!$A$4:$J$60,10)) -> 0 | M110: =K110*L110 -> 0 | N110: =IF(J110=0,0,IF(B110="Peinture",30+J110*15)) -> 0 | O110: =N110*MinuteMO -> 0 | Q110: =IF(J110=0,0,J110*VLOOKUP(B110,'Prix Matiere'!$A$4:$L$60,12)) -> 0 | R110: =IF(J110=0,0,Q110*VLOOKUP(B110,'Prix Matiere'!$A$4:$L$60,11)) -> 0
A111: Fermetures | B111: =C19 -> Vis bois | M111: =IF(B111="Vis bois",0,(F4*2+F6*2)*1.5) -> 0 | N111: =IF(B111="Vis bois",0,45) -> 0 | O111: =N111*MinuteMO -> 0 | R111: =IF(J111=0,0,Q111*VLOOKUP(E111,'Prix Matiere'!$A$4:$L$60,11)) -> 0
A112: Poignées | B112: =C21 -> Bois | M112: =IF(B112="Métal x 4 sur GC",4*2,IF(B112="Métal x 2 sur bouts",2*2,0)) -> 0 | N112: =IF(B112="Métal x 4 sur GC",4*3,IF(B112="Métal x 2 sur bouts",2*3,0)) -> 0 | O112: =N112*MinuteMO -> 0 | R112: =IF(J112=0,0,Q112*VLOOKUP(E112,'Prix Matiere'!$A$4:$L$60,11)) -> 0
L114: =IF(E114=0,0,VLOOKUP(E114,'Prix Matiere'!$A$4:$J$65,10)) -> 0 | M114: =SUM(M54:M113) -> 45.351229 | N114: =SUM(N54:N113) -> 104.25419 | O114: =N114*MinuteMO -> 88.616064 | Q114: =SUM(Q54:Q106) -> 13.167892 | R114: =SUM(R54:R106) -> 10.759756
B115: Total matière | C115: =IF($F$9=0,0,M114) -> 45.351229 | E115: Contreplaqué | F115: =CONCATENATE(ROUNDUP(SUM(K54:K56)+SUM(K80:K81),2)," m²") -> 1,14 m² | G115: =(SUM(M54:M56)+SUM(M80:M81)) -> 19.170019
B116: Total MO | C116: =IF($F$9=0,0,O114) -> 88.616064 | D116: =IF($F$9=0,0,N114) -> 104.25419 | E116: Bois massif | F116: =CONCATENATE(ROUNDUP(SUM(K59:K65),2)," m²") -> 0,76 m² | G116: =(SUM(M59:M65)) -> 16.561417
B117: Total frais généraux | C117: =IF($F$9=0,0,((C115+C116)/Frais_Généraux)-(C115+C116)) -> 72.136235 | E117: Polystyrène extrudé | F117: =CONCATENATE(ROUNDUP(SUM(K74:K76)+SUM(K85:K87),2)," m²") -> 0,68 m² | G117: =(SUM(M74:M76)+SUM(M85:M87)) -> 6.9921772
B118: Total revient | C118: =IF($F$9=0,0,SUM(C115:C117)) -> 206.10353 | E118: Mousse | F118: =CONCATENATE(ROUNDUP(SUM(K68:K70)+SUM(K92:K105),2)," m²") -> 0,28 m² | G118: =(SUM(M68:M70)+SUM(M92:M105)) -> 2.609134
B119: Marge | C119: =IF($F$9=0,0,(C118/(1-Marge)-C118)) -> 15.513169 | D119: =C118+C119 -> 221.6167 | E119: Carton | F119: =CONCATENATE(ROUNDUP(K106,2)," m²") -> 0,01 m² | G119: =(M106) -> 0.018481961
B120: Remise (-) ou Majoration (+) en % | C120: =IF($F$10="BOVIS",((C118+C119)*(1+C121))-(C118+C119),((C118+C119)*(1+D120))-(C118+C119)) -> 0
...

Sheet T1-T6 LOUVRE
A1: Caisse Tableau Louvre de 2 à 6 Oeuvres
E3: =IF(C19="Boulons et platines","Boulons et Platines",0) -> 0 | F3: =IF(E3="Boulons et Platines","Nbre de Trous",0) -> 0 | G3: =IF(E3="Boulons et Platines","Dim du Bord",0) -> 0
E4: =IF(C19="Vis bois",0,"Trous dans la Longueur") -> 0 | F4: =IF(E4=0,0,IF(C91<100,2,IF(C91<150,3,IF(C91<200,4,IF(C91<250,5,IF(C91<300,6,7)))))) -> 0 | G4: =IF(F4=0,0,IF(F4=3,0,(($C$91-32)/(F4-1))+16)) -> 0
E5: =IF(F4=6,"2ème Trou",IF(F4=7,"2ème Trou",0)) -> 0 | G5: =IF(E5=0,0,G4+G4-16) -> 0
E6: =IF(C19="Vis bois",0,"Trous dans la Hauteur") -> 0 | F6: =IF(E6=0,0,IF(D91<100,2,IF(D91<150,3,IF(D91<200,4,IF(D91<250,5,IF(D91<310,6,7)))))) -> 0 | G6: =IF(F6=0,0,IF(F6=3,0,(($D$91-32)/(F6-1))+16)) -> 0
E7: =IF(F6=6,"2ème Trou",IF(F6=7,"2ème Trou",0)) -> 0 | G7: =IF(E7=0,0,G6+G6-16) -> 0
B9: N° de dossier | E9: Responsable Dossier
B10: Ville de destination | E10: Client | F10: ESI
B11: N° de caisse | E11: Délai
B13: Type de Contreplaqué | C13: Peuplier 15 mm
B15: Barres | C15: Pin raboté 4 faces | E15: Garnissage | F15: Valsem | I15: =VLOOKUP($F$10,'Infos Clients'!$B$2:$G$10,2) -> #VALUE!
B17: Type d'isolant | C17: Aucun
B19: Fermeture | C19: Vis bois | E19: Peinture | F19: Non
E20: =IF(F19="Oui","Type de Peinture",0) -> 0 | F20: =IF(F19="Non",0,VLOOKUP(F10,'Infos Clients'!B2:E10,4)) -> 0
B21: Poignées | C21: Bois | E21: Tyvek | F21: Non
B23: Skis | C23: Skis en 30 mm | E23: Option Calage | F23: Aucun
B25: =IF(F23="Aucun"," ",F23) | D25: =IF(F21="Oui","+",0) -> 0 | E25: =IF(F21="Oui","Mousse Garnie Tyvek",0) -> 0
